Workbook

Sheet 0_Легенда
A1: МОДЕЛЬ ПО ШАГАМ v1.1: вкладка = шаг расчёта; результаты шагов передаются в симуляцию (шаг 12). v1.1: поля каталога «класс задачи / способ обработки / допуск в помещения», замещение по паре задача×способ
A2: Переключите объект в жёлтой ячейке — все шаги пересчитаются. Синие ячейки — ввод; чёрные — формулы.
A4: Выбранный объект: | B4: Склад
A6: Сценарии по объектам (решение A / решение B — коды листа 1c_Каталог):
A7: Объект | B7: Решение A | C7: Решение B | D7: Процесс
A8: Склад | B8: DMR-CARRIER-P | C8: RONAVI-H1500 | D8: перемещение паллет док ↔ хранение
A9: Аэропорт | B9: COGNITIVE-TUG | C9: EVOCARGO-N1 | D9: перевозка багажа перрон ↔ терминал
A10: Медучреждение | B10: RONAVI-M | C10: MOROS-AMR800 | D10: транспортировка тележек: питание, бельё, отходы, расходники
A12: Решение A (выбрано): | B12: =INDEX(B8:B10,MATCH(SEL_OBJ,A8:A10,0)) -> DMR-CARRIER-P
A13: Решение B (выбрано): | B13: =INDEX(C8:C10,MATCH(SEL_OBJ,A8:A10,0)) -> RONAVI-H1500
A14: Процесс: | B14: =INDEX(D8:D10,MATCH(SEL_OBJ,A8:A10,0)) -> перемещение паллет док ↔ хранение
A16: Типы происхождения параметров (столбец «Тип» на каждом шаге):
A17: СЫРОЙ — датасет | B17: значение взято как есть из Датасеты_хакатон.xlsx (лист объекта)
A18: СЫРОЙ — каталог CSV | B18: значение из catalog_export_v4.csv: цена (с НДС, без доставки/ПНР), статус, УГТ
A19: СЫРОЙ — docx ТТХ | B19: ТТХ из Примеры_решений_типы_объектов.docx (или описаний каталога); неподтверждённые помечены на 1c_Каталог
A20: НОРМАТИВ — организатор | B20: норматив из легенды датасета / ТЗ / Дополнений (ФОТ 1.302, загрузка 80%, резерв 15%, резерв CAPEX 10%, АКБ 4 года)
A21: ДОПУЩЕНИЕ — команда | B21: коэффициент команды с обоснованием; подлежит изменению пользователем (ТЗ 3.5.3)
A22: ПРЕДПОСЧИТАН — шаг N | B22: рассчитан формулой на шаге N; сюда попадает ссылкой, не вводится
A24: Конвейер шагов:
A25: 1_Сырые_данные | B25: Параметры объекта из датасета (три объекта в столбцах; выбранный — формулой)
A26: 1b_Нормативы | B26: Глобальные нормативы и допущения
A27: 1c_Каталог | B27: Решения: цены (CSV) + ТТХ (docx) + допущения по решению
A28: 2_Процесс | B28: Предпосчёт параметров процесса из сырых данных (объём, пик, масса единицы, маршрут, целевой ФОТ)
A29: 3_Решение_фильтры | B29: Подтягивание ТТХ выбранных решений и проверка применимости
A30: 4_Потребность | B30: Пиковая потребность в рейсах робота
A31: 5_Парк | B31: Цикл рейса, эффективная производительность, количество роботов и станций
A32: 6_База | B32: Базовый сценарий без роботизации
A33: 7_CAPEX | B33: Капитальные затраты по статьям
A34: 8_OPEX | B34: Операционные затраты решения
A35: 9_Эффект | B35: Эффект, окупаемость, ROI, TCO, интерпретация, риски
A36: 10_ДенПоток | B36: Денежный поток по годам, NPV, IRR, дисконтированная окупаемость
... A39: 13_Итог | B39: Сводка по выбранному объекту

Sheet 1_Сырые_данные
A1: ШАГ 1. СЫРЫЕ ДАННЫЕ ОБЪЕКТА (Датасеты_хакатон.xlsx) — вход конвейера
A2: Столбцы D–F — базовые значения датасета по трём объектам (синие = сырой ввод); столбец G — значение выбранного объекта (формула). Пусто = параметр не применяется к объекту.
A4: Код | B4: Параметр | C4: Ед. | D4: Склад | E4: Аэропорт | F4: Медучреждение | G4: Выбрано (SEL_OBJ) | H4: Тип | I4: Источник (лист датасета / примечание)
A5: S_total | B5: Общая площадь объекта / здания | C5: м² | D5: 20000 | E5: 85000 | F5: 45000 | G5: =INDEX(D5:F5,MATCH(SEL_OBJ,$D$4:$F$4,0)) -> 20000 | H5: СЫРОЙ — датасет | I5: Склад: общая площадь; Аэропорт: площадь терминалов; Мед: площадь зданий
A6: S_active | B6: Площадь активной (роботизируемой) зоны / перрона | C6: м² | D6: 10000 | E6: 100000 | G6: =INDEX(D6:F6,MATCH(SEL_OBJ,$D$4:$F$4,0)) -> 10000 | H6: СЫРОЙ — датасет | I6: Склад: активная зона 50%; Аэропорт: перрон и техзоны
A7: aisle_main | B7: Ширина главных проездов | C7: м | D7: 3.5 | G7: =INDEX(D7:F7,MATCH(SEL_OBJ,$D$4:$F$4,0)) -> 3.5 | H7: СЫРОЙ — датасет | I7: Склад
A8: aisle_rack | B8: Ширина рабочих проходов между стеллажами | C8: м | D8: 2.8 | G8: =INDEX(D8:F8,MATCH(SEL_OBJ,$D$4:$F$4,0)) -> 2.8 | H8: СЫРОЙ — датасет | I8: Склад
A9: corridor | B9: Ширина коридоров (основных) | C9: м | F9: 2.4 | G9: =INDEX(D9:F9,MATCH(SEL_OBJ,$D$4:$F$4,0)) -> 0 | H9: СЫРОЙ — датасет | I9: Мед
A10: floors | B10: Этажей | C10: шт. | D10: 1 | F10: 9 | G10: =INDEX(D10:F10,MATCH(SEL_OBJ,$D$4:$F$4,0)) -> 1 | H10: СЫРОЙ — датасет | I10: Склад: мезонины; Мед: основной корпус
A11: lifts | B11: Лифтов | C11: шт. | F11: 4 | G11: =INDEX(D11:F11,MATCH(SEL_OBJ,$D$4:$F$4,0)) -> 0 | H11: СЫРОЙ — датасет | I11: Мед
A12: shifts | B12: Смен в сутки | C12: смен | D12: 2 | F12: 3 | G12: =INDEX(D12:F12,MATCH(SEL_OBJ,$D$4:$F$4,0)) -> 2 | H12: СЫРОЙ — датасет | I12: Склад; Мед: смены медперсонала
A13: shift_h | B13: Продолжительность смены | C13: ч | D13: 11 | G13: =INDEX(D13:F13,MATCH(SEL_OBJ,$D$4:$F$4,0)) -> 11 | H13: СЫРОЙ — датасет | I13: Склад (с учётом перерывов)
A14: peak_k | B14: Пиковый коэффициент нагрузки | C14: коэф. | D14: 1.5 | G14: =INDEX(D14:F14,MATCH(SEL_OBJ,$D$4:$F$4,0)) -> 1.5 | H14: СЫРОЙ — датасет | I14: Склад (макс. час / средний час)
A15: in_pallets | B15: Объём приёмки | C15: поддон/сут | D15: 1000 | G15: =INDEX(D15:F15,MATCH(SEL_OBJ,$D$4:$F$4,0)) -> 1000 | H15: СЫРОЙ — датасет | I15: Склад
A16: out_pallets | B16: Объём отгрузки | C16: поддон/сут | D16: 1000 | G16: =INDEX(D16:F16,MATCH(SEL_OBJ,$D$4:$F$4,0)) -> 1000 | H16: СЫРОЙ — датасет | I16: Склад
A17: pallet_mass | B17: Средняя масса паллета | C17: кг | D17: 800 | G17: =INDEX(D17:F17,MATCH(SEL_OBJ,$D$4:$F$4,0)) -> 800 | H17: СЫРОЙ — датасет | I17: Склад
A18: oversize_share | B18: Доля негабаритных грузов | C18: доля | D18: 0.05 | G18: =INDEX(D18:F18,MATCH(SEL_OBJ,$D$4:$F$4,0)) -> 0.05 | H18: СЫРОЙ — датасет | I18: Склад (остаётся ручным)
A19: flights_day | B19: Рейсов в сутки (взлёт+посадка) | C19: рейсов/сут | E19: 280 | G19: =INDEX(D19:F19,MATCH(SEL_OBJ,$D$4:$F$4,0)) -> 0 | H19: СЫРОЙ — датасет | I19: Аэропорт
A20: flights_peak_h | B20: Пиковых рейсов в час | C20: рейсов/ч | E20: 32 | G20: =INDEX(D20:F20,MATCH(SEL_OBJ,$D$4:$F$4,0)) -> 0 | H20: СЫРОЙ — датасет | I20: Аэропорт
A21: bags_day | B21: Багажа в сутки | C21: ед./сут | E21: 35000 | G21: =INDEX(D21:F21,MATCH(SEL_OBJ,$D$4:$F$4,0)) -> 0 | H21: СЫРОЙ — датасет | I21: Аэропорт
A22: bag_mass | B22: Масса единицы багажа | C22: кг | E22: 18 | G22: =INDEX(D22:F22,MATCH(SEL_OBJ,$D$4:$F$4,0)) -> 0 | H22: СЫРОЙ — датасет | I22: Аэропорт
A23: temp_min_ds | B23: Температура в неотапливаемых зонах (зима) | C23: °C | E23: -25 | G23: =INDEX(D23:F23,MATCH(SEL_OBJ,$D$4:$F$4,0)) -> 0 | H23: СЫРОЙ — датасет | I23: Аэропорт (перрон)
A24: feedings | B24: Кормлений в сутки | C24: раз/сут | F24: 3 | G24: =INDEX(D24:F24,MATCH(SEL_OBJ,$D$4:$F$4,0)) -> 0 | H24: СЫРОЙ — датасет | I24: Мед
A25: food_points | B25: Точек раздачи питания | C25: шт. | F25: 18 | G25: =INDEX(D25:F25,MATCH(SEL_OBJ,$D$4:$F$4,0)) -> 0 | H25: СЫРОЙ — датасет | I25: Мед
A26: L_food | B26: Расстояние пищеблок → отделение | C26: м | F26: 180 | G26: =INDEX(D26:F26,MATCH(SEL_OBJ,$D$4:$F$4,0)) -> 0 | H26: СЫРОЙ — датасет | I26: Мед
A27: cart_mass | B27: Масса тележки с питанием | C27: кг | F27: 120 | G27: =INDEX(D27:F27,MATCH(SEL_OBJ,$D$4:$F$4,0)) -> 0 | H27: СЫРОЙ — датасет | I27: Мед
A28: linen_points | B28: Точек сбора/выдачи белья | C28: шт. | F28: 18 | G28: =INDEX(D28:F28,MATCH(SEL_OBJ,$D$4:$F$4,0)) -> 0 | H28: СЫРОЙ — датасет | I28: Мед
A29: linen_freq | B29: Периодичность смены белья | C29: раз/сут | F29: 1.3 | G29: =INDEX(D29:F29,MATCH(SEL_OBJ,$D$4:$F$4,0)) -> 0 | H29: СЫРОЙ — датасет | I29: Мед
A30: linen_mass | B30: Масса контейнера с бельём | C30: кг | F30: 55 | G30: =INDEX(D30:F30,MATCH(SEL_OBJ,$D$4:$F$4,0)) -> 0 | H30: СЫРОЙ — датасет | I30: Мед
A31: supplies_trips | B31: Доставка расходников | C31: рейсов/сут | F31: 45 | G31: =INDEX(D31:F31,MATCH(SEL_OBJ,$D$4:$F$4,0)) -> 0 | H31: СЫРОЙ — датасет | I31: Мед
A32: waste_points | B32: Точек сбора отходов | C32: шт. | F32: 20 | G32: =INDEX(D32:F32,MATCH(SEL_OBJ,$D$4:$F$4,0)) -> 0 | H32: СЫРОЙ — датасет | I32: Мед
A33: waste_freq | B33: Периодичность вывоза отходов | C33: раз/сут | F33: 2 | G33: =INDEX(D33:F33,MATCH(SEL_OBJ,$D$4:$F$4,0)) -> 0 | H33: СЫРОЙ — датасет | I33: Мед
A34: g1_n | B34: Целевая группа персонала 1 — численность | C34: чел. | D34: 25 | E34: 320 | F34: 65 | G34: =INDEX(D34:F34,MATCH(SEL_OBJ,$D$4:$F$4,0)) -> 25 | H34: СЫРОЙ — датасет | I34: Склад: операторы погрузчиков; Аэропорт: персонал рампа; Мед: санитары/транспортировщики
A35: g1_sal | B35: Целевая группа 1 — оклад gross | C35: руб./мес. | D35: 120000 | E35: 100000 | F35: 55000 | G35: =INDEX(D35:F35,MATCH(SEL_OBJ,$D$4:$F$4,0)) -> 120000 | H35: СЫРОЙ — датасет | I35: Датасет
A36: g2_n | B36: Целевая группа 2 — численность | C36: чел. | F36: 28 | G36: =INDEX(D36:F36,MATCH(SEL_OBJ,$D$4:$F$4,0)) -> 0 | H36: СЫРОЙ — датасет | I36: Мед: пищеблок (раздача)
A37: g2_sal | B37: Целевая группа 2 — оклад gross | C37: руб./мес. | F37: 52000 | G37: =INDEX(D37:F37,MATCH(SEL_OBJ,$D$4:$F$4,0)) -> 0 | H37: СЫРОЙ — датасет | I37: Мед
A38: g3_n | B38: Целевая группа 3 — численность | C38: чел. | F38: 18 | G38: =INDEX(D38:F38,MATCH(SEL_OBJ,$D$4:$F$4,0)) -> 0 | H38: СЫРОЙ — датасет | I38: Мед: прачечная (транспорт белья)
A39: loss_k_ds | B39: Коэффициент потерь рабочего времени | C39: доля | D39: 0.25 | G39: =INDEX(D39:F39,MATCH(SEL_OBJ,$D$4:$F$4,0)) -> 0.25 | H39: СЫРОЙ — датасет | I39: Склад (отпуск, болезнь, текучесть)
A40: turnover_ds | B40: Годовая текучесть персонала | C40: доля | E40: 0.35 | F40: 0.45 | G40: =INDEX(D40:F40,MATCH(SEL_OBJ,$D$4:$F$4,0)) -> 0 | H40: СЫРОЙ — датасет | I40: Аэропорт: персонал терминала; Мед: немедицинский персонал
A41: power_kw | B41: Доступная мощность для зарядной инфраструктуры | C41: кВт | D41: 500 | E41: 300 | F41: 80 | G41: =INDEX(D41:F41,MATCH(SEL_OBJ,$D$4:$F$4,0)) -> 500 | H41: СЫРОЙ — датасет | I41: Датасет
A42: budget | B42: Планируемый бюджет на роботизацию (CAPEX) | C42: млн руб. | D42: 80 | E42: 120 | F42: 35 | G42: =INDEX(D42:F42,MATCH(SEL_OBJ,$D$4:$F$4,0)) -> 80 | H42: СЫРОЙ — датасет | I42: Датасет
A43: horizon | B43: Горизонт расчёта окупаемости | C43: лет | D43: 5 | E43: 7 | F43: 7 | G43: =INDEX(D43:F43,MATCH(SEL_OBJ,$D$4:$F$4,0)) -> 5 | H43: СЫРОЙ — датасет | I43: Датасет

Sheet 1b_Нормативы
A1: ШАГ 1b. ГЛОБАЛЬНЫЕ НОРМАТИВЫ И ДОПУЩЕНИЯ
A2: Используются на шагах 2–11. Тип показывает, задан ли норматив организатором или принят командой.
A4: Код | B4: Норматив | C4: Ед. | D4: Значение | E4: Тип | F4: Источник / обоснование | G4: Используется на шагах
A5: N_fot | B5: Коэффициент начислений на ФОТ | C5: коэф. | D5: 1.302 | E5: НОРМАТИВ — организатор | F5: Датасет: 30.2% страховых взносов | G5: 2, 6, 8
A6: N_util | B6: Коэффициент загрузки робота | C6: доля | D6: 0.8 | E6: НОРМАТИВ — организатор | F6: Датасет, легенда: 70–85% | G6: 5
A7: N_avail | B7: Коэффициент технической готовности | C7: доля | D7: 0.95 | E7: ДОПУЩЕНИЕ — команда | F7: Плановое ТО и отказы; SLA вендоров 95–98% | G7: 5
A8: N_reserve | B8: Резерв парка на пик | C8: доля | D8: 0.15 | E8: НОРМАТИВ — организатор | F8: Датасет, легенда: 15–20% | G8: 5
A9: N_kv | B9: Средняя скорость / максимальная | C9: коэф. | D9: 0.6 | E9: ДОПУЩЕНИЕ — команда | F9: Разгон, повороты, трафик; уточняется симуляцией (шаг 12) | G9: 5
A10: N_charger_ratio | B10: Роботов на зарядную станцию | C10: шт. | D10: 4 | E10: ДОПУЩЕНИЕ — команда | F10: Opportunity charging | G10: 5
A11: N_charger_price | B11: Стоимость зарядной станции с монтажом | C11: руб. | D11: 250000 | E11: ДОПУЩЕНИЕ — команда | F11: Оценка рынка | G11: 7
A12: N_charger_kw | B12: Мощность зарядной станции | C12: кВт | D12: 5 | E12: ДОПУЩЕНИЕ — команда | F12: Типовые станции 3–10 кВт | G12: 5
A13: N_sw_pct | B13: ПО управления флотом, % от оборудования | C13: доля | D13: 0.1 | E13: ДОПУЩЕНИЕ — команда | F13: Разовая лицензия/внедрение | G13: 7
A14: N_delivery_pct | B14: Доставка, % от оборудования | C14: доля | D14: 0.02 | E14: ДОПУЩЕНИЕ — команда | F14: Дополнения п.6: не включена в цену | G14: 7
A15: N_pnr_pct | B15: Пусконаладка, % от оборудования | C15: доля | D15: 0.05 | E15: ДОПУЩЕНИЕ — команда | F15: Дополнения п.6: не включена в цену | G15: 7
A16: N_training | B16: Обучение персонала | C16: руб. | D16: 300000 | E16: ДОПУЩЕНИЕ — команда | F16: На проект | G16: 7
... A18: N_service_pct | B18: Сервисный контракт, %/год от оборудования | C18: доля | D18: 0.08 | E18: ДОПУЩЕНИЕ — команда | F18: Отраслевой диапазон 5–10% | G18: 8
A19: N_license_pct | B19: Лицензии ПО, %/год | C19: доля | D19: 0.03 | E19: ДОПУЩЕНИЕ — команда | G19: 8
A20: N_repair_pct | B20: Ремонт вне контракта, %/год | C20: доля | D20: 0.02 | E20: ДОПУЩЕНИЕ — команда | G20: 8
A21: N_energy_price | B21: Тариф на электроэнергию | C21: руб./кВт·ч | D21: 7.5 | E21: ДОПУЩЕНИЕ — команда | F21: Средний тариф юрлиц; уточнить по объекту | G21: 8
A22: N_battery_life | B22: Срок службы АКБ | C22: лет | D22: 4 | E22: НОРМАТИВ — организатор | F22: Датасет, легенда: 3–5 лет | G22: 9, 10
A23: N_battery_share | B23: Стоимость замены АКБ, % цены робота | C23: доля | D23: 0.1 | E23: ДОПУЩЕНИЕ — команда | G23: 9, 10
A24: N_connect | B24: Связь / Wi-Fi поддержка, руб./год | C24: руб./год | D24: 60000 | E24: ДОПУЩЕНИЕ — команда | G24: 8
A25: N_life | B25: Срок службы (амортизация, линейно) | C25: лет | D25: 7 | E25: ДОПУЩЕНИЕ — команда | F25: Дополнения п.2.2 | G25: 9
A26: N_raas_pct | B26: Ставка RaaS, % цены робота в месяц | C26: доля | D26: 0.03 | E26: ДОПУЩЕНИЕ — команда | F26: Рынок RaaS/лизинга: 2.5–4%/мес; включает сервис, ПО, АКБ | G26: 8
A27: N_raas_setup | B27: Установочный платёж RaaS, % цены парка | C27: доля | D27: 0.05 | E27: ДОПУЩЕНИЕ — команда | G27: 7
A28: N_residual_pct | B28: Остаточная стоимость оборудования на конец горизонта, % цены | C28: доля | D28: 0 | E28: ДОПУЩЕНИЕ — команда | F28: Консервативно 0 (рекомендация коллеги: учитывать; при наличии данных — ввести) | G28: 10
A29: N_hire_cost | B29: Стоимость замены сотрудника, окладов | C29: окладов | D29: 0.5 | E29: ДОПУЩЕНИЕ — команда | F29: HR-бенчмарк | G29: 9
A30: N_discount | B30: Ставка дисконтирования | C30: доля | D30: 0.15 | E30: ДОПУЩЕНИЕ — команда | F30: Для NPV / IRR (справочно) | G30: 10
A31: N_loan_share | B31: Доля заёмного финансирования | C31: доля | D31: 0 | E31: НОРМАТИВ — организатор | F31: Дополнения п.2.1: база — собственные средства | G31: 8
A32: N_loan_rate | B32: Ставка кредита | C32: доля | D32: 0.2 | E32: ДОПУЩЕНИЕ — команда | F32: Уточнить на дату расчёта | G32: 8
A33: N_loan_years | B33: Срок кредита | C33: лет | D33: 3 | E33: ДОПУЩЕНИЕ — команда | G33: 8
A34: N_pb_good | B34: Порог «высокой целесообразности», лет | C34: лет | D34: 3 | E34: НОРМАТИВ — организатор | F34: ТЗ 3.5.7 | G34: 9
A35: N_pb_mid | B35: Порог «средней целесообразности», лет | C35: лет | D35: 5 | E35: НОРМАТИВ — организатор | F35: ТЗ 3.5.7 | G35: 9
A36: N_sens | B36: Шаг чувствительности | C36: доля | D36: 0.2 | E36: ДОПУЩЕНИЕ — команда | F36: ТЗ 3.5.6 | G36: 11
A37: N_loss_k_default | B37: Потери рабочего времени по умолчанию | C37: доля | D37: 0.25 | E37: ДОПУЩЕНИЕ — команда | F37: Как у склада (датасет) | G37: 2
A38: N_sim_tol | B38: Допуск расхождения расчёта и симуляции | C38: доля | D38: 0.1 | E38: ДОПУЩЕНИЕ — команда | F38: Правило подтверждения расчёта симуляцией | G38: 12

Sheet 1c_Каталог
A1: ШАГ 1c. КАТАЛОГ РЕШЕНИЙ: цена и статус — СЫРЫЕ из CSV; ТТХ — СЫРЫЕ из docx; коэффициенты замещения/времена операций — ДОПУЩЕНИЯ
A2: Жёлтая заливка — ТТХ по аналогу или допущение (Дополнения п.4). Добавление решения = новая строка.
A4: Код | B4: Наименование | C4: Производитель | D4: Статус | E4: УГТ | F4: Цена, руб. (с НДС) | G4: Грузоподъёмность, кг | H4: Макс. скорость, м/с | I4: Автономность, ч | J4: Зарядка, мин | K4: Длина, мм | L4: Ширина, мм | M4: Высота, мм | N4: Темп. мин, °C | O4: Ср. мощность, кВт | P4: Загрузка, с | Q4: Разгрузка, с | R4: Коэф. замещения (справочно; в расчёте — по паре задача×способ, лист 2) | S4: Улица (1/0) | T4: Класс задачи | U4: Способ обработки груза | V4: Допуск в помещения (1/0) | W4: ТТХ подтверждены | X4: Источник ТТХ / примечание
A5: СЫРОЙ — каталог CSV | B5: СЫРОЙ — каталог CSV | C5: СЫРОЙ — каталог CSV | D5: СЫРОЙ — каталог CSV | E5: СЫРОЙ — каталог CSV | F5: СЫРОЙ — каталог CSV | G5: СЫРОЙ — docx ТТХ | H5: СЫРОЙ — docx ТТХ | I5: СЫРОЙ — docx ТТХ | J5: СЫРОЙ — docx ТТХ | K5: СЫРОЙ — docx ТТХ | L5: СЫРОЙ — docx ТТХ | M5: СЫРОЙ — docx ТТХ | N5: СЫРОЙ — docx ТТХ | O5: ДОПУЩЕНИЕ — команда | P5: ДОПУЩЕНИЕ — команда | Q5: ДОПУЩЕНИЕ — команда | R5: ДОПУЩЕНИЕ — команда | S5: СЫРОЙ — docx ТТХ | T5: СЫРОЙ — каталог CSV | U5: СЫРОЙ — docx ТТХ | V5: СЫРОЙ — docx ТТХ | W5: ДОПУЩЕНИЕ — команда | X5: ДОПУЩЕНИЕ — команда
A6: DMR-CARRIER-P | B6: DMR Carrier P (FMR) | C6: ООО "Диком-Сервис" | D6: piloting | E6: 8 | F6: 4300000 | G6: 1500 | H6: 1.5 | I6: 10 | J6: 90 | K6: 1975 | L6: 1000 | M6: 2050 | N6: 5 | O6: 3 | P6: 60 | Q6: 60 | R6: 0.8 | S6: 0 | T6: транспорт | U6: вилы | V6: 1 | W6: Частично | X6: Docx (пример FMR); зарядка, темп., мощность, времена — допущения
A7: RONAVI-H1500 | B7: Ronavi H1500 (AMR, 1500 кг) | C7: ООО "Ронави Роботикс" | D7: operation | E7: 8 | F7: 2700000 | G7: 1500 | H7: 1.5 | I7: 6 | J7: 18 | K7: 1044 | L7: 654 | M7: 380 | N7: 5 | O7: 1 | P7: 30 | Q7: 30 | R7: 0.6 | S7: 0 | T7: транспорт | U7: платформа | V7: 1 | W7: Да | X7: Docx; подъёмный AMR — передача паллет через станции → замещение 0.6
A8: RONAVI-M | B8: Ronavi M (AMR для тележек, 1200 кг) | C8: ООО "Ронави Роботикс" | D8: piloting | E8: 7 | F8: 2400000 | G8: 1200 | H8: 1.5 | I8: 6 | J8: 18 | K8: 1044 | L8: 654 | M8: 380 | N8: 5 | O8: 1 | P8: 45 | Q8: 45 | R8: 0.8 | S8: 0 | T8: транспорт | U8: платформа | V8: 1 | W8: Частично | X8: Описание каталога; прочие ТТХ по аналогу H1500 — требуют проверки
A9: MOROS-AMR800 | B9: AMR 800 (Морос) | C9: ООО "Морос" | D9: operation | E9: 9 | F9: 1800000 | G9: 800 | H9: 1.5 | I9: 20 | J9: 60 | K9: 1100 | L9: 600 | M9: 230 | N9: 5 | O9: 1 | P9: 45 | Q9: 45 | R9: 0.8 | S9: 0 | T9: транспорт | U9: платформа | V9: 1 | W9: Частично | X9: ТТХ по аналогу AMR 1500 (описание каталога) — требуют проверки
A10: RONAVI-SD | B10: Ronavi SD (AMR, 10 кг) | C10: ООО "Ронави Роботикс" | D10: piloting | E10: 8 | F10: 1400000 | G10: 10 | H10: 2.5 | I10: 10 | J10: 60 | K10: 420 | L10: 400 | M10: 200 | N10: 5 | O10: 0.3 | P10: 20 | Q10: 20 | R10: 0.5 | S10: 0 | T10: транспорт | U10: кузов | V10: 1 | W10: Да | X10: Docx (пример для медицины); исключается фильтром грузоподъёмности для тележек
A11: COGNITIVE-TUG | B11: Беспилотный тягач (Cognitive Pilot) | C11: АО "Когнитив Пилот" | D11: operation | E11: 8 | F11: 4000000 | G11: 3000 | H11: 4.17 | I11: 24 | J11: 30 | K11: 2300 | L11: 1400 | M11: 1500 | N11: -40 | O11: 6 | P11: 180 | Q11: 180 | R11: 0.8 | S11: 1 | T11: транспорт | U11: буксировка | V11: 0 | W11: Да | X11: Docx; скорость рабочая 15 км/ч; гибрид — энергия как эквивалент 6 кВт·ч/ч; сцепка 180 с — допущение
A12: EVOCARGO-N1 | B12: EVOCARGO N1 (электрогрузовик) | C12: ООО "Эвокарго" | D12: operation | E12: 9 | F12: 6000000 | G12: 2000 | H12: 5.56 | I12: 8 | J12: 30 | K12: 5000 | L12: 1800 | M12: 2200 | N12: -40 | O12: 6 | P12: 240 | Q12: 240 | R12: 0.8 | S12: 1 | T12: транспорт | U12: кузов | V12: 0 | W12: Да | X12: Docx; скорость 20 км/ч; перегрузка контейнеров 240 с — допущение
A13: MARK-2-SE | B13: MARK 2 SE (робот-уборщик) | C13: ООО "Р2Б" | D13: operation | E13: 9 | F13: 1900000 | G13: 0 | H13: 1 | I13: 3 | J13: 120 | K13: 860 | L13: 610 | M13: 980 | N13: 5 | O13: 1 | P13: 0 | Q13: 0 | R13: 0.7 | S13: 0 | T13: уборка | U13: щётки | V13: 1 | W13: Да | X13: Docx; процесс «уборка» (расчёт по площади) — не используется в демо

Sheet 2_Процесс
A1: ШАГ 2. ПРЕДПОСЧЁТ ПАРАМЕТРОВ ПРОЦЕССА из сырых данных шага 1 + объектные допущения
A2: Столбцы D–F — формулы/допущения по каждому объекту; G — выбранный объект. Всё, что здесь помечено ПРЕДПОСЧИТАН, дальше не вводится, а ссылается.
A4: Код | B4: Параметр | C4: Ед. | D4: Склад | E4: Аэропорт | F4: Медучреждение | G4: Выбрано | H4: Тип | I4: Обоснование / входы
A5: hours_day | B5: Часов работы процесса в сутки | C5: ч | D5: =1_Сырые_данные!D12*1_Сырые_данные!D13 -> 22 | E5: 24 | F5: 16 | G5: =INDEX(D5:F5,MATCH(SEL_OBJ,$D$4:$F$4,0)) -> 22 | H5: ПРЕДПОСЧИТАН — шаг 1 | I5: Склад: смены × длительность (сырые); Аэропорт: 24/7 (допущение); Мед: окно 06–22 (допущение)
A6: shifts | B6: Смен персонала эксплуатации | C6: смен | D6: =1_Сырые_данные!D12 -> 2 | E6: 3 | F6: =1_Сырые_данные!F12 -> 3 | G6: =INDEX(D6:F6,MATCH(SEL_OBJ,$D$4:$F$4,0)) -> 2 | H6: ПРЕДПОСЧИТАН — шаг 1 | I6: Аэропорт: 3 смены (допущение)
A7: ops_day | B7: Объём операций процесса в сутки | C7: оп./сут | D7: =1_Сырые_данные!D15+1_Сырые_данные!D16 -> 2000 | E7: =1_Сырые_данные!E19*2 -> 560 | F7: =1_Сырые_данные!F24*1_Сырые_данные!F25*2+1_Сырые_данные!F28*1_Сырые_данные!F29*2+1_Сырые_данные!F32*1_Сырые_данные!F33*2+1_Сырые_данные!F31 -> 279.8 | G7: =INDEX(D7:F7,MATCH(SEL_OBJ,$D$4:$F$4,0)) -> 2000 | H7: ПРЕДПОСЧИТАН — шаг 1 | I7: Склад: приёмка+отгрузка; Аэропорт: рейсов×2 направления; Мед: питание+бельё+отходы (×2: доставка и возврат)+расходники
A8: peak_k | B8: Пиковый коэффициент | C8: коэф. | D8: =1_Сырые_данные!D14 -> 1.5 | E8: 1 | F8: 1.8 | G8: =INDEX(D8:F8,MATCH(SEL_OBJ,$D$4:$F$4,0)) -> 1.5 | H8: ДОПУЩЕНИЕ — команда | I8: Склад — сырой; Аэропорт — пик задан напрямую (=1); Мед — два пиковых окна (допущение)
A9: peak_ops_h | B9: Пиковая интенсивность (до учёта доли автоматизации) | C9: оп./ч | D9: =D7/D5*D8 -> 136.36364 | E9: =1_Сырые_данные!E20*2 -> 64 | F9: =F7/F5*F8 -> 31.4775 | G9: =INDEX(D9:F9,MATCH(SEL_OBJ,$D$4:$F$4,0)) -> 136.36364 | H9: ПРЕДПОСЧИТАН — шаг 2 | I9: Аэропорт: пиковых рейсов/ч × 2 (сырой)
A10: auto_share | B10: Доля автоматизируемых операций | C10: доля | D10: =1-1_Сырые_данные!D18 -> 0.95 | E10: 0.9 | F10: 0.9 | G10: =INDEX(D10:F10,MATCH(SEL_OBJ,$D$4:$F$4,0)) -> 0.95 | H10: ДОПУЩЕНИЕ — команда | I10: Склад: 1 − негабарит (сырой); Аэропорт/Мед: 10% операций остаются ручными (допущение)
A11: unit_mass | B11: Масса единицы груза | C11: кг | D11: =1_Сырые_данные!D17 -> 800 | E11: =1_Сырые_данные!E21/1_Сырые_данные!E19*1_Сырые_данные!E22 -> 2250 | F11: =MAX(1_Сырые_данные!F27,1_Сырые_данные!F30) -> 120 | G11: =INDEX(D11:F11,MATCH(SEL_OBJ,$D$4:$F$4,0)) -> 800 | H11: ПРЕДПОСЧИТАН — шаг 1 | I11: Аэропорт: багаж одного рейса; Мед: тяжелейшая тележка
A12: divisible | B12: Груз делимый на рейсы (1/0) | C12: 1/0 | D12: 0 | E12: 1 | F12: 0 | G12: =INDEX(D12:F12,MATCH(SEL_OBJ,$D$4:$F$4,0)) -> 0 | H12: ДОПУЩЕНИЕ — команда | I12: Паллет и тележка неделимы; багаж рейса делим
A13: L | B13: Средняя длина маршрута в одну сторону | C13: м | D13: =SQRT(1_Сырые_данные!D6) -> 100 | E13: =2*SQRT(1_Сырые_данные!E6) -> 632.45553 | F13: =1_Сырые_данные!F26 -> 180 | G13: =INDEX(D13:F13,MATCH(SEL_OBJ,$D$4:$F$4,0)) -> 100 | H13: ДОПУЩЕНИЕ — команда | I13: Склад: √площади зоны; Аэропорт: 2√площади перрона (допущения, калибруются схемой на шаге 12); Мед — сырой
A14: speed_cap | B14: Ограничение скорости на объекте | C14: м/с | D14: 1.5 | E14: 4.17 | F14: 1 | G14: =INDEX(D14:F14,MATCH(SEL_OBJ,$D$4:$F$4,0)) -> 1.5 | H14: ДОПУЩЕНИЕ — команда | I14: Зоны с людьми / перрон 15 км/ч / коридоры
A15: lift_share | B15: Доля рейсов через лифт | C15: доля | D15: 0 | E15: 0 | F15: 0.8 | G15: =INDEX(D15:F15,MATCH(SEL_OBJ,$D$4:$F$4,0)) -> 0 | H15: ДОПУЩЕНИЕ — команда | I15: Мед: 9 этажей
A16: lift_time | B16: Ожидание + проезд лифта (один проход) | C16: с | D16: 0 | E16: 0 | F16: 180 | G16: =INDEX(D16:F16,MATCH(SEL_OBJ,$D$4:$F$4,0)) -> 0 | H16: ДОПУЩЕНИЕ — команда | I16: Мед: 4 лифта на 9 этажей — узкое место; уточняется симуляцией
A17: aisle | B17: Минимальная ширина прохода | C17: м | D17: =MIN(1_Сырые_данные!D7,1_Сырые_данные!D8) -> 2.8 | E17: 4 | F17: =1_Сырые_данные!F9 -> 2.4 | G17: =INDEX(D17:F17,MATCH(SEL_OBJ,$D$4:$F$4,0)) -> 2.8 | H17: ПРЕДПОСЧИТАН — шаг 1 | I17: Аэропорт: служебные проезды (допущение)
A18: clearance | B18: Запас по ширине | C18: м | D18: 0.6 | E18: 0.6 | F18: 0.9 | G18: =INDEX(D18:F18,MATCH(SEL_OBJ,$D$4:$F$4,0)) -> 0.6 | H18: ДОПУЩЕНИЕ — команда | I18: Мед: разминовка с каталкой
A19: outdoor_req | B19: Требуется улица (1/0) | C19: 1/0 | D19: 0 | E19: 1 | F19: 0 | G19: =INDEX(D19:F19,MATCH(SEL_OBJ,$D$4:$F$4,0)) -> 0 | H19: СЫРОЙ — датасет | I19: Перрон — открытая зона
A20: task_class | B20: Класс задачи процесса | D20: транспорт | E20: транспорт | F20: транспорт | G20: =INDEX(D20:F20,MATCH(SEL_OBJ,$D$4:$F$4,0)) -> транспорт | H20: ДОПУЩЕНИЕ — команда | I20: транспорт (рейсы) / уборка (площадь)
A21: handling_req | B21: Допустимые способы обработки груза (через ;) | D21: вилы;платформа | E21: буксировка;кузов | F21: платформа;кузов | G21: =INDEX(D21:F21,MATCH(SEL_OBJ,$D$4:$F$4,0)) -> вилы;платформа | H21: ДОПУЩЕНИЕ — команда | I21: Склад: паллет с пола — вилы, платформа — через станции; Аэропорт: буксировка тележек/кузов; Мед: подъём тележки платформой / кузов
A22: indoor_req | B22: Работа внутри помещений (1/0) | C22: 1/0 | D22: 1 | E22: 0 | F22: 1 | G22: =INDEX(D22:F22,MATCH(SEL_OBJ,$D$4:$F$4,0)) -> 1 | H22: СЫРОЙ — датасет | I22: Уличные гибриды/грузовики не допускаются в помещения
A23: repl_forks | B23: Коэф. замещения труда: вилы | C23: доля | D23: 0.8 | E23: 0.8 | F23: 0.8 | G23: =INDEX(D23:F23,MATCH(SEL_OBJ,$D$4:$F$4,0)) -> 0.8 | H23: ДОПУЩЕНИЕ — команда | I23: Полный цикл без станций
A24: repl_platform | B24: Коэф. замещения труда: платформа | C24: доля | D24: 0.6 | E24: 0.6 | F24: 0.8 | G24: =INDEX(D24:F24,MATCH(SEL_OBJ,$D$4:$F$4,0)) -> 0.6 | H24: ДОПУЩЕНИЕ — команда | I24: Склад: нужны станции передачи; Мед: тележка подхватывается напрямую
A25: repl_tow | B25: Коэф. замещения труда: буксировка | C25: доля | D25: 0.8 | E25: 0.8 | F25: 0.8 | G25: =INDEX(D25:F25,MATCH(SEL_OBJ,$D$4:$F$4,0)) -> 0.8 | H25: ДОПУЩЕНИЕ — команда | I25: Сцепка остаётся ручной
A26: repl_body | B26: Коэф. замещения труда: кузов | C26: доля | D26: 0.5 | E26: 0.8 | F26: 0.5 | G26: =INDEX(D26:F26,MATCH(SEL_OBJ,$D$4:$F$4,0)) -> 0.5 | H26: ДОПУЩЕНИЕ — команда | I26: Ручная погрузка/выгрузка кузова
A27: temp_min | B27: Мин. температура эксплуатации | C27: °C | D27: 5 | E27: =1_Сырые_данные!E23 -> -25 | F27: 18 | G27: =INDEX(D27:F27,MATCH(SEL_OBJ,$D$4:$F$4,0)) -> 5 | H27: ПРЕДПОСЧИТАН — шаг 1 | I27: Склад/Мед: отапливаемые помещения (допущение)
A28: func1 | B28: Доля функции группы 1, приходящаяся на процесс | C28: доля | D28: 1 | E28: 0.2 | F28: 0.5 | G28: =INDEX(D28:F28,MATCH(SEL_OBJ,$D$4:$F$4,0)) -> 1 | H28: ДОПУЩЕНИЕ — команда | I28: Склад: вся работа операторов; Аэропорт: доля водителей тягачей в рампе; Мед: транспортировка у санитаров
A29: func2 | B29: Доля функции группы 2 | C29: доля | D29: 0 | E29: 0 | F29: 0.3 | G29: =INDEX(D29:F29,MATCH(SEL_OBJ,$D$4:$F$4,0)) -> 0 | H29: ДОПУЩЕНИЕ — команда | I29: Мед: пищеблок — только транспорт
A30: func3 | B30: Доля функции группы 3 | C30: доля | D30: 0 | E30: 0 | F30: 0.5 | G30: =INDEX(D30:F30,MATCH(SEL_OBJ,$D$4:$F$4,0)) -> 0 | H30: ДОПУЩЕНИЕ — команда | I30: Мед: прачечная
A31: g3_sal | B31: Оклад группы 3 | C31: руб./мес. | D31: 0 | E31: 0 | F31: =1_Сырые_данные!F35 -> 55000 | G31: =INDEX(D31:F31,MATCH(SEL_OBJ,$D$4:$F$4,0)) -> 0 | H31: ДОПУЩЕНИЕ — команда | I31: Мед: прачечная = санитар (в датасете нет)
A32: fte_target | B32: Целевые FTE процесса | C32: FTE | D32: =(1_Сырые_данные!D34*D28+1_Сырые_данные!D36*D29+1_Сырые_данные!D38*D30)*D10 -> 23.75 | E32: =(1_Сырые_данные!E34*E28+1_Сырые_данные!E36*E29+1_Сырые_данные!E38*E30)*E10 -> 57.6 | F32: =(1_Сырые_данные!F34*F28+1_Сырые_данные!F36*F29+1_Сырые_данные!F38*F30)*F10 -> 44.91 | G32: =INDEX(D32:F32,MATCH(SEL_OBJ,$D$4:$F$4,0)) -> 23.75 | H32: ПРЕДПОСЧИТАН — шаг 2 | I32: Σ численность × доля функции × доля автоматизируемых
A33: labor_target | B33: Годовой ФОТ целевых FTE (с начислениями) | C33: руб./год | D33: =(1_Сырые_данные!D34*D28*1_Сырые_данные!D35+1_Сырые_данные!D36*D29*1_Сырые_данные!D37+1_Сырые_данные!D38*D30*D31)*D10*12*N_fot -> 44528400 | E33: =(1_Сырые_данные!E34*E28*1_Сырые_данные!E35+1_Сырые_данные!E36*E29*1_Сырые_данные!E37+1_Сырые_данные!E38*E30*E31)*E10*12*N_fot -> 89994240 | F33: =(1_Сырые_данные!F34*F28*1_Сырые_данные!F35+1_Сырые_данные!F36*F29*1_Сырые_данные!F37+1_Сырые_данные!F38*F30*F31)*F10*12*N_fot -> 38237709 | G33: =INDEX(D33:F33,MATCH(SEL_OBJ,$D$4:$F$4,0)) -> 44528400 | H33: ПРЕДПОСЧИТАН — шаг 2
A34: base_labor | B34: Годовой ФОТ всего персонала процесса (база) | C34: руб./год | D34: =(1_Сырые_данные!D34*D28*1_Сырые_данные!D35+1_Сырые_данные!D36*D29*1_Сырые_данные!D37+1_Сырые_данные!D38*D30*D31)*12*N_fot -> 46872000 | E34: =(1_Сырые_данные!E34*E28*1_Сырые_данные!E35+1_Сырые_данные!E36*E29*1_Сырые_данные!E37+1_Сырые_данные!E38*E30*E31)*12*N_fot -> 99993600 | F34: =(1_Сырые_данные!F34*F28*1_Сырые_данные!F35+1_Сырые_данные!F36*F29*1_Сырые_данные!F37+1_Сырые_данные!F38*F30*F31)*12*N_fot -> 42486343 | G34: =INDEX(D34:F34,MATCH(SEL_OBJ,$D$4:$F$4,0)) -> 46872000 | H34: ПРЕДПОСЧИТАН — шаг 2
A35: sal_target | B35: Средний оклад целевого персонала | C35: руб./мес. | D35: =1_Сырые_данные!D35 -> 120000 | E35: =1_Сырые_данные!E35 -> 100000 | F35: =1_Сырые_данные!F35 -> 55000 | G35: =INDEX(D35:F35,MATCH(SEL_OBJ,$D$4:$F$4,0)) -> 120000 | H35: ПРЕДПОСЧИТАН — шаг 1
A36: turnover | B36: Текучесть целевого персонала | C36: доля | D36: =0 -> 0 | E36: =1_Сырые_данные!E40 -> 0.35 | F36: =1_Сырые_данные!F40 -> 0.45 | G36: =INDEX(D36:F36,MATCH(SEL_OBJ,$D$4:$F$4,0)) -> 0 | H36: ПРЕДПОСЧИТАН — шаг 1 | I36: Склад: нет в датасете → 0
A37: loss_k | B37: Потери рабочего времени | C37: доля | D37: =1_Сырые_данные!D39 -> 0.25 | E37: =N_loss_k_default -> 0.25 | F37: =N_loss_k_default -> 0.25 | G37: =INDEX(D37:F37,MATCH(SEL_OBJ,$D$4:$F$4,0)) -> 0.25 | H37: ПРЕДПОСЧИТАН — шаг 1 | I37: Аэропорт/Мед: норматив по умолчанию
A38: fleet_per_shift | B38: Операторов флота на смену | C38: чел. | D38: 1 | E38: 1 | F38: 1 | G38: =INDEX(D38:F38,MATCH(SEL_OBJ,$D$4:$F$4,0)) -> 1 | H38: ДОПУЩЕНИЕ — команда
A39: fleet_sal | B39: Оклад оператора флота | C39: руб./мес. | D39: =1_Сырые_данные!D35 -> 120000 | E39: =1_Сырые_данные!E35 -> 100000 | F39: =1_Сырые_данные!F35 -> 55000 | G39: =INDEX(D39:F39,MATCH(SEL_OBJ,$D$4:$F$4,0)) -> 120000 | H39: ДОПУЩЕНИЕ — команда | I39: На уровне группы 1
A40: site_pct | B40: Подготовка объекта, % от стоимости парка | C40: доля | D40: 0.05 | E40: 0.1 | F40: 0.15 | G40: =INDEX(D40:F40,MATCH(SEL_OBJ,$D$4:$F$4,0)) -> 0.05 | H40: ДОПУЩЕНИЕ — команда | I40: Разметка/Wi-Fi; СКУД airside; API лифтов
A41: integration | B41: Интеграция с ИТ-системами объекта | C41: руб. | D41: 2000000 | E41: 3000000 | F41: 2500000 | G41: =INDEX(D41:F41,MATCH(SEL_OBJ,$D$4:$F$4,0)) -> 2000000 | H41: ДОПУЩЕНИЕ — команда | I41: WMS/1С; AODB/BHS; МИС/лифты
A42: consum_per_robot | B42: Расходники на робота в год | C42: руб./год | D42: 0 | E42: 0 | F42: =2*365*120 -> 87600 | G42: =INDEX(D42:F42,MATCH(SEL_OBJ,$D$4:$F$4,0)) -> 0 | H42: ДОПУЩЕНИЕ — команда | I42: Мед: дезинфекция 2 раза/сут × 120 руб.
A43: other_effects | B43: Иные измеримые эффекты | C43: руб./год | D43: 0 | E43: 0 | F43: 0 | G43: =INDEX(D43:F43,MATCH(SEL_OBJ,$D$4:$F$4,0)) -> 0 | H43: ДОПУЩЕНИЕ — команда | I43: Ошибки/потери — ввод пользователя
A44: power_kw | B44: Доступная мощность | C44: кВт | D44: =1_Сырые_данные!D41 -> 500 | E44: =1_Сырые_данные!E41 -> 300 | F44: =1_Сырые_данные!F41 -> 80 | G44: =INDEX(D44:F44,MATCH(SEL_OBJ,$D$4:$F$4,0)) -> 500 | H44: ПРЕДПОСЧИТАН — шаг 1
A45: budget | B45: Бюджет CAPEX | C45: млн руб. | D45: =1_Сырые_данные!D42 -> 80 | E45: =1_Сырые_данные!E42 -> 120 | F45: =1_Сырые_данные!F42 -> 35 | G45: =INDEX(D45:F45,MATCH(SEL_OBJ,$D$4:$F$4,0)) -> 80 | H45: ПРЕДПОСЧИТАН — шаг 1
A46: horizon | B46: Горизонт расчёта | C46: лет | D46: =1_Сырые_данные!D43 -> 5 | E46: =1_Сырые_данные!E43 -> 7 | F46: =1_Сырые_данные!F43 -> 7 | G46: =INDEX(D46:F46,MATCH(SEL_OBJ,$D$4:$F$4,0)) -> 5 | H46: ПРЕДПОСЧИТАН — шаг 1

Sheet 3_Решение_фильтры
A1: ШАГ 3. РЕШЕНИЕ: ТТХ, ЦЕНА, ПРОВЕРКА ПРИМЕНИМОСТИ
A2: Столбцы F–H — три сценария выбранного объекта. Ключевое ограничение → решение не рекомендуется (ТЗ 3.4.3); причина выводится текстом (ТЗ 3.4.2).
A4: ВХОДНЫЕ ПАРАМЕТРЫ ШАГА (откуда берутся и какого типа)
B5: Параметр | C5: Ед. | D5: Тип происхождения | E5: Источник (шаг / лист) | F5: Значение (Покупка A) | G5: Значение (RaaS A) | H5: Значение (Покупка B)
B6: Код решения (по сценарию, из 0_Легенда) | D6: ПРЕДПОСЧИТАН — шаг 0 | E6: 0_Легенда: SEL_A / SEL_B | F6: =SEL_A -> DMR-CARRIER-P | G6: =SEL_A -> DMR-CARRIER-P | H6: =SEL_B -> RONAVI-H1500
B7: Модель приобретения | D7: ДОПУЩЕНИЕ — команда | E7: Сценарий | F7: Покупка | G7: RaaS | H7: Покупка
B8: Масса единицы груза | C8: кг | D8: ПРЕДПОСЧИТАН — шаг 2 | E8: 2_Процесс: unit_mass | F8: =P_unit_mass -> 800 | G8: =P_unit_mass -> 800 | H8: =P_unit_mass -> 800
B9: Груз делимый | C9: 1/0 | D9: ДОПУЩЕНИЕ — команда | E9: 2_Процесс: divisible | F9: =P_divisible -> 0 | G9: =P_divisible -> 0 | H9: =P_divisible -> 0
B10: Мин. ширина прохода / запас | C10: м | D10: ПРЕДПОСЧИТАН — шаг 2 | E10: 2_Процесс: aisle, clearance | F10: =P_aisle -> 2.8 | G10: =P_aisle -> 2.8 | H10: =P_aisle -> 2.8
B11: Требуется улица / мин. температура | D11: ПРЕДПОСЧИТАН — шаг 2 | E11: 2_Процесс: outdoor_req, temp_min | F11: =P_outdoor_req -> 0 | G11: =P_outdoor_req -> 0 | H11: =P_outdoor_req -> 0
B12: Класс задачи / допустимые способы обработки / работа в помещении | D12: ДОПУЩЕНИЕ — команда | E12: 2_Процесс: task_class, handling_req, indoor_req | F12: =P_handling_req -> вилы;платформа | G12: =P_handling_req -> вилы;платформа | H12: =P_handling_req -> вилы;платформа
B13: Коэф. замещения по способу обработки | C13: доля | D13: ДОПУЩЕНИЕ — команда | E13: 2_Процесс: repl_forks, repl_platform, repl_tow, repl_body | F13: =P_repl_platform -> 0.6 | G13: =P_repl_platform -> 0.6 | H13: =P_repl_platform -> 0.6
A15: РАСЧЁТ ШАГА
A16: Ключ | B16: Показатель | C16: Ед. | D16: Формула (пояснение) | F16: Покупка A | G16: RaaS A | H16: Покупка B
B17: 3.1 ТТХ и цена из каталога (шаг 1c)
A18: sol_name | B18: Наименование | D18: INDEX(Cat_name,MATCH($6,Cat_code,0)) | F18: =INDEX(Cat_name,MATCH(F$6,Cat_code,0)) -> DMR Carrier P (FMR) | G18: =INDEX(Cat_name,MATCH(G$6,Cat_code,0)) -> DMR Carrier P (FMR) | H18: =INDEX(Cat_name,MATCH(H$6,Cat_code,0)) -> Ronavi H1500 (AMR, 1500 кг)
A19: sol_status | B19: Статус (СЫРОЙ — CSV) | D19: INDEX(Cat_status,MATCH($6,Cat_code,0)) | F19: =INDEX(Cat_status,MATCH(F$6,Cat_code,0)) -> piloting | G19: =INDEX(Cat_status,MATCH(G$6,Cat_code,0)) -> piloting | H19: =INDEX(Cat_status,MATCH(H$6,Cat_code,0)) -> operation
A20: sol_conf | B20: ТТХ подтверждены | D20: INDEX(Cat_conf,MATCH($6,Cat_code,0)) | F20: =INDEX(Cat_conf,MATCH(F$6,Cat_code,0)) -> Частично | G20: =INDEX(Cat_conf,MATCH(G$6,Cat_code,0)) -> Частично | H20: =INDEX(Cat_conf,MATCH(H$6,Cat_code,0)) -> Да
A21: price | B21: Цена изделия (СЫРОЙ — CSV) | C21: руб. | D21: INDEX(Cat_price,MATCH($6,Cat_code,0)) | F21: =INDEX(Cat_price,MATCH(F$6,Cat_code,0)) -> 4300000 | G21: =INDEX(Cat_price,MATCH(G$6,Cat_code,0)) -> 4300000 | H21: =INDEX(Cat_price,MATCH(H$6,Cat_code,0)) -> 2700000
A22: cap | B22: Грузоподъёмность (СЫРОЙ — docx) | C22: кг | D22: INDEX(Cat_cap,MATCH($6,Cat_code,0)) | F22: =INDEX(Cat_cap,MATCH(F$6,Cat_code,0)) -> 1500 | G22: =INDEX(Cat_cap,MATCH(G$6,Cat_code,0)) -> 1500 | H22: =INDEX(Cat_cap,MATCH(H$6,Cat_code,0)) -> 1500
A23: vmax | B23: Макс. скорость (СЫРОЙ — docx) | C23: м/с | D23: INDEX(Cat_vmax,MATCH($6,Cat_code,0)) | F23: =INDEX(Cat_vmax,MATCH(F$6,Cat_code,0)) -> 1.5 | G23: =INDEX(Cat_vmax,MATCH(G$6,Cat_code,0)) -> 1.5 | H23: =INDEX(Cat_vmax,MATCH(H$6,Cat_code,0)) -> 1.5
A24: tload | B24: Время загрузки (ДОПУЩЕНИЕ) | C24: с | D24: INDEX(Cat_tload,MATCH($6,Cat_code,0)) | F24: =INDEX(Cat_tload,MATCH(F$6,Cat_code,0)) -> 60 | G24: =INDEX(Cat_tload,MATCH(G$6,Cat_code,0)) -> 60 | H24: =INDEX(Cat_tload,MATCH(H$6,Cat_code,0)) -> 30
A25: tunload | B25: Время разгрузки (ДОПУЩЕНИЕ) | C25: с | D25: INDEX(Cat_tunload,MATCH($6,Cat_code,0)) | F25: =INDEX(Cat_tunload,MATCH(F$6,Cat_code,0)) -> 60 | G25: =INDEX(Cat_tunload,MATCH(G$6,Cat_code,0)) -> 60 | H25: =INDEX(Cat_tunload,MATCH(H$6,Cat_code,0)) -> 30
A26: power | B26: Мощность (ДОПУЩЕНИЕ) | C26: кВт | D26: INDEX(Cat_power,MATCH($6,Cat_code,0)) | F26: =INDEX(Cat_power,MATCH(F$6,Cat_code,0)) -> 3 | G26: =INDEX(Cat_power,MATCH(G$6,Cat_code,0)) -> 3 | H26: =INDEX(Cat_power,MATCH(H$6,Cat_code,0)) -> 1
A27: handling | B27: Способ обработки груза (СЫРОЙ — docx/каталог) | D27: INDEX(Cat_handling,MATCH($6,Cat_code,0)) | F27: =INDEX(Cat_handling,MATCH(F$6,Cat_code,0)) -> вилы | G27: =INDEX(Cat_handling,MATCH(G$6,Cat_code,0)) -> вилы | H27: =INDEX(Cat_handling,MATCH(H$6,Cat_code,0)) -> платформа
A28: indoor | B28: Допуск в помещения | C28: 1/0 | D28: INDEX(Cat_indoor,MATCH($6,Cat_code,0)) | F28: =INDEX(Cat_indoor,MATCH(F$6,Cat_code,0)) -> 1 | G28: =INDEX(Cat_indoor,MATCH(G$6,Cat_code,0)) -> 1 | H28: =INDEX(Cat_indoor,MATCH(H$6,Cat_code,0)) -> 1
A29: task | B29: Класс задачи решения | D29: INDEX(Cat_task,MATCH($6,Cat_code,0)) | F29: =INDEX(Cat_task,MATCH(F$6,Cat_code,0)) -> транспорт | G29: =INDEX(Cat_task,MATCH(G$6,Cat_code,0)) -> транспорт | H29: =INDEX(Cat_task,MATCH(H$6,Cat_code,0)) -> транспорт
A30: repl | B30: Коэф. замещения труда = по паре задача × способ обработки (ПРЕДПОСЧИТАН — шаг 2) | C30: доля | D30: IF([handling]="вилы",P_repl_forks,IF([handling]="платформа",P_repl_platform,IF([handling]="буксировка",P_repl_tow,IF([handling]="кузов",P_repl_body,0)))) | F30: =IF(F27="вилы",P_repl_forks,IF(F27="платформа",P_repl_platform,IF(F27="буксировка",P_repl_tow,IF(F27="кузов",P_repl_body,0)))) -> 0.8 | G30: =IF(G27="вилы",P_repl_forks,IF(G27="платформа",P_repl_platform,IF(G27="буксировка",P_repl_tow,IF(G27="кузов",P_repl_body,0)))) -> 0.8 | H30: =IF(H27="вилы",P_repl_forks,IF(H27="платформа",P_repl_platform,IF(H27="буксировка",P_repl_tow,IF(H27="кузов",P_repl_body,0)))) -> 0.6
A31: wid | B31: Ширина | C31: мм | D31: INDEX(Cat_wid,MATCH($6,Cat_code,0)) | F31: =INDEX(Cat_wid,MATCH(F$6,Cat_code,0)) -> 1000 | G31: =INDEX(Cat_wid,MATCH(G$6,Cat_code,0)) -> 1000 | H31: =INDEX(Cat_wid,MATCH(H$6,Cat_code,0)) -> 654
A32: tmin | B32: Мин. температура | C32: °C | D32: INDEX(Cat_tmin,MATCH($6,Cat_code,0)) | F32: =INDEX(Cat_tmin,MATCH(F$6,Cat_code,0)) -> 5 | G32: =INDEX(Cat_tmin,MATCH(G$6,Cat_code,0)) -> 5 | H32: =INDEX(Cat_tmin,MATCH(H$6,Cat_code,0)) -> 5
A33: outdoor | B33: Улица | C33: 1/0 | D33: INDEX(Cat_outdoor,MATCH($6,Cat_code,0)) | F33: =INDEX(Cat_outdoor,MATCH(F$6,Cat_code,0)) -> 0 | G33: =INDEX(Cat_outdoor,MATCH(G$6,Cat_code,0)) -> 0 | H33: =INDEX(Cat_outdoor,MATCH(H$6,Cat_code,0)) -> 0
A34: auton | B34: Автономность (для шага 12) | C34: ч | D34: INDEX(Cat_auton,MATCH($6,Cat_code,0)) | F34: =INDEX(Cat_auton,MATCH(F$6,Cat_code,0)) -> 10 | G34: =INDEX(Cat_auton,MATCH(G$6,Cat_code,0)) -> 10 | H34: =INDEX(Cat_auton,MATCH(H$6,Cat_code,0)) -> 6
A35: charge | B35: Время зарядки (для шага 12) | C35: мин | D35: INDEX(Cat_charge,MATCH($6,Cat_code,0)) | F35: =INDEX(Cat_charge,MATCH(F$6,Cat_code,0)) -> 90 | G35: =INDEX(Cat_charge,MATCH(G$6,Cat_code,0)) -> 90 | H35: =INDEX(Cat_charge,MATCH(H$6,Cat_code,0)) -> 18
B36: 3.2 Проверка применимости
A37: chk_task | B37: Класс задачи совпадает | D37: IF([task]=P_task_class,"ОК","НЕТ") | F37: =IF(F29=P_task_class,"ОК","НЕТ") -> ОК | G37: =IF(G29=P_task_class,"ОК","НЕТ") -> ОК | H37: =IF(H29=P_task_class,"ОК","НЕТ") -> ОК
A38: chk_handling | B38: Способ обработки допустим для задачи | D38: IF(ISNUMBER(SEARCH([handling],P_handling_req)),"ОК","НЕТ") | F38: =IF(ISNUMBER(SEARCH(F27,P_handling_req)),"ОК","НЕТ") -> ОК | G38: =IF(ISNUMBER(SEARCH(G27,P_handling_req)),"ОК","НЕТ") -> ОК | H38: =IF(ISNUMBER(SEARCH(H27,P_handling_req)),"ОК","НЕТ") -> ОК
A39: chk_indoor | B39: Допуск в помещения | D39: IF(AND(P_indoor_req=1,[indoor]=0),"НЕТ","ОК") | F39: =IF(AND(P_indoor_req=1,F28=0),"НЕТ","ОК") -> ОК | G39: =IF(AND(P_indoor_req=1,G28=0),"НЕТ","ОК") -> ОК | H39: =IF(AND(P_indoor_req=1,H28=0),"НЕТ","ОК") -> ОК
A40: chk_cap | B40: Грузоподъёмность: неделимый груз и cap < масса → НЕТ | D40: IF(AND(P_divisible=0,[cap]<P_unit_mass),"НЕТ","ОК") | F40: =IF(AND(P_divisible=0,F22<P_unit_mass),"НЕТ","ОК") -> ОК | G40: =IF(AND(P_divisible=0,G22<P_unit_mass),"НЕТ","ОК") -> ОК | H40: =IF(AND(P_divisible=0,H22<P_unit_mass),"НЕТ","ОК") -> ОК
A41: chk_aisle | B41: Проход: ширина + запас ≤ мин. проход | D41: IF([wid]/1000+P_clearance<=P_aisle,"ОК","НЕТ") | F41: =IF(F31/1000+P_clearance<=P_aisle,"ОК","НЕТ") -> ОК | G41: =IF(G31/1000+P_clearance<=P_aisle,"ОК","НЕТ") -> ОК | H41: =IF(H31/1000+P_clearance<=P_aisle,"ОК","НЕТ") -> ОК
A42: chk_env | B42: Условия: улица и температура | D42: IF(P_outdoor_req=1,IF(AND([outdoor]=1,[tmin]<=P_temp_min),"ОК","НЕТ"),"ОК") | F42: =IF(P_outdoor_req=1,IF(AND(F33=1,F32<=P_temp_min),"ОК","НЕТ"),"ОК") -> ОК | G42: =IF(P_outdoor_req=1,IF(AND(G33=1,G32<=P_temp_min),"ОК","НЕТ"),"ОК") -> ОК | H42: =IF(P_outdoor_req=1,IF(AND(H33=1,H32<=P_temp_min),"ОК","НЕТ"),"ОК") -> ОК
A43: feasible | B43: ПРИМЕНИМО (1/0) | C43: 1/0 | D43: IF(AND([chk_task]="ОК",[chk_handling]="ОК",[chk_indoor]="ОК",[chk_cap]="ОК",[chk_aisle]="ОК",[chk_env]="ОК"),1,0) | F43: =IF(AND(F37="ОК",F38="ОК",F39="ОК",F40="ОК",F41="ОК",F42="ОК"),1,0) -> 1 | G43: =IF(AND(G37="ОК",G38="ОК",G39="ОК",G40="ОК",G41="ОК",G42="ОК"),1,0) -> 1 | H43: =IF(AND(H37="ОК",H38="ОК",H39="ОК",H40="ОК",H41="ОК",H42="ОК"),1,0) -> 1
A44: feas_text | B44: Причина включения / исключения | D44: IF([feasible]=1,"Применимо: ключевые ограничения выполнены","Не применимо: "&IF([chk_task]="НЕТ","класс задачи; ","")&IF([chk_handling]="НЕТ","способ обработки груза; ","")&IF([chk_indoor]="НЕТ","не допущен в помещения; ","")&IF([chk_cap]="НЕТ","грузоподъёмность; ","")&IF([chk_aisle]="НЕТ","габариты/проход; ","")&IF([chk_env]="НЕТ","условия эксплуатации; ","")) | F44: =IF(F43=1,"Применимо: ключевые ограничения выполнены","Не применимо: "&IF(F37="НЕТ","класс задачи; ","")&IF(F38="НЕТ","способ обработки груза; ","")&IF(F39="НЕТ","не допущен в помещения; ","")&IF(F40="НЕТ","грузоподъёмность; ","")&IF(F41="НЕТ","габариты/проход; ","")&IF(F42="НЕТ","условия эксплуатации; ","")) -> Применимо: ключевые ограничения выполнены | G44: =IF(G43=1,"Применимо: ключевые ограничения выполнены","Не применимо: "&IF(G37="НЕТ","класс задачи; ","")&IF(G38="НЕТ","способ обработки груза; ","")&IF(G39="НЕТ","не допущен в помещения; ","")&IF(G40="НЕТ","грузоподъёмность; ","")&IF(G41="НЕТ","габариты/проход; ","")&IF(G42="НЕТ","условия эксплуатации; ","")) -> Применимо: ключевые ограничения выполнены | H44: =IF(H43=1,"Применимо: ключевые ограничения выполнены","Не применимо: "&IF(H37="НЕТ","класс задачи; ","")&IF(H38="НЕТ","способ обработки груза; ","")&IF(H39="НЕТ","не допущен в помещения; ","")&IF(H40="НЕТ","грузоподъёмность; ","")&IF(H41="НЕТ","габариты/проход; ","")&IF(H42="НЕТ","условия эксплуатации; ","")) -> Применимо: ключевые ограничения выполнены
A45: is_purchase | B45: Модель «Покупка» = 1 / RaaS = 0 | C45: 1/0 | D45: IF($7="Покупка",1,0) | F45: =IF(F$7="Покупка",1,0) -> 1 | G45: =IF(G$7="Покупка",1,0) -> 0 | H45: =IF(H$7="Покупка",1,0) -> 1
A47: ВЫХОДЫ ШАГА → куда передаются
B48: price, cap, vmax, tload, tunload, power, repl → шаги 4, 5, 7, 8, 9; feasible → все последующие шаги; auton, charge → шаг 12 (симуляция).

Sheet 4_Потребность
A1: ШАГ 4. ПОТРЕБНОСТЬ В ОПЕРАЦИЯХ (ТЗ 3.5.2: пиковая потребность)
A2: Все входы — предпосчитанные на шаге 2, кроме грузоподъёмности решения (сырая ТТХ).
A4: ВХОДНЫЕ ПАРАМЕТРЫ ШАГА (откуда берутся и какого типа)
B5: Параметр | C5: Ед. | D5: Тип происхождения | E5: Источник (шаг / лист) | F5: Значение (Покупка A) | G5: Значение (RaaS A) | H5: Значение (Покупка B)
B6: Объём операций в сутки | C6: оп./сут | D6: ПРЕДПОСЧИТАН — шаг 2 | E6: 2_Процесс: ops_day | F6: =P_ops_day -> 2000 | G6: =P_ops_day -> 2000 | H6: =P_ops_day -> 2000
B7: Доля автоматизируемых операций | C7: доля | D7: ДОПУЩЕНИЕ — команда | E7: 2_Процесс: auto_share | F7: =P_auto_share -> 0.95 | G7: =P_auto_share -> 0.95 | H7: =P_auto_share -> 0.95
B8: Пиковая интенсивность | C8: оп./ч | D8: ПРЕДПОСЧИТАН — шаг 2 | E8: 2_Процесс: peak_ops_h | F8: =P_peak_ops_h -> 136.36364 | G8: =P_peak_ops_h -> 136.36364 | H8: =P_peak_ops_h -> 136.36364
B9: Часов работы в сутки | C9: ч | D9: ПРЕДПОСЧИТАН — шаг 2 | E9: 2_Процесс: hours_day | F9: =P_hours_day -> 22 | G9: =P_hours_day -> 22 | H9: =P_hours_day -> 22
B10: Масса единицы груза / делимость | C10: кг | D10: ПРЕДПОСЧИТАН — шаг 2 | E10: 2_Процесс: unit_mass, divisible | F10: =P_unit_mass -> 800 | G10: =P_unit_mass -> 800 | H10: =P_unit_mass -> 800
B11: Грузоподъёмность решения | C11: кг | D11: СЫРОЙ — docx ТТХ | E11: 3_Решение_фильтры: cap | F11: =3_Решение_фильтры!F22 -> 1500 | G11: =3_Решение_фильтры!G22 -> 1500 | H11: =3_Решение_фильтры!H22 -> 1500
A13: РАСЧЁТ ШАГА
A14: Ключ | B14: Показатель | C14: Ед. | D14: Формула (пояснение) | F14: Покупка A | G14: RaaS A | H14: Покупка B
A15: ops_auto | B15: Автоматизируемых операций в сутки = объём × доля | C15: оп./сут | D15: P_ops_day*P_auto_share | F15: =P_ops_day*P_auto_share -> 1900 | G15: =P_ops_day*P_auto_share -> 1900 | H15: =P_ops_day*P_auto_share -> 1900
A16: trips_per_op | B16: Рейсов робота на операцию = делимый ? ROUNDUP(масса/cap) : 1 | C16: рейсов | D16: IF(P_divisible=1,ROUNDUP(P_unit_mass/MAX([шаг 3: cap],1),0),1) | F16: =IF(P_divisible=1,ROUNDUP(P_unit_mass/MAX(3_Решение_фильтры!F22,1),0),1) -> 1 | G16: =IF(P_divisible=1,ROUNDUP(P_unit_mass/MAX(3_Решение_фильтры!G22,1),0),1) -> 1 | H16: =IF(P_divisible=1,ROUNDUP(P_unit_mass/MAX(3_Решение_фильтры!H22,1),0),1) -> 1
A17: avg_h | B17: Среднечасовая потребность | C17: оп./ч | D17: [ops_auto]/P_hours_day | F17: =F15/P_hours_day -> 86.363636 | G17: =G15/P_hours_day -> 86.363636 | H17: =H15/P_hours_day -> 86.363636
A18: peak_h | B18: Пиковая потребность (автоматизируемая) | C18: оп./ч | D18: P_peak_ops_h*P_auto_share | F18: =P_peak_ops_h*P_auto_share -> 129.54545 | G18: =P_peak_ops_h*P_auto_share -> 129.54545 | H18: =P_peak_ops_h*P_auto_share -> 129.54545
A19: peak_trips | B19: ПИКОВАЯ ПОТРЕБНОСТЬ В РЕЙСАХ РОБОТА | C19: рейсов/ч | D19: [peak_h]*[trips_per_op] | F19: =F18*F16 -> 129.54545 | G19: =G18*G16 -> 129.54545 | H19: =H18*H16 -> 129.54545
A20: trips_day | B20: Рейсов робота в сутки (для симуляции) | C20: рейсов/сут | D20: [ops_auto]*[trips_per_op] | F20: =F15*F16 -> 1900 | G20: =G15*G16 -> 1900 | H20: =H15*H16 -> 1900
A22: ВЫХОДЫ ШАГА → куда передаются
B23: peak_trips → шаг 5 (размер парка); avg_h, trips_day, trips_per_op → шаг 12 (профиль заявок симуляции).

Sheet 5_Парк
A1: ШАГ 5. ЦИКЛ РЕЙСА, ПРОИЗВОДИТЕЛЬНОСТЬ, СОСТАВ ПАРКА
A2: Именно эти величины (v_eff, t_cycle, n_robots, n_chargers, util_avg) должна воспроизвести симуляция (шаг 12).
A4: ВХОДНЫЕ ПАРАМЕТРЫ ШАГА (откуда берутся и какого типа)
B5: Параметр | C5: Ед. | D5: Тип происхождения | E5: Источник (шаг / лист) | F5: Значение (Покупка A) | G5: Значение (RaaS A) | H5: Значение (Покупка B)
B6: Длина маршрута | C6: м | D6: ДОПУЩЕНИЕ — команда | E6: 2_Процесс: L (склад/аэропорт — допущение; мед — сырой) | F6: =P_L -> 100 | G6: =P_L -> 100 | H6: =P_L -> 100
B7: Ограничение скорости объекта | C7: м/с | D7: ДОПУЩЕНИЕ — команда | E7: 2_Процесс: speed_cap | F7: =P_speed_cap -> 1.5 | G7: =P_speed_cap -> 1.5 | H7: =P_speed_cap -> 1.5
B8: Макс. скорость решения | C8: м/с | D8: СЫРОЙ — docx ТТХ | E8: 3_Решение_фильтры: vmax | F8: =3_Решение_фильтры!F23 -> 1.5 | G8: =3_Решение_фильтры!G23 -> 1.5 | H8: =3_Решение_фильтры!H23 -> 1.5
B9: Времена загрузки / разгрузки | C9: с | D9: ДОПУЩЕНИЕ — команда | E9: 3_Решение_фильтры: tload, tunload | F9: =3_Решение_фильтры!F24 -> 60 | G9: =3_Решение_фильтры!G24 -> 60 | H9: =3_Решение_фильтры!H24 -> 30
B10: Лифт: доля рейсов / время прохода | D10: ДОПУЩЕНИЕ — команда | E10: 2_Процесс: lift_share, lift_time | F10: =P_lift_share -> 0 | G10: =P_lift_share -> 0 | H10: =P_lift_share -> 0
B11: Коэффициенты: скорость 0.6, загрузка 0.8, готовность 0.95, резерв 0.15 | D11: НОРМАТИВ — организатор | E11: 1b_Нормативы: N_kv (допущение), N_util, N_reserve (нормативы), N_avail (допущение) | F11: =N_util -> 0.8 | G11: =N_util -> 0.8 | H11: =N_util -> 0.8
B12: Пиковая потребность в рейсах | C12: рейсов/ч | D12: ПРЕДПОСЧИТАН — шаг 4 | E12: 4_Потребность: peak_trips | F12: =4_Потребность!F19 -> 129.54545 | G12: =4_Потребность!G19 -> 129.54545 | H12: =4_Потребность!H19 -> 129.54545
B13: Роботов на станцию / мощность станции / доступная мощность | D13: ДОПУЩЕНИЕ — команда | E13: 1b_Нормативы; 2_Процесс: power_kw | F13: =N_charger_ratio -> 4 | G13: =N_charger_ratio -> 4 | H13: =N_charger_ratio -> 4
A15: РАСЧЁТ ШАГА
A16: Ключ | B16: Показатель | C16: Ед. | D16: Формула (пояснение) | F16: Покупка A | G16: RaaS A | H16: Покупка B
A17: v_eff | B17: Эксплуатационная скорость = MIN(vmax; лимит) × N_kv | C17: м/с | D17: MIN([шаг 3: vmax],P_speed_cap)*N_kv | F17: =MIN(3_Решение_фильтры!F23,P_speed_cap)*N_kv -> 0.9 | G17: =MIN(3_Решение_фильтры!G23,P_speed_cap)*N_kv -> 0.9 | H17: =MIN(3_Решение_фильтры!H23,P_speed_cap)*N_kv -> 0.9
A18: t_move | B18: Время движения за цикл = 2L / v_eff | C18: с | D18: 2*P_L/[v_eff] | F18: =2*P_L/F17 -> 222.22222 | G18: =2*P_L/G17 -> 222.22222 | H18: =2*P_L/H17 -> 222.22222
A19: t_lift | B19: Время лифта за цикл = доля × 2 × время | C19: с | D19: P_lift_share*2*P_lift_time | F19: =P_lift_share*2*P_lift_time -> 0 | G19: =P_lift_share*2*P_lift_time -> 0 | H19: =P_lift_share*2*P_lift_time -> 0
A20: t_cycle | B20: ПОЛНЫЙ ЦИКЛ РЕЙСА | C20: с | D20: [t_move]+[шаг 3: tload]+[шаг 3: tunload]+[t_lift] | F20: =F18+3_Решение_фильтры!F24+3_Решение_фильтры!F25+F19 -> 342.22222 | G20: =G18+3_Решение_фильтры!G24+3_Решение_фильтры!G25+G19 -> 342.22222 | H20: =H18+3_Решение_фильтры!H24+3_Решение_фильтры!H25+H19 -> 282.22222
A21: cycles_h | B21: Циклов в час (номинально) | C21: рейсов/ч | D21: 3600/[t_cycle] | F21: =3600/F20 -> 10.519481 | G21: =3600/G20 -> 10.519481 | H21: =3600/H20 -> 12.755906
A22: eff_prod | B22: ЭФФЕКТИВНАЯ ПРОИЗВОДИТЕЛЬНОСТЬ РОБОТА = циклы × N_util × N_avail | C22: рейсов/ч | D22: [cycles_h]*N_util*N_avail | F22: =F21*N_util*N_avail -> 7.9948052 | G22: =G21*N_util*N_avail -> 7.9948052 | H22: =H21*N_util*N_avail -> 9.6944882
A23: n_robots | B23: КОЛИЧЕСТВО РОБОТОВ = ROUNDUP(пик / произв. × (1+резерв)) | C23: шт. | D23: IF([шаг 3: feasible]=1,MAX(1,ROUNDUP([шаг 4: peak_trips]/[eff_prod]*(1+N_reserve),0)),0) | F23: =IF(3_Решение_фильтры!F43=1,MAX(1,ROUNDUP(4_Потребность!F19/F22*(1+N_reserve),0)),0) -> 19 | G23: =IF(3_Решение_фильтры!G43=1,MAX(1,ROUNDUP(4_Потребность!G19/G22*(1+N_reserve),0)),0) -> 19 | H23: =IF(3_Решение_фильтры!H43=1,MAX(1,ROUNDUP(4_Потребность!H19/H22*(1+N_reserve),0)),0) -> 16
A24: n_chargers | B24: ЗАРЯДНЫХ СТАНЦИЙ = ROUNDUP(роботов / на станцию) | C24: шт. | D24: ROUNDUP([n_robots]/N_charger_ratio,0) | F24: =ROUNDUP(F23/N_charger_ratio,0) -> 5 | G24: =ROUNDUP(G23/N_charger_ratio,0) -> 5 | H24: =ROUNDUP(H23/N_charger_ratio,0) -> 4
A25: fleet_cap | B25: Пропускная способность парка (≥ пиковой потребности) | C25: рейсов/ч | D25: [n_robots]*[eff_prod] | F25: =F23*F22 -> 151.9013 | G25: =G23*G22 -> 151.9013 | H25: =H23*H22 -> 155.11181
A26: util_avg | B26: Среднесуточная загрузка парка | C26: % | D26: IF([n_robots]>0,[шаг 4: avg_h]*[шаг 4: trips_per_op]/([n_robots]*[cycles_h]),0) | F26: =IF(F23>0,4_Потребность!F17*4_Потребность!F16/(F23*F21),0) -> 0.43209877 | G26: =IF(G23>0,4_Потребность!G17*4_Потребность!G16/(G23*G21),0) -> 0.43209877 | H26: =IF(H23>0,4_Потребность!H17*4_Потребность!H16/(H23*H21),0) -> 0.42315516
A27: power_need | B27: Требуемая мощность станций | C27: кВт | D27: [n_chargers]*N_charger_kw | F27: =F24*N_charger_kw -> 25 | G27: =G24*N_charger_kw -> 25 | H27: =H24*N_charger_kw -> 20
A28: chk_power | B28: Проверка электроснабжения | D28: IF([power_need]<=P_power_kw,"ОК","Требуется усиление сети") | F28: =IF(F27<=P_power_kw,"ОК","Требуется усиление сети") -> ОК | G28: =IF(G27<=P_power_kw,"ОК","Требуется усиление сети") -> ОК | H28: =IF(H27<=P_power_kw,"ОК","Требуется усиление сети") -> ОК
A30: ВЫХОДЫ ШАГА → куда передаются
B31: n_robots, n_chargers → шаги 7, 8; t_cycle, eff_prod, fleet_cap, util_avg → шаг 12 (контрольные значения для симуляции).

Sheet 6_База
A1: ШАГ 6. БАЗОВЫЙ СЦЕНАРИЙ БЕЗ РОБОТИЗАЦИИ
A2: Не зависит от решения — одна колонка.
A4: ВХОДНЫЕ ПАРАМЕТРЫ ШАГА (откуда берутся и какого типа)
B5: Параметр | C5: Ед. | D5: Тип происхождения | E5: Источник (шаг / лист) | F5: Значение / ссылка
B6: Численность и оклады целевых групп | C6: чел., руб./мес. | D6: СЫРОЙ — датасет | E6: 1_Сырые_данные: g1_n, g1_sal, g2_n, g2_sal, g3_n | F6: =R_g1_n -> 25
B7: Доли функции групп в процессе | C7: доля | D7: ДОПУЩЕНИЕ — команда | E7: 2_Процесс: func1, func2, func3 | F7: =P_func1 -> 1
B8: Коэффициент ФОТ | C8: коэф. | D8: НОРМАТИВ — организатор | E8: 1b_Нормативы: N_fot | F8: =N_fot -> 1.302
A10: РАСЧЁТ ШАГА
A11: Ключ | B11: Показатель | C11: Ед. | D11: Формула (пояснение) | F11: Значение
A12: base_labor | B12: ФОТ персонала процесса = Σ численность × доля функции × оклад × 12 × N_fot | C12: руб./год | D12: P_base_labor | F12: =P_base_labor -> 46872000
A13: base_other | B13: Прочие текущие затраты процесса (ввод; в датасете нет) | C13: руб./год | D13: 0 | F13: =0 -> 0
A14: base_opex | B14: OPEX БАЗОВОГО СЦЕНАРИЯ | C14: руб./год | D14: [base_labor]+[base_other] | F14: =F12+F13 -> 46872000
A15: base_tco | B15: Совокупные затраты базы за горизонт | C15: руб. | D15: [base_opex]*P_horizon | F15: =F14*P_horizon -> 234360000
A17: ВЫХОДЫ ШАГА → куда передаются
B18: base_opex, base_tco → шаг 9 (ΔOPEX, эффект, TCO).

Sheet 7_CAPEX
A1: ШАГ 7. CAPEX ПО СТАТЬЯМ (ТЗ 3.5.2)
A2: Оборудование + инфраструктура + ПО + интеграция + доставка + ПНР + обучение + резерв.
A4: ВХОДНЫЕ ПАРАМЕТРЫ ШАГА (откуда берутся и какого типа)
B5: Параметр | C5: Ед. | D5: Тип происхождения | E5: Источник (шаг / лист) | F5: Значение (Покупка A) | G5: Значение (RaaS A) | H5: Значение (Покупка B)
B6: Количество роботов / станций | C6: шт. | D6: ПРЕДПОСЧИТАН — шаг 5 | E6: 5_Парк: n_robots, n_chargers | F6: =5_Парк!F23 -> 19 | G6: =5_Парк!G23 -> 19 | H6: =5_Парк!H23 -> 16
B7: Цена изделия | C7: руб. | D7: СЫРОЙ — каталог CSV | E7: 3_Решение_фильтры: price | F7: =3_Решение_фильтры!F21 -> 4300000 | G7: =3_Решение_фильтры!G21 -> 4300000 | H7: =3_Решение_фильтры!H21 -> 2700000
B8: Модель: покупка (1) / RaaS (0) | C8: 1/0 | D8: ПРЕДПОСЧИТАН — шаг 3 | E8: 3_Решение_фильтры: is_purchase | F8: =3_Решение_фильтры!F45 -> 1 | G8: =3_Решение_фильтры!G45 -> 0 | H8: =3_Решение_фильтры!H45 -> 1
B9: Подготовка объекта, % / интеграция, руб. | D9: ДОПУЩЕНИЕ — команда | E9: 2_Процесс: site_pct, integration | F9: =P_site_pct -> 0.05 | G9: =P_site_pct -> 0.05 | H9: =P_site_pct -> 0.05
B10: Нормативы: станция, ПО 10%, доставка 2%, ПНР 5%, обучение, резерв 10%, установочный платёж RaaS 5% | D10: НОРМАТИВ — организатор | E10: 1b_Нормативы | F10: =N_capex_reserve -> 0.1 | G10: =N_capex_reserve -> 0.1 | H10: =N_capex_reserve -> 0.1
B11: Бюджет объекта | C11: млн руб. | D11: СЫРОЙ — датасет | E11: 2_Процесс: budget | F11: =P_budget -> 80 | G11: =P_budget -> 80 | H11: =P_budget -> 80
A13: РАСЧЁТ ШАГА
A14: Ключ | B14: Показатель | C14: Ед. | D14: Формула (пояснение) | F14: Покупка A | G14: RaaS A | H14: Покупка B
A15: capex_equip | B15: Оборудование = роботов × цена (покупка) | C15: руб. | D15: [шаг 5: n_robots]*[шаг 3: price]*[шаг 3: is_purchase] | F15: =5_Парк!F23*3_Решение_фильтры!F21*3_Решение_фильтры!F45 -> 81700000 | G15: =5_Парк!G23*3_Решение_фильтры!G21*3_Решение_фильтры!G45 -> 0 | H15: =5_Парк!H23*3_Решение_фильтры!H21*3_Решение_фильтры!H45 -> 43200000
A16: capex_chargers | B16: Зарядные станции (покупка) | C16: руб. | D16: [шаг 5: n_chargers]*N_charger_price*[шаг 3: is_purchase] | F16: =5_Парк!F24*N_charger_price*3_Решение_фильтры!F45 -> 1250000 | G16: =5_Парк!G24*N_charger_price*3_Решение_фильтры!G45 -> 0 | H16: =5_Парк!H24*N_charger_price*3_Решение_фильтры!H45 -> 1000000
A17: capex_site | B17: Подготовка объекта = парк × цена × % | C17: руб. | D17: [шаг 5: n_robots]*[шаг 3: price]*P_site_pct | F17: =5_Парк!F23*3_Решение_фильтры!F21*P_site_pct -> 4085000 | G17: =5_Парк!G23*3_Решение_фильтры!G21*P_site_pct -> 4085000 | H17: =5_Парк!H23*3_Решение_фильтры!H21*P_site_pct -> 2160000
A18: capex_sw | B18: ПО управления флотом | C18: руб. | D18: [capex_equip]*N_sw_pct | F18: =F15*N_sw_pct -> 8170000 | G18: =G15*N_sw_pct -> 0 | H18: =H15*N_sw_pct -> 4320000
A19: capex_integ | B19: Интеграция с ИТ-системами | C19: руб. | D19: P_integration*IF([шаг 5: n_robots]>0,1,0) | F19: =P_integration*IF(5_Парк!F23>0,1,0) -> 2000000 | G19: =P_integration*IF(5_Парк!G23>0,1,0) -> 2000000 | H19: =P_integration*IF(5_Парк!H23>0,1,0) -> 2000000
A20: capex_delivery | B20: Доставка | C20: руб. | D20: [capex_equip]*N_delivery_pct | F20: =F15*N_delivery_pct -> 1634000 | G20: =G15*N_delivery_pct -> 0 | H20: =H15*N_delivery_pct -> 864000
A21: capex_pnr | B21: ПНР / установочный платёж RaaS | C21: руб. | D21: [capex_equip]*N_pnr_pct+(1-[шаг 3: is_purchase])*[шаг 5: n_robots]*[шаг 3: price]*N_raas_setup | F21: =F15*N_pnr_pct+(1-3_Решение_фильтры!F45)*5_Парк!F23*3_Решение_фильтры!F21*N_raas_setup -> 4085000 | G21: =G15*N_pnr_pct+(1-3_Решение_фильтры!G45)*5_Парк!G23*3_Решение_фильтры!G21*N_raas_setup -> 4085000 | H21: =H15*N_pnr_pct+(1-3_Решение_фильтры!H45)*5_Парк!H23*3_Решение_фильтры!H21*N_raas_setup -> 2160000
A22: capex_training | B22: Обучение | C22: руб. | D22: N_training*IF([шаг 5: n_robots]>0,1,0) | F22: =N_training*IF(5_Парк!F23>0,1,0) -> 300000 | G22: =N_training*IF(5_Парк!G23>0,1,0) -> 300000 | H22: =N_training*IF(5_Парк!H23>0,1,0) -> 300000
A23: capex_sub | B23: Итого до резерва | C23: руб. | D23: [capex_equip]+[capex_chargers]+[capex_site]+[capex_sw]+[capex_integ]+[capex_delivery]+[capex_pnr]+[capex_training] | F23: =F15+F16+F17+F18+F19+F20+F21+F22 -> 103224000 | G23: =G15+G16+G17+G18+G19+G20+G21+G22 -> 10470000 | H23: =H15+H16+H17+H18+H19+H20+H21+H22 -> 56004000
A24: capex_reserve | B24: Резерв | C24: руб. | D24: [capex_sub]*N_capex_reserve | F24: =F23*N_capex_reserve -> 10322400 | G24: =G23*N_capex_reserve -> 1047000 | H24: =H23*N_capex_reserve -> 5600400
A25: capex_total | B25: CAPEX ИТОГО | C25: руб. | D25: [capex_sub]+[capex_reserve] | F25: =F23+F24 -> 113546400 | G25: =G23+G24 -> 11517000 | H25: =H23+H24 -> 61604400
A26: chk_budget | B26: Проверка бюджета | D26: IF([capex_total]<=P_budget*1000000,"В бюджете","Превышает бюджет") | F26: =IF(F25<=P_budget*1000000,"В бюджете","Превышает бюджет") -> Превышает бюджет | G26: =IF(G25<=P_budget*1000000,"В бюджете","Превышает бюджет") -> В бюджете | H26: =IF(H25<=P_budget*1000000,"В бюджете","Превышает бюджет") -> В бюджете
A28: ВЫХОДЫ ШАГА → куда передаются
B29: capex_total, capex_equip → шаги 8 (проценты), 9, 10, 11.

Sheet 8_OPEX
A1: ШАГ 8. OPEX РОБОТИЗИРОВАННОГО СЦЕНАРИЯ (ТЗ 3.5.2)
A2: Сервис + лицензии + энергия + связь + расходники + ремонт + персонал эксплуатации (+ аренда при RaaS, + проценты при кредите).
A4: ВХОДНЫЕ ПАРАМЕТРЫ ШАГА (откуда берутся и какого типа)
B5: Параметр | C5: Ед. | D5: Тип происхождения | E5: Источник (шаг / лист) | F5: Значение (Покупка A) | G5: Значение (RaaS A) | H5: Значение (Покупка B)
B6: Количество роботов | C6: шт. | D6: ПРЕДПОСЧИТАН — шаг 5 | E6: 5_Парк: n_robots | F6: =5_Парк!F23 -> 19 | G6: =5_Парк!G23 -> 19 | H6: =5_Парк!H23 -> 16
B7: Цена изделия / оборудование CAPEX | C7: руб. | D7: ПРЕДПОСЧИТАН — шаг 7 | E7: 3: price; 7: capex_equip, capex_total | F7: =7_CAPEX!F15 -> 81700000 | G7: =7_CAPEX!G15 -> 0 | H7: =7_CAPEX!H15 -> 43200000
B8: Мощность робота | C8: кВт | D8: ДОПУЩЕНИЕ — команда | E8: 3_Решение_фильтры: power | F8: =3_Решение_фильтры!F26 -> 3 | G8: =3_Решение_фильтры!G26 -> 3 | H8: =3_Решение_фильтры!H26 -> 1
B9: Часов работы в сутки, смен, потери, оклад оператора флота | D9: ПРЕДПОСЧИТАН — шаг 2 | E9: 2_Процесс: hours_day, shifts, loss_k, fleet_per_shift, fleet_sal | F9: =P_hours_day -> 22 | G9: =P_hours_day -> 22 | H9: =P_hours_day -> 22
B10: Нормативы: RaaS 3%/мес, сервис 8%, лицензии 3%, ремонт 2%, тариф 7.5, связь, кредит | D10: НОРМАТИВ — организатор | E10: 1b_Нормативы | F10: =N_service_pct -> 0.08 | G10: =N_service_pct -> 0.08 | H10: =N_service_pct -> 0.08
B11: Расходники на робота | C11: руб./год | D11: ДОПУЩЕНИЕ — команда | E11: 2_Процесс: consum_per_robot | F11: =P_consum_per_robot -> 0 | G11: =P_consum_per_robot -> 0 | H11: =P_consum_per_robot -> 0
A13: РАСЧЁТ ШАГА
A14: Ключ | B14: Показатель | C14: Ед. | D14: Формула (пояснение) | F14: Покупка A | G14: RaaS A | H14: Покупка B
A15: opex_rent | B15: Платёж RaaS = роботов × цена × ставка × 12 | C15: руб./год | D15: (1-[шаг 3: is_purchase])*[шаг 5: n_robots]*[шаг 3: price]*N_raas_pct*12 | F15: =(1-3_Решение_фильтры!F45)*5_Парк!F23*3_Решение_фильтры!F21*N_raas_pct*12 -> 0 | G15: =(1-3_Решение_фильтры!G45)*5_Парк!G23*3_Решение_фильтры!G21*N_raas_pct*12 -> 29412000 | H15: =(1-3_Решение_фильтры!H45)*5_Парк!H23*3_Решение_фильтры!H21*N_raas_pct*12 -> 0
A16: opex_service | B16: Сервисный контракт (покупка) | C16: руб./год | D16: [шаг 3: is_purchase]*[шаг 7: capex_equip]*N_service_pct | F16: =3_Решение_фильтры!F45*7_CAPEX!F15*N_service_pct -> 6536000 | G16: =3_Решение_фильтры!G45*7_CAPEX!G15*N_service_pct -> 0 | H16: =3_Решение_фильтры!H45*7_CAPEX!H15*N_service_pct -> 3456000
A17: opex_license | B17: Лицензии ПО (покупка) | C17: руб./год | D17: [шаг 3: is_purchase]*[шаг 7: capex_equip]*N_license_pct | F17: =3_Решение_фильтры!F45*7_CAPEX!F15*N_license_pct -> 2451000 | G17: =3_Решение_фильтры!G45*7_CAPEX!G15*N_license_pct -> 0 | H17: =3_Решение_фильтры!H45*7_CAPEX!H15*N_license_pct -> 1296000
A18: opex_repair | B18: Ремонт вне контракта (покупка) | C18: руб./год | D18: [шаг 3: is_purchase]*[шаг 7: capex_equip]*N_repair_pct | F18: =3_Решение_фильтры!F45*7_CAPEX!F15*N_repair_pct -> 1634000 | G18: =3_Решение_фильтры!G45*7_CAPEX!G15*N_repair_pct -> 0 | H18: =3_Решение_фильтры!H45*7_CAPEX!H15*N_repair_pct -> 864000
A19: opex_energy | B19: Электроэнергия = роботов × кВт × ч/сут × 365 × тариф | C19: руб./год | D19: [шаг 5: n_robots]*[шаг 3: power]*P_hours_day*365*N_energy_price | F19: =5_Парк!F23*3_Решение_фильтры!F26*P_hours_day*365*N_energy_price -> 3432825 | G19: =5_Парк!G23*3_Решение_фильтры!G26*P_hours_day*365*N_energy_price -> 3432825 | H19: =5_Парк!H23*3_Решение_фильтры!H26*P_hours_day*365*N_energy_price -> 963600
A20: opex_connect | B20: Связь | C20: руб./год | D20: N_connect*IF([шаг 5: n_robots]>0,1,0) | F20: =N_connect*IF(5_Парк!F23>0,1,0) -> 60000 | G20: =N_connect*IF(5_Парк!G23>0,1,0) -> 60000 | H20: =N_connect*IF(5_Парк!H23>0,1,0) -> 60000
A21: opex_consum | B21: Расходники | C21: руб./год | D21: P_consum_per_robot*[шаг 5: n_robots] | F21: =P_consum_per_robot*5_Парк!F23 -> 0 | G21: =P_consum_per_robot*5_Парк!G23 -> 0 | H21: =P_consum_per_robot*5_Парк!H23 -> 0
A22: opex_fleet | B22: Персонал эксплуатации = чел./смену × смен × (1+потери) × оклад × 12 × N_fot | C22: руб./год | D22: P_fleet_per_shift*P_shifts*(1+P_loss_k)*P_fleet_sal*12*N_fot*IF([шаг 5: n_robots]>0,1,0) | F22: =P_fleet_per_shift*P_shifts*(1+P_loss_k)*P_fleet_sal*12*N_fot*IF(5_Парк!F23>0,1,0) -> 4687200 | G22: =P_fleet_per_shift*P_shifts*(1+P_loss_k)*P_fleet_sal*12*N_fot*IF(5_Парк!G23>0,1,0) -> 4687200 | H22: =P_fleet_per_shift*P_shifts*(1+P_loss_k)*P_fleet_sal*12*N_fot*IF(5_Парк!H23>0,1,0) -> 4687200
A23: opex_loan | B23: Обслуживание долга (если доля кредита > 0) | C23: руб./год | D23: [шаг 3: is_purchase]*[шаг 7: capex_total]*N_loan_share*N_loan_rate*(N_loan_years+1)/(2*N_loan_years) | F23: =3_Решение_фильтры!F45*7_CAPEX!F25*N_loan_share*N_loan_rate*(N_loan_years+1)/(2*N_loan_years) -> 0 | G23: =3_Решение_фильтры!G45*7_CAPEX!G25*N_loan_share*N_loan_rate*(N_loan_years+1)/(2*N_loan_years) -> 0 | H23: =3_Решение_фильтры!H45*7_CAPEX!H25*N_loan_share*N_loan_rate*(N_loan_years+1)/(2*N_loan_years) -> 0
A24: opex_robot | B24: OPEX РЕШЕНИЯ ИТОГО (дополнительный OPEX) | C24: руб./год | D24: [opex_rent]+[opex_service]+[opex_license]+[opex_repair]+[opex_energy]+[opex_connect]+[opex_consum]+[opex_fleet]+[opex_loan] | F24: =F15+F16+F17+F18+F19+F20+F21+F22+F23 -> 18801025 | G24: =G15+G16+G17+G18+G19+G20+G21+G22+G23 -> 37592025 | H24: =H15+H16+H17+H18+H19+H20+H21+H22+H23 -> 11326800
A26: ВЫХОДЫ ШАГА → куда передаются
B27: opex_robot → шаги 9, 10, 11.

Sheet 9_Эффект
A1: ШАГ 9. ЭФФЕКТ, ОКУПАЕМОСТЬ, ROI, TCO, ИНТЕРПРЕТАЦИЯ
A2: Все входы — предпосчитанные на шагах 2, 3, 6, 7, 8 плюс нормативы.
A4: ВХОДНЫЕ ПАРАМЕТРЫ ШАГА (откуда берутся и какого типа)
B5: Параметр | C5: Ед. | D5: Тип происхождения | E5: Источник (шаг / лист) | F5: Значение (Покупка A) | G5: Значение (RaaS A) | H5: Значение (Покупка B)
B6: OPEX базы / совокупные затраты базы | C6: руб./год | D6: ПРЕДПОСЧИТАН — шаг 6 | E6: 6_База: base_opex, base_tco | F6: =6_База!F14 -> 46872000 | G6: =6_База!F14 -> 46872000 | H6: =6_База!F14 -> 46872000
B7: Целевые FTE и их ФОТ; средний оклад; текучесть | D7: ПРЕДПОСЧИТАН — шаг 2 | E7: 2_Процесс: fte_target, labor_target, sal_target, turnover | F7: =P_fte_target -> 23.75 | G7: =P_fte_target -> 23.75 | H7: =P_fte_target -> 23.75
B8: Коэффициент замещения; применимость | D8: ДОПУЩЕНИЕ — команда | E8: 3_Решение_фильтры: repl, feasible, status, conf | F8: =3_Решение_фильтры!F30 -> 0.8 | G8: =3_Решение_фильтры!G30 -> 0.8 | H8: =3_Решение_фильтры!H30 -> 0.6
B9: CAPEX итого / оборудование | C9: руб. | D9: ПРЕДПОСЧИТАН — шаг 7 | E9: 7_CAPEX | F9: =7_CAPEX!F25 -> 113546400 | G9: =7_CAPEX!G25 -> 11517000 | H9: =7_CAPEX!H25 -> 61604400
B10: OPEX решения | C10: руб./год | D10: ПРЕДПОСЧИТАН — шаг 8 | E10: 8_OPEX: opex_robot | F10: =8_OPEX!F24 -> 18801025 | G10: =8_OPEX!G24 -> 37592025 | H10: =8_OPEX!H24 -> 11326800
B11: Горизонт, срок АКБ, доля замены АКБ, срок службы, пороги интерпретации | D11: НОРМАТИВ — организатор | E11: 2_Процесс: horizon; 1b_Нормативы | F11: =P_horizon -> 5 | G11: =P_horizon -> 5 | H11: =P_horizon -> 5
B12: Иные эффекты (ввод) | C12: руб./год | D12: ДОПУЩЕНИЕ — команда | E12: 2_Процесс: other_effects | F12: =P_other_effects -> 0 | G12: =P_other_effects -> 0 | H12: =P_other_effects -> 0
A14: РАСЧЁТ ШАГА
A15: Ключ | B15: Показатель | C15: Ед. | D15: Формула (пояснение) | F15: Покупка A | G15: RaaS A | H15: Покупка B
A16: fte_freed | B16: Высвобождаемый персонал = целевые FTE × замещение | C16: FTE | D16: P_fte_target*[шаг 3: repl]*[шаг 3: feasible] | F16: =P_fte_target*3_Решение_фильтры!F30*3_Решение_фильтры!F43 -> 19 | G16: =P_fte_target*3_Решение_фильтры!G30*3_Решение_фильтры!G43 -> 19 | H16: =P_fte_target*3_Решение_фильтры!H30*3_Решение_фильтры!H43 -> 14.25
A17: labor_saving | B17: Экономия ФОТ | C17: руб./год | D17: P_labor_target*[шаг 3: repl]*[шаг 3: feasible] | F17: =P_labor_target*3_Решение_фильтры!F30*3_Решение_фильтры!F43 -> 35622720 | G17: =P_labor_target*3_Решение_фильтры!G30*3_Решение_фильтры!G43 -> 35622720 | H17: =P_labor_target*3_Решение_фильтры!H30*3_Решение_фильтры!H43 -> 26717040
A18: labor_remaining | B18: Остаточный ФОТ | C18: руб./год | D18: [шаг 6: base_opex]-[labor_saving] | F18: =6_База!F14-F17 -> 11249280 | G18: =6_База!F14-G17 -> 11249280 | H18: =6_База!F14-H17 -> 20154960
A19: opex_new_total | B19: OPEX сценария итого = остаточный ФОТ + OPEX решения | C19: руб./год | D19: [labor_remaining]+[шаг 8: opex_robot] | F19: =F18+8_OPEX!F24 -> 30050305 | G19: =G18+8_OPEX!G24 -> 48841305 | H19: =H18+8_OPEX!H24 -> 31481760
A20: delta_opex | B20: ΔOPEX к базе (минус = экономия) | C20: руб./год | D20: [opex_new_total]-[шаг 6: base_opex] | F20: =F19-6_База!F14 -> -16821695 | G20: =G19-6_База!F14 -> 1969305 | H20: =H19-6_База!F14 -> -15390240
A21: hire_saving | B21: Экономия на подборе = FTE × текучесть × стоимость замены × оклад | C21: руб./год | D21: [fte_freed]*P_turnover*N_hire_cost*P_sal_target | F21: =F16*P_turnover*N_hire_cost*P_sal_target -> 0 | G21: =G16*P_turnover*N_hire_cost*P_sal_target -> 0 | H21: =H16*P_turnover*N_hire_cost*P_sal_target -> 0
A22: other_eff | B22: Иные эффекты | C22: руб./год | D22: P_other_effects*[шаг 3: feasible] | F22: =P_other_effects*3_Решение_фильтры!F43 -> 0 | G22: =P_other_effects*3_Решение_фильтры!G43 -> 0 | H22: =P_other_effects*3_Решение_фильтры!H43 -> 0
A23: effect_net | B23: ЧИСТЫЙ ГОДОВОЙ ЭФФЕКТ = (OPEX база − OPEX сцен.) + подбор + иные | C23: руб./год | D23: [шаг 6: base_opex]-[opex_new_total]+[hire_saving]+[other_eff] | F23: =6_База!F14-F19+F21+F22 -> 16821695 | G23: =6_База!F14-G19+G21+G22 -> -1969305 | H23: =6_База!F14-H19+H21+H22 -> 15390240
A24: amort | B24: Амортизация (линейно, N_life; RaaS = 0) | C24: руб./год | D24: [шаг 7: capex_total]/N_life*[шаг 3: is_purchase] | F24: =7_CAPEX!F25/N_life*3_Решение_фильтры!F45 -> 16220914 | G24: =7_CAPEX!G25/N_life*3_Решение_фильтры!G45 -> 0 | H24: =7_CAPEX!H25/N_life*3_Решение_фильтры!H45 -> 8800628.6
A25: effect_amort | B25: Эффект с учётом амортизации (учётный) | C25: руб./год | D25: [effect_net]-[amort] | F25: =F23-F24 -> 600780.71 | G25: =G23-G24 -> -1969305 | H25: =H23-H24 -> 6589611.4
A26: payback | B26: ПРОСТОЙ СРОК ОКУПАЕМОСТИ = CAPEX / эффект | C26: лет | D26: IF(AND([шаг 3: feasible]=1,[effect_net]>0),[шаг 7: capex_total]/[effect_net],"не окупается") | F26: =IF(AND(3_Решение_фильтры!F43=1,F23>0),7_CAPEX!F25/F23,"не окупается") -> 6.7499975 | G26: =IF(AND(3_Решение_фильтры!G43=1,G23>0),7_CAPEX!G25/G23,"не окупается") -> не окупается | H26: =IF(AND(3_Решение_фильтры!H43=1,H23>0),7_CAPEX!H25/H23,"не окупается") -> 4.0028226
A27: batt_events | B27: Замен АКБ = INT((горизонт−1)/срок АКБ) (покупка) | C27: шт. | D27: [шаг 3: is_purchase]*INT((P_horizon-1)/N_battery_life) | F27: =3_Решение_фильтры!F45*INT((P_horizon-1)/N_battery_life) -> 1 | G27: =3_Решение_фильтры!G45*INT((P_horizon-1)/N_battery_life) -> 0 | H27: =3_Решение_фильтры!H45*INT((P_horizon-1)/N_battery_life) -> 1
A28: batt_cost | B28: Стоимость замены АКБ на парк | C28: руб. | D28: [шаг 7: capex_equip]*N_battery_share | F28: =7_CAPEX!F15*N_battery_share -> 8170000 | G28: =7_CAPEX!G15*N_battery_share -> 0 | H28: =7_CAPEX!H15*N_battery_share -> 4320000
A29: cum_effect | B29: Накопленный эффект за горизонт | C29: руб. | D29: [effect_net]*P_horizon-[batt_events]*[batt_cost] | F29: =F23*P_horizon-F27*F28 -> 75938475 | G29: =G23*P_horizon-G27*G28 -> -9846525 | H29: =H23*P_horizon-H27*H28 -> 72631200
A30: roi | B30: ROI (ТЗ) = накопленный эффект / CAPEX | C30: % | D30: IF([шаг 7: capex_total]>0,[cum_effect]/[шаг 7: capex_total],"—") | F30: =IF(7_CAPEX!F25>0,F29/7_CAPEX!F25,"—") -> 0.66878805 | G30: =IF(7_CAPEX!G25>0,G29/7_CAPEX!G25,"—") -> -0.85495572 | H30: =IF(7_CAPEX!H25>0,H29/7_CAPEX!H25,"—") -> 1.1789937
A31: roi_simple | B31: Cumulative simple ROI = (накопл. эффект − CAPEX) / CAPEX | C31: % | D31: IF([шаг 7: capex_total]>0,([cum_effect]-[шаг 7: capex_total])/[шаг 7: capex_total],"—") | F31: =IF(7_CAPEX!F25>0,(F29-7_CAPEX!F25)/7_CAPEX!F25,"—") -> -0.33121195 | G31: =IF(7_CAPEX!G25>0,(G29-7_CAPEX!G25)/7_CAPEX!G25,"—") -> -1.8549557 | H31: =IF(7_CAPEX!H25>0,(H29-7_CAPEX!H25)/7_CAPEX!H25,"—") -> 0.17899371
A32: tco_solution | B32: TCO РЕШЕНИЯ = CAPEX + OPEX решения × горизонт + замены АКБ | C32: руб. | D32: [шаг 7: capex_total]+[шаг 8: opex_robot]*P_horizon+[batt_events]*[batt_cost] | F32: =7_CAPEX!F25+8_OPEX!F24*P_horizon+F27*F28 -> 215721525 | G32: =7_CAPEX!G25+8_OPEX!G24*P_horizon+G27*G28 -> 199477125 | H32: =7_CAPEX!H25+8_OPEX!H24*P_horizon+H27*H28 -> 122558400
A33: tco_new | B33: Совокупные затраты процесса за горизонт (сценарий) | C33: руб. | D33: [шаг 7: capex_total]+[opex_new_total]*P_horizon+[batt_events]*[batt_cost] | F33: =7_CAPEX!F25+F19*P_horizon+F27*F28 -> 271967925 | G33: =7_CAPEX!G25+G19*P_horizon+G27*G28 -> 255723525 | H33: =7_CAPEX!H25+H19*P_horizon+H27*H28 -> 223333200
A34: tco_delta | B34: Разница к базе (минус = выгода) | C34: руб. | D34: [tco_new]-[шаг 6: base_tco] | F34: =F33-6_База!F15 -> 37607925 | G34: =G33-6_База!F15 -> 21363525 | H34: =H33-6_База!F15 -> -11026800
A35: verdict | B35: ИНТЕРПРЕТАЦИЯ (ТЗ 3.5.7) | D35: IF([шаг 3: feasible]=0,"Не применимо",IF([effect_net]<=0,"Не окупается",IF([payback]<=N_pb_good,"Высокая целесообразность",IF([payback]<=N_pb_mid,"Средняя — рекомендован пилот","Низкая — требует уточнения данных")))) | F35: =IF(3_Решение_фильтры!F43=0,"Не применимо",IF(F23<=0,"Не окупается",IF(F26<=N_pb_good,"Высокая целесообразность",IF(F26<=N_pb_mid,"Средняя — рекомендован пилот","Низкая — требует уточнения данных")))) -> Низкая — требует уточнения данных | G35: =IF(3_Решение_фильтры!G43=0,"Не применимо",IF(G23<=0,"Не окупается",IF(G26<=N_pb_good,"Высокая целесообразность",IF(G26<=N_pb_mid,"Средняя — рекомендован пилот","Низкая — требует уточнения данных")))) -> Не окупается | H35: =IF(3_Решение_фильтры!H43=0,"Не применимо",IF(H23<=0,"Не окупается",IF(H26<=N_pb_good,"Высокая целесообразность",IF(H26<=N_pb_mid,"Средняя — рекомендован пилот","Низкая — требует уточнения данных")))) -> Средняя — рекомендован пилот
A36: risks | B36: Риски | D36: IF([шаг 3: sol_status]<>"operation","Зрелость: "&[шаг 3: sol_status]&"; ","")&IF([шаг 3: sol_conf]<>"Да","ТТХ требуют подтверждения; ","")&IF([шаг 7: chk_budget]="Превышает бюджет","CAPEX выше бюджета; ","")&IF([шаг 5: chk_power]<>"ОК","мощность сети; ","")&IF([шаг 5: util_avg]<0.3,"парк рассчитан на пик (низкая средняя загрузка); ","") | F36: =IF(3_Решение_фильтры!F19<>"operation","Зрелость: "&3_Решение_фильтры!F19&"; ","")&IF(3_Решение_фильтры!F20<>"Да","ТТХ требуют подтверждения; ","")&IF(7_CAPEX!F26="Превышает бюджет","CAPEX выше бюджета; ","")&IF(5_Парк!F28<>"ОК","мощность сети; ","")&IF(5_Парк!F26<0.3,"парк рассчитан на пик (низкая средняя загрузка); ","") -> Зрелость: piloting; ТТХ требуют подтверждения; CAPEX выше бюджета; | G36: =IF(3_Решение_фильтры!G19<>"operation","Зрелость: "&3_Решение_фильтры!G19&"; ","")&IF(3_Решение_фильтры!G20<>"Да","ТТХ требуют подтверждения; ","")&IF(7_CAPEX!G26="Превышает бюджет","CAPEX выше бюджета; ","")&IF(5_Парк!G28<>"ОК","мощность сети; ","")&IF(5_Парк!G26<0.3,"парк рассчитан на пик (низкая средняя загрузка); ","") -> Зрелость: piloting; ТТХ требуют подтверждения; | H36: =IF(3_Решение_фильтры!H19<>"operation","Зрелость: "&3_Решение_фильтры!H19&"; ","")&IF(3_Решение_фильтры!H20<>"Да","ТТХ требуют подтверждения; ","")&IF(7_CAPEX!H26="Превышает бюджет","CAPEX выше бюджета; ","")&IF(5_Парк!H28<>"ОК","мощность сети; ","")&IF(5_Парк!H26<0.3,"парк рассчитан на пик (низкая средняя загрузка); ","")
A38: ВЫХОДЫ ШАГА → куда передаются
B39: effect_net, payback, roi, tco → шаги 10, 13; verdict, risks → отчёт; effect_net, batt_cost → шаг 10.

Sheet 10_ДенПоток
A1: ШАГ 10. ДЕНЕЖНЫЙ ПОТОК ПО ГОДАМ, NPV, IRR, ДИСКОНТИРОВАННАЯ ОКУПАЕМОСТЬ
A2: Входы: CAPEX (шаг 7), чистый эффект и замена АКБ (шаг 9), горизонт (шаг 2), N_discount, N_residual_pct (1b). Год 0 = −CAPEX; последний год горизонта + остаточная стоимость.
B4: Год | C4: Покупка A: поток | D4: Покупка A: накопл. | E4: Покупка A: дисконт. накопл. | F4: RaaS A: поток | G4: RaaS A: накопл. | H4: RaaS A: дисконт. накопл. | I4: Покупка B: поток | J4: Покупка B: накопл. | K4: Покупка B: дисконт. накопл.
B5: 0 | C5: =-7_CAPEX!F25 -> -113546400 | D5: =C5 -> -113546400 | E5: =C5 -> -113546400 | F5: =-7_CAPEX!G25 -> -11517000 | G5: =F5 -> -11517000 | H5: =F5 -> -11517000 | I5: =-7_CAPEX!H25 -> -61604400 | J5: =I5 -> -61604400 | K5: =I5 -> -61604400
B6: 1 | C6: =IF(1<=P_horizon,9_Эффект!F23-IF(AND(3_Решение_фильтры!F45=1,MOD(1,N_battery_life)=0,1<=P_horizon-1),9_Эффект!F28,0)+IF(1=P_horizon,7_CAPEX!F15*N_residual_pct,0),0) -> 16821695 | D6: =D5+C6 -> -96724705 | E6: =E5+C6/(1+N_discount)^1 -> -98918839 | F6: =IF(1<=P_horizon,9_Эффект!G23-IF(AND(3_Решение_фильтры!G45=1,MOD(1,N_battery_life)=0,1<=P_horizon-1),9_Эффект!G28,0)+IF(1=P_horizon,7_CAPEX!G15*N_residual_pct,0),0) -> -1969305 | G6: =G5+F6 -> -13486305 | H6: =H5+F6/(1+N_discount)^1 -> -13229439 | I6: =IF(1<=P_horizon,9_Эффект!H23-IF(AND(3_Решение_фильтры!H45=1,MOD(1,N_battery_life)=0,1<=P_horizon-1),9_Эффект!H28,0)+IF(1=P_horizon,7_CAPEX!H15*N_residual_pct,0),0) -> 15390240 | J6: =J5+I6 -> -46214160 | K6: =K5+I6/(1+N_discount)^1 -> -48221583
B7: 2 | C7: =IF(2<=P_horizon,9_Эффект!F23-IF(AND(3_Решение_фильтры!F45=1,MOD(2,N_battery_life)=0,2<=P_horizon-1),9_Эффект!F28,0)+IF(2=P_horizon,7_CAPEX!F15*N_residual_pct,0),0) -> 16821695 | D7: =D6+C7 -> -79903010 | E7: =E6+C7/(1+N_discount)^2 -> -86199221 | F7: =IF(2<=P_horizon,9_Эффект!G23-IF(AND(3_Решение_фильтры!G45=1,MOD(2,N_battery_life)=0,2<=P_horizon-1),9_Эффект!G28,0)+IF(2=P_horizon,7_CAPEX!G15*N_residual_pct,0),0) -> -1969305 | G7: =G6+F7 -> -15455610 | H7: =H6+F7/(1+N_discount)^2 -> -14718517 | I7: =IF(2<=P_horizon,9_Эффект!H23-IF(AND(3_Решение_фильтры!H45=1,MOD(2,N_battery_life)=0,2<=P_horizon-1),9_Эффект!H28,0)+IF(2=P_horizon,7_CAPEX!H15*N_residual_pct,0),0) -> 15390240 | J7: =J6+I7 -> -30823920 | K7: =K6+I7/(1+N_discount)^2 -> -36584350
B8: 3 | C8: =IF(3<=P_horizon,9_Эффект!F23-IF(AND(3_Решение_фильтры!F45=1,MOD(3,N_battery_life)=0,3<=P_horizon-1),9_Эффект!F28,0)+IF(3=P_horizon,7_CAPEX!F15*N_residual_pct,0),0) -> 16821695 | D8: =D7+C8 -> -63081315 | E8: =E7+C8/(1+N_discount)^3 -> -75138683 | F8: =IF(3<=P_horizon,9_Эффект!G23-IF(AND(3_Решение_фильтры!G45=1,MOD(3,N_battery_life)=0,3<=P_horizon-1),9_Эффект!G28,0)+IF(3=P_horizon,7_CAPEX!G15*N_residual_pct,0),0) -> -1969305 | G8: =G7+F8 -> -17424915 | H8: =H7+F8/(1+N_discount)^3 -> -16013367 | I8: =IF(3<=P_horizon,9_Эффект!H23-IF(AND(3_Решение_фильтры!H45=1,MOD(3,N_battery_life)=0,3<=P_horizon-1),9_Эффект!H28,0)+IF(3=P_horizon,7_CAPEX!H15*N_residual_pct,0),0) -> 15390240 | J8: =J7+I8 -> -15433680 | K8: =K7+I8/(1+N_discount)^3 -> -26465017
B9: 4 | C9: =IF(4<=P_horizon,9_Эффект!F23-IF(AND(3_Решение_фильтры!F45=1,MOD(4,N_battery_life)=0,4<=P_horizon-1),9_Эффект!F28,0)+IF(4=P_horizon,7_CAPEX!F15*N_residual_pct,0),0) -> 8651695 | D9: =D8+C9 -> -54429620 | E9: =E8+C9/(1+N_discount)^4 -> -70192049 | F9: =IF(4<=P_horizon,9_Эффект!G23-IF(AND(3_Решение_фильтры!G45=1,MOD(4,N_battery_life)=0,4<=P_horizon-1),9_Эффект!G28,0)+IF(4=P_horizon,7_CAPEX!G15*N_residual_pct,0),0) -> -1969305 | G9: =G8+F9 -> -19394220 | H9: =H8+F9/(1+N_discount)^4 -> -17139323 | I9: =IF(4<=P_horizon,9_Эффект!H23-IF(AND(3_Решение_фильтры!H45=1,MOD(4,N_battery_life)=0,4<=P_horizon-1),9_Эффект!H28,0)+IF(4=P_horizon,7_CAPEX!H15*N_residual_pct,0),0) -> 11070240 | J9: =J8+I9 -> -4363440 | K9: =K8+I9/(1+N_discount)^4 -> -20135572
B10: 5 | C10: =IF(5<=P_horizon,9_Эффект!F23-IF(AND(3_Решение_фильтры!F45=1,MOD(5,N_battery_life)=0,5<=P_horizon-1),9_Эффект!F28,0)+IF(5=P_horizon,7_CAPEX!F15*N_residual_pct,0),0) -> 16821695 | D10: =D9+C10 -> -37607925 | E10: =E9+C10/(1+N_discount)^5 -> -61828693 | F10: =IF(5<=P_horizon,9_Эффект!G23-IF(AND(3_Решение_фильтры!G45=1,MOD(5,N_battery_life)=0,5<=P_horizon-1),9_Эффект!G28,0)+IF(5=P_horizon,7_CAPEX!G15*N_residual_pct,0),0) -> -1969305 | G10: =G9+F10 -> -21363525 | H10: =H9+F10/(1+N_discount)^5 -> -18118416 | I10: =IF(5<=P_horizon,9_Эффект!H23-IF(AND(3_Решение_фильтры!H45=1,MOD(5,N_battery_life)=0,5<=P_horizon-1),9_Эффект!H28,0)+IF(5=P_horizon,7_CAPEX!H15*N_residual_pct,0),0) -> 15390240 | J10: =J9+I10 -> 11026800 | K10: =K9+I10/(1+N_discount)^5 -> -12483903
B11: 6 | C11: =IF(6<=P_horizon,9_Эффект!F23-IF(AND(3_Решение_фильтры!F45=1,MOD(6,N_battery_life)=0,6<=P_horizon-1),9_Эффект!F28,0)+IF(6=P_horizon,7_CAPEX!F15*N_residual_pct,0),0) -> 0 | D11: =D10+C11 -> -37607925 | E11: =E10+C11/(1+N_discount)^6 -> -61828693 | F11: =IF(6<=P_horizon,9_Эффект!G23-IF(AND(3_Решение_фильтры!G45=1,MOD(6,N_battery_life)=0,6<=P_horizon-1),9_Эффект!G28,0)+IF(6=P_horizon,7_CAPEX!G15*N_residual_pct,0),0) -> 0 | G11: =G10+F11 -> -21363525 | H11: =H10+F11/(1+N_discount)^6 -> -18118416 | I11: =IF(6<=P_horizon,9_Эффект!H23-IF(AND(3_Решение_фильтры!H45=1,MOD(6,N_battery_life)=0,6<=P_horizon-1),9_Эффект!H28,0)+IF(6=P_horizon,7_CAPEX!H15*N_residual_pct,0),0) -> 0 | J11: =J10+I11 -> 11026800 | K11: =K10+I11/(1+N_discount)^6 -> -12483903
B12: 7 | C12: =IF(7<=P_horizon,9_Эффект!F23-IF(AND(3_Решение_фильтры!F45=1,MOD(7,N_battery_life)=0,7<=P_horizon-1),9_Эффект!F28,0)+IF(7=P_horizon,7_CAPEX!F15*N_residual_pct,0),0) -> 0 | D12: =D11+C12 -> -37607925 | E12: =E11+C12/(1+N_discount)^7 -> -61828693 | F12: =IF(7<=P_horizon,9_Эффект!G23-IF(AND(3_Решение_фильтры!G45=1,MOD(7,N_battery_life)=0,7<=P_horizon-1),9_Эффект!G28,0)+IF(7=P_horizon,7_CAPEX!G15*N_residual_pct,0),0) -> 0 | G12: =G11+F12 -> -21363525 | H12: =H11+F12/(1+N_discount)^7 -> -18118416 | I12: =IF(7<=P_horizon,9_Эффект!H23-IF(AND(3_Решение_фильтры!H45=1,MOD(7,N_battery_life)=0,7<=P_horizon-1),9_Эффект!H28,0)+IF(7=P_horizon,7_CAPEX!H15*N_residual_pct,0),0) -> 0 | J12: =J11+I12 -> 11026800 | K12: =K11+I12/(1+N_discount)^7 -> -12483903
B13: 8 | C13: =IF(8<=P_horizon,9_Эффект!F23-IF(AND(3_Решение_фильтры!F45=1,MOD(8,N_battery_life)=0,8<=P_horizon-1),9_Эффект!F28,0)+IF(8=P_horizon,7_CAPEX!F15*N_residual_pct,0),0) -> 0 | D13: =D12+C13 -> -37607925 | E13: =E12+C13/(1+N_discount)^8 -> -61828693 | F13: =IF(8<=P_horizon,9_Эффект!G23-IF(AND(3_Решение_фильтры!G45=1,MOD(8,N_battery_life)=0,8<=P_horizon-1),9_Эффект!G28,0)+IF(8=P_horizon,7_CAPEX!G15*N_residual_pct,0),0) -> 0 | G13: =G12+F13 -> -21363525 | H13: =H12+F13/(1+N_discount)^8 -> -18118416 | I13: =IF(8<=P_horizon,9_Эффект!H23-IF(AND(3_Решение_фильтры!H45=1,MOD(8,N_battery_life)=0,8<=P_horizon-1),9_Эффект!H28,0)+IF(8=P_horizon,7_CAPEX!H15*N_residual_pct,0),0) -> 0 | J13: =J12+I13 -> 11026800 | K13: =K12+I13/(1+N_discount)^8 -> -12483903
B14: 9 | C14: =IF(9<=P_horizon,9_Эффект!F23-IF(AND(3_Решение_фильтры!F45=1,MOD(9,N_battery_life)=0,9<=P_horizon-1),9_Эффект!F28,0)+IF(9=P_horizon,7_CAPEX!F15*N_residual_pct,0),0) -> 0 | D14: =D13+C14 -> -37607925 | E14: =E13+C14/(1+N_discount)^9 -> -61828693 | F14: =IF(9<=P_horizon,9_Эффект!G23-IF(AND(3_Решение_фильтры!G45=1,MOD(9,N_battery_life)=0,9<=P_horizon-1),9_Эффект!G28,0)+IF(9=P_horizon,7_CAPEX!G15*N_residual_pct,0),0) -> 0 | G14: =G13+F14 -> -21363525 | H14: =H13+F14/(1+N_discount)^9 -> -18118416 | I14: =IF(9<=P_horizon,9_Эффект!H23-IF(AND(3_Решение_фильтры!H45=1,MOD(9,N_battery_life)=0,9<=P_horizon-1),9_Эффект!H28,0)+IF(9=P_horizon,7_CAPEX!H15*N_residual_pct,0),0) -> 0 | J14: =J13+I14 -> 11026800 | K14: =K13+I14/(1+N_discount)^9 -> -12483903
B15: 10 | C15: =IF(10<=P_horizon,9_Эффект!F23-IF(AND(3_Решение_фильтры!F45=1,MOD(10,N_battery_life)=0,10<=P_horizon-1),9_Эффект!F28,0)+IF(10=P_horizon,7_CAPEX!F15*N_residual_pct,0),0) -> 0 | D15: =D14+C15 -> -37607925 | E15: =E14+C15/(1+N_discount)^10 -> -61828693 | F15: =IF(10<=P_horizon,9_Эффект!G23-IF(AND(3_Решение_фильтры!G45=1,MOD(10,N_battery_life)=0,10<=P_horizon-1),9_Эффект!G28,0)+IF(10=P_horizon,7_CAPEX!G15*N_residual_pct,0),0) -> 0 | G15: =G14+F15 -> -21363525 | H15: =H14+F15/(1+N_discount)^10 -> -18118416 | I15: =IF(10<=P_horizon,9_Эффект!H23-IF(AND(3_Решение_фильтры!H45=1,MOD(10,N_battery_life)=0,10<=P_horizon-1),9_Эффект!H28,0)+IF(10=P_horizon,7_CAPEX!H15*N_residual_pct,0),0) -> 0 | J15: =J14+I15 -> 11026800 | K15: =K14+I15/(1+N_discount)^10 -> -12483903
B16: 11 | C16: =IF(11<=P_horizon,9_Эффект!F23-IF(AND(3_Решение_фильтры!F45=1,MOD(11,N_battery_life)=0,11<=P_horizon-1),9_Эффект!F28,0)+IF(11=P_horizon,7_CAPEX!F15*N_residual_pct,0),0) -> 0 | D16: =D15+C16 -> -37607925 | E16: =E15+C16/(1+N_discount)^11 -> -61828693 | F16: =IF(11<=P_horizon,9_Эффект!G23-IF(AND(3_Решение_фильтры!G45=1,MOD(11,N_battery_life)=0,11<=P_horizon-1),9_Эффект!G28,0)+IF(11=P_horizon,7_CAPEX!G15*N_residual_pct,0),0) -> 0 | G16: =G15+F16 -> -21363525 | H16: =H15+F16/(1+N_discount)^11 -> -18118416 | I16: =IF(11<=P_horizon,9_Эффект!H23-IF(AND(3_Решение_фильтры!H45=1,MOD(11,N_battery_life)=0,11<=P_horizon-1),9_Эффект!H28,0)+IF(11=P_horizon,7_CAPEX!H15*N_residual_pct,0),0) -> 0 | J16: =J15+I16 -> 11026800 | K16: =K15+I16/(1+N_discount)^11 -> -12483903
B17: 12 | C17: =IF(12<=P_horizon,9_Эффект!F23-IF(AND(3_Решение_фильтры!F45=1,MOD(12,N_battery_life)=0,12<=P_horizon-1),9_Эффект!F28,0)+IF(12=P_horizon,7_CAPEX!F15*N_residual_pct,0),0) -> 0 | D17: =D16+C17 -> -37607925 | E17: =E16+C17/(1+N_discount)^12 -> -61828693 | F17: =IF(12<=P_horizon,9_Эффект!G23-IF(AND(3_Решение_фильтры!G45=1,MOD(12,N_battery_life)=0,12<=P_horizon-1),9_Эффект!G28,0)+IF(12=P_horizon,7_CAPEX!G15*N_residual_pct,0),0) -> 0 | G17: =G16+F17 -> -21363525 | H17: =H16+F17/(1+N_discount)^12 -> -18118416 | I17: =IF(12<=P_horizon,9_Эффект!H23-IF(AND(3_Решение_фильтры!H45=1,MOD(12,N_battery_life)=0,12<=P_horizon-1),9_Эффект!H28,0)+IF(12=P_horizon,7_CAPEX!H15*N_residual_pct,0),0) -> 0 | J17: =J16+I17 -> 11026800 | K17: =K16+I17/(1+N_discount)^12 -> -12483903
B18: 13 | C18: =IF(13<=P_horizon,9_Эффект!F23-IF(AND(3_Решение_фильтры!F45=1,MOD(13,N_battery_life)=0,13<=P_horizon-1),9_Эффект!F28,0)+IF(13=P_horizon,7_CAPEX!F15*N_residual_pct,0),0) -> 0 | D18: =D17+C18 -> -37607925 | E18: =E17+C18/(1+N_discount)^13 -> -61828693 | F18: =IF(13<=P_horizon,9_Эффект!G23-IF(AND(3_Решение_фильтры!G45=1,MOD(13,N_battery_life)=0,13<=P_horizon-1),9_Эффект!G28,0)+IF(13=P_horizon,7_CAPEX!G15*N_residual_pct,0),0) -> 0 | G18: =G17+F18 -> -21363525 | H18: =H17+F18/(1+N_discount)^13 -> -18118416 | I18: =IF(13<=P_horizon,9_Эффект!H23-IF(AND(3_Решение_фильтры!H45=1,MOD(13,N_battery_life)=0,13<=P_horizon-1),9_Эффект!H28,0)+IF(13=P_horizon,7_CAPEX!H15*N_residual_pct,0),0) -> 0 | J18: =J17+I18 -> 11026800 | K18: =K17+I18/(1+N_discount)^13 -> -12483903
B19: 14 | C19: =IF(14<=P_horizon,9_Эффект!F23-IF(AND(3_Решение_фильтры!F45=1,MOD(14,N_battery_life)=0,14<=P_horizon-1),9_Эффект!F28,0)+IF(14=P_horizon,7_CAPEX!F15*N_residual_pct,0),0) -> 0 | D19: =D18+C19 -> -37607925 | E19: =E18+C19/(1+N_discount)^14 -> -61828693 | F19: =IF(14<=P_horizon,9_Эффект!G23-IF(AND(3_Решение_фильтры!G45=1,MOD(14,N_battery_life)=0,14<=P_horizon-1),9_Эффект!G28,0)+IF(14=P_horizon,7_CAPEX!G15*N_residual_pct,0),0) -> 0 | G19: =G18+F19 -> -21363525 | H19: =H18+F19/(1+N_discount)^14 -> -18118416 | I19: =IF(14<=P_horizon,9_Эффект!H23-IF(AND(3_Решение_фильтры!H45=1,MOD(14,N_battery_life)=0,14<=P_horizon-1),9_Эффект!H28,0)+IF(14=P_horizon,7_CAPEX!H15*N_residual_pct,0),0) -> 0 | J19: =J18+I19 -> 11026800 | K19: =K18+I19/(1+N_discount)^14 -> -12483903
B20: 15 | C20: =IF(15<=P_horizon,9_Эффект!F23-IF(AND(3_Решение_фильтры!F45=1,MOD(15,N_battery_life)=0,15<=P_horizon-1),9_Эффект!F28,0)+IF(15=P_horizon,7_CAPEX!F15*N_residual_pct,0),0) -> 0 | D20: =D19+C20 -> -37607925 | E20: =E19+C20/(1+N_discount)^15 -> -61828693 | F20: =IF(15<=P_horizon,9_Эффект!G23-IF(AND(3_Решение_фильтры!G45=1,MOD(15,N_battery_life)=0,15<=P_horizon-1),9_Эффект!G28,0)+IF(15=P_horizon,7_CAPEX!G15*N_residual_pct,0),0) -> 0 | G20: =G19+F20 -> -21363525 | H20: =H19+F20/(1+N_discount)^15 -> -18118416 | I20: =IF(15<=P_horizon,9_Эффект!H23-IF(AND(3_Решение_фильтры!H45=1,MOD(15,N_battery_life)=0,15<=P_horizon-1),9_Эффект!H28,0)+IF(15=P_horizon,7_CAPEX!H15*N_residual_pct,0),0) -> 0 | J20: =J19+I20 -> 11026800 | K20: =K19+I20/(1+N_discount)^15 -> -12483903
B21: NPV за горизонт | E21: =E20 -> -61828693 | H21: =H20 -> -18118416 | K21: =K20 -> -12483903
B22: IRR | E22: =IFERROR(IRR(C5:C20),"—") -> -0.12423456 | H22: =IFERROR(IRR(F5:F20),"—") -> — | K22: =IFERROR(IRR(I5:I20),"—") -> 0.058798111
B23: Дисконтированный срок окупаемости, лет (целых) | E23: =IF(E20<0,"не окупается",COUNTIF(E5:E20,"<0")) -> не окупается | H23: =IF(H20<0,"не окупается",COUNTIF(H5:H20,"<0")) -> не окупается | K23: =IF(K20<0,"не окупается",COUNTIF(K5:K20,"<0")) -> не окупается
B25: Выходы: NPV, IRR, дисконтированный срок → шаг 13 (сводка). Для RaaS IRR не определён при CAPEX ≈ 0 — выводится «—».

Sheet 11_Чувствительность
A1: ШАГ 11. ЧУВСТВИТЕЛЬНОСТЬ: пересчёт шагов 5, 7–9 при ±N_sens по цене оборудования, объёму операций и стоимости труда
A2: Каждая колонка — прогон сценария с множителями (формулы шагов 5, 7, 8, 9 повторены без изменений). Объём масштабирует парк и численность персонала.
B4: Сценарий | C4: Покупка A | D4: Покупка A | E4: Покупка A | F4: Покупка A | G4: Покупка A | H4: Покупка A | I4: Покупка A | J4: RaaS A | K4: RaaS A | L4: RaaS A | M4: RaaS A | N4: RaaS A | O4: RaaS A | P4: RaaS A | Q4: Покупка B | R4: Покупка B | S4: Покупка B | T4: Покупка B | U4: Покупка B | V4: Покупка B | W4: Покупка B
B5: Вариант | C5: База | D5: Оборуд. − | E5: Оборуд. + | F5: Объём − | G5: Объём + | H5: Труд − | I5: Труд + | J5: База | K5: Оборуд. − | L5: Оборуд. + | M5: Объём − | N5: Объём + | O5: Труд − | P5: Труд + | Q5: База | R5: Оборуд. − | S5: Оборуд. + | T5: Объём − | U5: Объём + | V5: Труд − | W5: Труд +
B6: k_цена | C6: 1 | D6: =1-N_sens -> 0.8 | E6: =1+N_sens -> 1.2 | F6: 1 | G6: 1 | H6: 1 | I6: 1 | J6: 1 | K6: =1-N_sens -> 0.8 | L6: =1+N_sens -> 1.2 | M6: 1 | N6: 1 | O6: 1 | P6: 1 | Q6: 1 | R6: =1-N_sens -> 0.8 | S6: =1+N_sens -> 1.2 | T6: 1 | U6: 1 | V6: 1 | W6: 1
B7: k_объём | C7: 1 | D7: 1 | E7: 1 | F7: =1-N_sens -> 0.8 | G7: =1+N_sens -> 1.2 | H7: 1 | I7: 1 | J7: 1 | K7: 1 | L7: 1 | M7: =1-N_sens -> 0.8 | N7: =1+N_sens -> 1.2 | O7: 1 | P7: 1 | Q7: 1 | R7: 1 | S7: 1 | T7: =1-N_sens -> 0.8 | U7: =1+N_sens -> 1.2 | V7: 1 | W7: 1
B8: k_труд | C8: 1 | D8: 1 | E8: 1 | F8: 1 | G8: 1 | H8: =1-N_sens -> 0.8 | I8: =1+N_sens -> 1.2 | J8: 1 | K8: 1 | L8: 1 | M8: 1 | N8: 1 | O8: =1-N_sens -> 0.8 | P8: =1+N_sens -> 1.2 | Q8: 1 | R8: 1 | S8: 1 | T8: 1 | U8: 1 | V8: =1-N_sens -> 0.8 | W8: =1+N_sens -> 1.2
B10: Константы прогона (ссылки на шаги)
A11: feas | B11: Применимо (шаг 3) | C11: =3_Решение_фильтры!F43 -> 1 | D11: =3_Решение_фильтры!F43 -> 1 | E11: =3_Решение_фильтры!F43 -> 1 | F11: =3_Решение_фильтры!F43 -> 1 | G11: =3_Решение_фильтры!F43 -> 1 | H11: =3_Решение_фильтры!F43 -> 1 | I11: =3_Решение_фильтры!F43 -> 1 | J11: =3_Решение_фильтры!G43 -> 1 | K11: =3_Решение_фильтры!G43 -> 1 | L11: =3_Решение_фильтры!G43 -> 1 | M11: =3_Решение_фильтры!G43 -> 1 | N11: =3_Решение_фильтры!G43 -> 1 | O11: =3_Решение_фильтры!G43 -> 1 | P11: =3_Решение_фильтры!G43 -> 1 | Q11: =3_Решение_фильтры!H43 -> 1 | R11: =3_Решение_фильтры!H43 -> 1 | S11: =3_Решение_фильтры!H43 -> 1 | T11: =3_Решение_фильтры!H43 -> 1 | U11: =3_Решение_фильтры!H43 -> 1 | V11: =3_Решение_фильтры!H43 -> 1 | W11: =3_Решение_фильтры!H43 -> 1
A12: isp | B12: Покупка=1 (шаг 3) | C12: =3_Решение_фильтры!F45 -> 1 | D12: =3_Решение_фильтры!F45 -> 1 | E12: =3_Решение_фильтры!F45 -> 1 | F12: =3_Решение_фильтры!F45 -> 1 | G12: =3_Решение_фильтры!F45 -> 1 | H12: =3_Решение_фильтры!F45 -> 1 | I12: =3_Решение_фильтры!F45 -> 1 | J12: =3_Решение_фильтры!G45 -> 0 | K12: =3_Решение_фильтры!G45 -> 0 | L12: =3_Решение_фильтры!G45 -> 0 | M12: =3_Решение_фильтры!G45 -> 0 | N12: =3_Решение_фильтры!G45 -> 0 | O12: =3_Решение_фильтры!G45 -> 0 | P12: =3_Решение_фильтры!G45 -> 0 | Q12: =3_Решение_фильтры!H45 -> 1 | R12: =3_Решение_фильтры!H45 -> 1 | S12: =3_Решение_фильтры!H45 -> 1 | T12: =3_Решение_фильтры!H45 -> 1 | U12: =3_Решение_фильтры!H45 -> 1 | V12: =3_Решение_фильтры!H45 -> 1 | W12: =3_Решение_фильтры!H45 -> 1
A13: price | B13: Цена (шаг 3) | C13: =3_Решение_фильтры!F21 -> 4300000 | D13: =3_Решение_фильтры!F21 -> 4300000 | E13: =3_Решение_фильтры!F21 -> 4300000 | F13: =3_Решение_фильтры!F21 -> 4300000 | G13: =3_Решение_фильтры!F21 -> 4300000 | H13: =3_Решение_фильтры!F21 -> 4300000 | I13: =3_Решение_фильтры!F21 -> 4300000 | J13: =3_Решение_фильтры!G21 -> 4300000 | K13: =3_Решение_фильтры!G21 -> 4300000 | L13: =3_Решение_фильтры!G21 -> 4300000 | M13: =3_Решение_фильтры!G21 -> 4300000 | N13: =3_Решение_фильтры!G21 -> 4300000 | O13: =3_Решение_фильтры!G21 -> 4300000 | P13: =3_Решение_фильтры!G21 -> 4300000 | Q13: =3_Решение_фильтры!H21 -> 2700000 | R13: =3_Решение_фильтры!H21 -> 2700000 | S13: =3_Решение_фильтры!H21 -> 2700000 | T13: =3_Решение_фильтры!H21 -> 2700000 | U13: =3_Решение_фильтры!H21 -> 2700000 | V13: =3_Решение_фильтры!H21 -> 2700000 | W13: =3_Решение_фильтры!H21 -> 2700000
A14: power | B14: Мощность (шаг 3) | C14: =3_Решение_фильтры!F26 -> 3 | D14: =3_Решение_фильтры!F26 -> 3 | E14: =3_Решение_фильтры!F26 -> 3 | F14: =3_Решение_фильтры!F26 -> 3 | G14: =3_Решение_фильтры!F26 -> 3 | H14: =3_Решение_фильтры!F26 -> 3 | I14: =3_Решение_фильтры!F26 -> 3 | J14: =3_Решение_фильтры!G26 -> 3 | K14: =3_Решение_фильтры!G26 -> 3 | L14: =3_Решение_фильтры!G26 -> 3 | M14: =3_Решение_фильтры!G26 -> 3 | N14: =3_Решение_фильтры!G26 -> 3 | O14: =3_Решение_фильтры!G26 -> 3 | P14: =3_Решение_фильтры!G26 -> 3 | Q14: =3_Решение_фильтры!H26 -> 1 | R14: =3_Решение_фильтры!H26 -> 1 | S14: =3_Решение_фильтры!H26 -> 1 | T14: =3_Решение_фильтры!H26 -> 1 | U14: =3_Решение_фильтры!H26 -> 1 | V14: =3_Решение_фильтры!H26 -> 1 | W14: =3_Решение_фильтры!H26 -> 1
A15: repl | B15: Замещение (шаг 3) | C15: =3_Решение_фильтры!F30 -> 0.8 | D15: =3_Решение_фильтры!F30 -> 0.8 | E15: =3_Решение_фильтры!F30 -> 0.8 | F15: =3_Решение_фильтры!F30 -> 0.8 | G15: =3_Решение_фильтры!F30 -> 0.8 | H15: =3_Решение_фильтры!F30 -> 0.8 | I15: =3_Решение_фильтры!F30 -> 0.8 | J15: =3_Решение_фильтры!G30 -> 0.8 | K15: =3_Решение_фильтры!G30 -> 0.8 | L15: =3_Решение_фильтры!G30 -> 0.8 | M15: =3_Решение_фильтры!G30 -> 0.8 | N15: =3_Решение_фильтры!G30 -> 0.8 | O15: =3_Решение_фильтры!G30 -> 0.8 | P15: =3_Решение_фильтры!G30 -> 0.8 | Q15: =3_Решение_фильтры!H30 -> 0.6 | R15: =3_Решение_фильтры!H30 -> 0.6 | S15: =3_Решение_фильтры!H30 -> 0.6 | T15: =3_Решение_фильтры!H30 -> 0.6 | U15: =3_Решение_фильтры!H30 -> 0.6 | V15: =3_Решение_фильтры!H30 -> 0.6 | W15: =3_Решение_фильтры!H30 -> 0.6
A16: peak | B16: Пиковая потребность (шаг 4) | C16: =4_Потребность!F19 -> 129.54545 | D16: =4_Потребность!F19 -> 129.54545 | E16: =4_Потребность!F19 -> 129.54545 | F16: =4_Потребность!F19 -> 129.54545 | G16: =4_Потребность!F19 -> 129.54545 | H16: =4_Потребность!F19 -> 129.54545 | I16: =4_Потребность!F19 -> 129.54545 | J16: =4_Потребность!G19 -> 129.54545 | K16: =4_Потребность!G19 -> 129.54545 | L16: =4_Потребность!G19 -> 129.54545 | M16: =4_Потребность!G19 -> 129.54545 | N16: =4_Потребность!G19 -> 129.54545 | O16: =4_Потребность!G19 -> 129.54545 | P16: =4_Потребность!G19 -> 129.54545 | Q16: =4_Потребность!H19 -> 129.54545 | R16: =4_Потребность!H19 -> 129.54545 | S16: =4_Потребность!H19 -> 129.54545 | T16: =4_Потребность!H19 -> 129.54545 | U16: =4_Потребность!H19 -> 129.54545 | V16: =4_Потребность!H19 -> 129.54545 | W16: =4_Потребность!H19 -> 129.54545
A17: eff | B17: Эфф. производительность (шаг 5) | C17: =5_Парк!F22 -> 7.9948052 | D17: =5_Парк!F22 -> 7.9948052 | E17: =5_Парк!F22 -> 7.9948052 | F17: =5_Парк!F22 -> 7.9948052 | G17: =5_Парк!F22 -> 7.9948052 | H17: =5_Парк!F22 -> 7.9948052 | I17: =5_Парк!F22 -> 7.9948052 | J17: =5_Парк!G22 -> 7.9948052 | K17: =5_Парк!G22 -> 7.9948052 | L17: =5_Парк!G22 -> 7.9948052 | M17: =5_Парк!G22 -> 7.9948052 | N17: =5_Парк!G22 -> 7.9948052 | O17: =5_Парк!G22 -> 7.9948052 | P17: =5_Парк!G22 -> 7.9948052 | Q17: =5_Парк!H22 -> 9.6944882 | R17: =5_Парк!H22 -> 9.6944882 | S17: =5_Парк!H22 -> 9.6944882 | T17: =5_Парк!H22 -> 9.6944882 | U17: =5_Парк!H22 -> 9.6944882 | V17: =5_Парк!H22 -> 9.6944882 | W17: =5_Парк!H22 -> 9.6944882
B18: Пересчёт
A19: n | B19: Роботов = MAX(1, ROUNDUP(пик × k_объём / произв. × (1+резерв))) | C19: =IF(C11=1,MAX(1,ROUNDUP(C16*C$7/C17*(1+N_reserve),0)),0) -> 19 | D19: =IF(D11=1,MAX(1,ROUNDUP(D16*D$7/D17*(1+N_reserve),0)),0) -> 19 | E19: =IF(E11=1,MAX(1,ROUNDUP(E16*E$7/E17*(1+N_reserve),0)),0) -> 19 | F19: =IF(F11=1,MAX(1,ROUNDUP(F16*F$7/F17*(1+N_reserve),0)),0) -> 15 | G19: =IF(G11=1,MAX(1,ROUNDUP(G16*G$7/G17*(1+N_reserve),0)),0) -> 23 | H19: =IF(H11=1,MAX(1,ROUNDUP(H16*H$7/H17*(1+N_reserve),0)),0) -> 19 | I19: =IF(I11=1,MAX(1,ROUNDUP(I16*I$7/I17*(1+N_reserve),0)),0) -> 19 | J19: =IF(J11=1,MAX(1,ROUNDUP(J16*J$7/J17*(1+N_reserve),0)),0) -> 19 | ... W19: =IF(W11=1,MAX(1,ROUNDUP(W16*W$7/W17*(1+N_reserve),0)),0) -> 16
A20: nch | B20: Зарядных станций | C20: =ROUNDUP(C19/N_charger_ratio,0) -> 5 | D20: =ROUNDUP(D19/N_charger_ratio,0) -> 5 | E20: =ROUNDUP(E19/N_charger_ratio,0) -> 5 | F20: =ROUNDUP(F19/N_charger_ratio,0) -> 4 | G20: =ROUNDUP(G19/N_charger_ratio,0) -> 6 | H20: =ROUNDUP(H19/N_charger_ratio,0) -> 5 | I20: =ROUNDUP(I19/N_charger_ratio,0) -> 5 | J20: =ROUNDUP(J19/N_charger_ratio,0) -> 5 | ... W20: =ROUNDUP(W19/N_charger_ratio,0) -> 4
A21: capex | B21: CAPEX (формулы шага 7 с k_цена) | C21: =(C19*C13*C$6*(C12*(1+N_sw_pct+N_delivery_pct+N_pnr_pct)+P_site_pct+(1-C12)*N_raas_setup)+C20*N_charger_price*C12+(P_integration+N_training)*IF(C19>0,1,0))*(1+N_capex_reserve) -> 113546400 | D21: =(D19*D13*D$6*(D12*(1+N_sw_pct+N_delivery_pct+N_pnr_pct)+P_site_pct+(1-D12)*N_raas_setup)+D20*N_charger_price*D12+(P_integration+N_training)*IF(D19>0,1,0))*(1+N_capex_reserve) -> 91618120 | E21: =(E19*E13*E$6*(E12*(1+N_sw_pct+N_delivery_pct+N_pnr_pct)+P_site_pct+(1-E12)*N_raas_setup)+E20*N_charger_price*E12+(P_integration+N_training)*IF(E19>0,1,0))*(1+N_capex_reserve) -> 135474680 | F21: =(F19*F13*F$6*(F12*(1+N_sw_pct+N_delivery_pct+N_pnr_pct)+P_site_pct+(1-F12)*N_raas_setup)+F20*N_charger_price*F12+(P_integration+N_training)*IF(F19>0,1,0))*(1+N_capex_reserve) -> 90189000 | G21: =(G19*G13*G$6*(G12*(1+N_sw_pct+N_delivery_pct+N_pnr_pct)+P_site_pct+(1-G12)*N_raas_setup)+G20*N_charger_price*G12+(P_integration+N_training)*IF(G19>0,1,0))*(1+N_capex_reserve) -> 136903800 | H21: =(H19*H13*H$6*(H12*(1+N_sw_pct+N_delivery_pct+N_pnr_pct)+P_site_pct+(1-H12)*N_raas_setup)+H20*N_charger_price*H12+(P_integration+N_training)*IF(H19>0,1,0))*(1+N_capex_reserve) -> 113546400 | I21: =(I19*I13*I$6*(I12*(1+N_sw_pct+N_delivery_pct+N_pnr_pct)+P_site_pct+(1-I12)*N_raas_setup)+I20*N_charger_price*I12+(P_integration+N_training)*IF(I19>0,1,0))*(1+N_capex_reserve) -> 113546400 | J21: =(J19*J13*J$6*(J12*(1+N_sw_pct+N_delivery_pct+N_pnr_pct)+P_site_pct+(1-J12)*N_raas_setup)+J20*N_charger_price*J12+(P_integration+N_training)*IF(J19>0,1,0))*(1+N_capex_reserve) -> 11517000 | ... W21: =(W19*W13*W$6*(W12*(1+N_sw_pct+N_delivery_pct+N_pnr_pct)+P_site_pct+(1-W12)*N_raas_setup)+W20*N_charger_price*W12+(P_integration+N_training)*IF(W19>0,1,0))*(1+N_capex_reserve) -> 61604400
A22: opex_r | B22: OPEX решения (формулы шага 8 с k_цена, k_труд) | C22: =C19*C13*C$6*((1-C12)*N_raas_pct*12+C12*(N_service_pct+N_license_pct+N_repair_pct))+C19*C14*P_hours_day*365*N_energy_price+(N_connect+P_fleet_per_shift*P_shifts*(1+P_loss_k)*P_fleet_sal*12*N_fot*C$8)*IF(C19>0,1,0)+P_consum_per_robot*C19+C12*C21*N_loan_share*N_loan_rate*(N_loan_years+1)/(2*N_loan_years) -> 18801025 | D22: =D19*D13*D$6*((1-D12)*N_raas_pct*12+D12*(N_service_pct+N_license_pct+N_repair_pct))+D19*D14*P_hours_day*365*N_energy_price+(N_connect+P_fleet_per_shift*P_shifts*(1+P_loss_k)*P_fleet_sal*12*N_fot*D$8)*IF(D19>0,1,0)+P_consum_per_robot*D19+D12*D21*N_loan_share*N_loan_rate*(N_loan_years+1)/(2*N_loan_years) -> 16676825 | E22: =E19*E13*E$6*((1-E12)*N_raas_pct*12+E12*(N_service_pct+N_license_pct+N_repair_pct))+E19*E14*P_hours_day*365*N_energy_price+(N_connect+P_fleet_per_shift*P_shifts*(1+P_loss_k)*P_fleet_sal*12*N_fot*E$8)*IF(E19>0,1,0)+P_consum_per_robot*E19+E12*E21*N_loan_share*N_loan_rate*(N_loan_years+1)/(2*N_loan_years) -> 20925225 | F22: =F19*F13*F$6*((1-F12)*N_raas_pct*12+F12*(N_service_pct+N_license_pct+N_repair_pct))+F19*F14*P_hours_day*365*N_energy_price+(N_connect+P_fleet_per_shift*P_shifts*(1+P_loss_k)*P_fleet_sal*12*N_fot*F$8)*IF(F19>0,1,0)+P_consum_per_robot*F19+F12*F21*N_loan_share*N_loan_rate*(N_loan_years+1)/(2*N_loan_years) -> 15842325 | G22: =G19*G13*G$6*((1-G12)*N_raas_pct*12+G12*(N_service_pct+N_license_pct+N_repair_pct))+G19*G14*P_hours_day*365*N_energy_price+(N_connect+P_fleet_per_shift*P_shifts*(1+P_loss_k)*P_fleet_sal*12*N_fot*G$8)*IF(G19>0,1,0)+P_consum_per_robot*G19+G12*G21*N_loan_share*N_loan_rate*(N_loan_years+1)/(2*N_loan_years) -> 21759725 | H22: =H19*H13*H$6*((1-H12)*N_raas_pct*12+H12*(N_service_pct+N_license_pct+N_repair_pct))+H19*H14*P_hours_day*365*N_energy_price+(N_connect+P_fleet_per_shift*P_shifts*(1+P_loss_k)*P_fleet_sal*12*N_fot*H$8)*IF(H19>0,1,0)+P_consum_per_robot*H19+H12*H21*N_loan_share*N_loan_rate*(N_loan_years+1)/(2*N_loan_years) -> 17863585 | I22: =I19*I13*I$6*((1-I12)*N_raas_pct*12+I12*(N_service_pct+N_license_pct+N_repair_pct))+I19*I14*P_hours_day*365*N_energy_price+(N_connect+P_fleet_per_shift*P_shifts*(1+P_loss_k)*P_fleet_sal*12*N_fot*I$8)*IF(I19>0,1,0)+P_consum_per_robot*I19+I12*I21*N_loan_share*N_loan_rate*(N_loan_years+1)/(2*N_loan_years) -> 19738465 | J22: =J19*J13*J$6*((1-J12)*N_raas_pct*12+J12*(N_service_pct+N_license_pct+N_repair_pct))+J19*J14*P_hours_day*365*N_energy_price+(N_connect+P_fleet_per_shift*P_shifts*(1+P_loss_k)*P_fleet_sal*12*N_fot*J$8)*IF(J19>0,1,0)+P_consum_per_robot*J19+J12*J21*N_loan_share*N_loan_rate*(N_loan_years+1)/(2*N_loan_years) -> 37592025 | ... W22: =W19*W13*W$6*((1-W12)*N_raas_pct*12+W12*(N_service_pct+N_license_pct+N_repair_pct))+W19*W14*P_hours_day*365*N_energy_price+(N_connect+P_fleet_per_shift*P_shifts*(1+P_loss_k)*P_fleet_sal*12*N_fot*W$8)*IF(W19>0,1,0)+P_consum_per_robot*W19+W12*W21*N_loan_share*N_loan_rate*(N_loan_years+1)/(2*N_loan_years) -> 12264240
A23: saving | B23: Экономия ФОТ × k_труд × k_объём | C23: =P_labor_target*C15*C11*C$8*C$7 -> 35622720 | D23: =P_labor_target*D15*D11*D$8*D$7 -> 35622720 | E23: =P_labor_target*E15*E11*E$8*E$7 -> 35622720 | F23: =P_labor_target*F15*F11*F$8*F$7 -> 28498176 | G23: =P_labor_target*G15*G11*G$8*G$7 -> 42747264 | H23: =P_labor_target*H15*H11*H$8*H$7 -> 28498176 | I23: =P_labor_target*I15*I11*I$8*I$7 -> 42747264 | J23: =P_labor_target*J15*J11*J$8*J$7 -> 35622720 | ... W23: =P_labor_target*W15*W11*W$8*W$7 -> 32060448
A24: hire | B24: Экономия на подборе | C24: =P_fte_target*C15*C11*C$7*P_turnover*N_hire_cost*P_sal_target*C$8 -> 0 | D24: =P_fte_target*D15*D11*D$7*P_turnover*N_hire_cost*P_sal_target*D$8 -> 0 | E24: =P_fte_target*E15*E11*E$7*P_turnover*N_hire_cost*P_sal_target*E$8 -> 0 | F24: =P_fte_target*F15*F11*F$7*P_turnover*N_hire_cost*P_sal_target*F$8 -> 0 | G24: =P_fte_target*G15*G11*G$7*P_turnover*N_hire_cost*P_sal_target*G$8 -> 0 | H24: =P_fte_target*H15*H11*H$7*P_turnover*N_hire_cost*P_sal_target*H$8 -> 0 | I24: =P_fte_target*I15*I11*I$7*P_turnover*N_hire_cost*P_sal_target*I$8 -> 0 | J24: =P_fte_target*J15*J11*J$7*P_turnover*N_hire_cost*P_sal_target*J$8 -> 0 | ... W24: =P_fte_target*W15*W11*W$7*P_turnover*N_hire_cost*P_sal_target*W$8 -> 0
A25: effect | B25: ЧИСТЫЙ ГОДОВОЙ ЭФФЕКТ | C25: =C23-C22+C24+P_other_effects*C11 -> 16821695 | D25: =D23-D22+D24+P_other_effects*D11 -> 18945895 | E25: =E23-E22+E24+P_other_effects*E11 -> 14697495 | F25: =F23-F22+F24+P_other_effects*F11 -> 12655851 | G25: =G23-G22+G24+P_other_effects*G11 -> 20987539 | H25: =H23-H22+H24+P_other_effects*H11 -> 10634591 | I25: =I23-I22+I24+P_other_effects*I11 -> 23008799 | J25: =J23-J22+J24+P_other_effects*J11 -> -1969305 | ... W25: =W23-W22+W24+P_other_effects*W11 -> 19796208
A26: payback | B26: СРОК ОКУПАЕМОСТИ, лет | C26: =IF(AND(C11=1,C25>0),C21/C25,"не окупается") -> 6.7499975 | D26: =IF(AND(D11=1,D25>0),D21/D25,"не окупается") -> 4.8357768 | E26: =IF(AND(E11=1,E25>0),E21/E25,"не окупается") -> 9.2175354 | F26: =IF(AND(F11=1,F25>0),F21/F25,"не окупается") -> 7.1262691 | G26: =IF(AND(G11=1,G25>0),G21/G25,"не окупается") -> 6.5230993 | H26: =IF(AND(H11=1,H25>0),H21/H25,"не окупается") -> 10.677082 | I26: =IF(AND(I11=1,I25>0),I21/I25,"не окупается") -> 4.9349121 | J26: =IF(AND(J11=1,J25>0),J21/J25,"не окупается") -> не окупается | ... W26: =IF(AND(W11=1,W25>0),W21/W25,"не окупается") -> 3.1119293
A27: roi | B27: ROI за горизонт | C27: =IF(C21>0,(C25*P_horizon-C12*INT((P_horizon-1)/N_battery_life)*C19*C13*C$6*N_battery_share)/C21,"—") -> 0.66878805 | D27: =IF(D21>0,(D25*P_horizon-D12*INT((P_horizon-1)/N_battery_life)*D19*D13*D$6*N_battery_share)/D21,"—") -> 0.96262044 | E27: =IF(E21>0,(E25*P_horizon-E12*INT((P_horizon-1)/N_battery_life)*E19*E13*E$6*N_battery_share)/E21,"—") -> 0.47007659 | F27: =IF(F21>0,(F25*P_horizon-F12*INT((P_horizon-1)/N_battery_life)*F19*F13*F$6*N_battery_share)/F21,"—") -> 0.63011293 | G27: =IF(G21>0,(G25*P_horizon-G12*INT((P_horizon-1)/N_battery_life)*G19*G13*G$6*N_battery_share)/G21,"—") -> 0.6942663 | H27: =IF(H21>0,(H25*P_horizon-H12*INT((P_horizon-1)/N_battery_life)*H19*H13*H$6*N_battery_share)/H21,"—") -> 0.39633978 | I27: =IF(I21>0,(I25*P_horizon-I12*INT((P_horizon-1)/N_battery_life)*I19*I13*I$6*N_battery_share)/I21,"—") -> 0.94123631 | J27: =IF(J21>0,(J25*P_horizon-J12*INT((P_horizon-1)/N_battery_life)*J19*J13*J$6*N_battery_share)/J21,"—") -> -0.85495572 | ... W27: =IF(W21>0,(W25*P_horizon-W12*INT((P_horizon-1)/N_battery_life)*W19*W13*W$6*N_battery_share)/W21,"—") -> 1.5365954
B29: Контроль: колонка «База» каждого сценария должна совпадать с шагами 5, 7, 8, 9 (n, CAPEX, OPEX решения, эффект, окупаемость).

Sheet 12_Симуляция
A1: ШАГ 12. ПЕРЕДАЧА В 2D-ИМИТАЦИЮ И ПРИЁМ РЕЗУЛЬТАТОВ (ТЗ 3.6.2: визуализация подтверждает расчёт)
A2: Блок А — что модель отдаёт симуляции (ссылки на шаги). Блок Б — что симуляция возвращает (синие ячейки заполняются по результатам прогона). Блок В — правила подтверждения и обратной связи в модель.
A4: А. ПАРАМЕТРЫ, ПЕРЕДАВАЕМЫЕ В СИМУЛЯЦИЮ (по выбранному сценарию)
A5: Ключ | B5: Параметр | C5: Ед. | D5: Тип | E5: Шаг-источник | F5: Покупка A | G5: RaaS A | H5: Покупка B | I5: Что задаёт в симуляции
A6: n_robots | B6: Количество агентов-роботов | C6: шт. | D6: ПРЕДПОСЧИТАН — шаг 5 | E6: шаг 5: n_robots | F6: =5_Парк!F23 -> 19 | G6: =5_Парк!G23 -> 19 | H6: =5_Парк!H23 -> 16 | I6: Число агентов на схеме
A7: n_chargers | B7: Число зарядных станций | C7: шт. | D7: ПРЕДПОСЧИТАН — шаг 5 | E7: шаг 5: n_chargers | F7: =5_Парк!F24 -> 5 | G7: =5_Парк!G24 -> 5 | H7: =5_Парк!H24 -> 4 | I7: Узлы зарядки; размещение: у узла-источника, далее k-медианы по узлам спроса (см. методику)
A8: v_eff | B8: Эксплуатационная скорость агента | C8: м/с | D8: ПРЕДПОСЧИТАН — шаг 5 | E8: шаг 5: v_eff | F8: =5_Парк!F17 -> 0.9 | G8: =5_Парк!G17 -> 0.9 | H8: =5_Парк!H17 -> 0.9 | I8: Скорость движения по рёбрам графа (или vmax × N_kv с лимитом ребра)
A9: tload | B9: Время загрузки | C9: с | D9: ДОПУЩЕНИЕ — команда | E9: шаг 3: tload | F9: =3_Решение_фильтры!F24 -> 60 | G9: =3_Решение_фильтры!G24 -> 60 | H9: =3_Решение_фильтры!H24 -> 30 | I9: Задержка в узле-источнике
A10: tunload | B10: Время разгрузки | C10: с | D10: ДОПУЩЕНИЕ — команда | E10: шаг 3: tunload | F10: =3_Решение_фильтры!F25 -> 60 | G10: =3_Решение_фильтры!G25 -> 60 | H10: =3_Решение_фильтры!H25 -> 30 | I10: Задержка в узле-приёмнике
A11: auton | B11: Автономность | C11: ч | D11: СЫРОЙ — docx ТТХ | E11: шаг 3: auton | F11: =3_Решение_фильтры!F34 -> 10 | G11: =3_Решение_фильтры!G34 -> 10 | H11: =3_Решение_фильтры!H34 -> 6 | I11: Ёмкость батареи агента (в часах хода)
A12: charge | B12: Время зарядки | C12: мин | D12: СЫРОЙ — docx ТТХ | E12: шаг 3: charge | F12: =3_Решение_фильтры!F35 -> 90 | G12: =3_Решение_фильтры!G35 -> 90 | H12: =3_Решение_фильтры!H35 -> 18 | I12: Длительность занятия станции
A13: L | B13: Средняя длина маршрута | C13: м | D13: ДОПУЩЕНИЕ — команда | E13: шаг 2: L | F13: =2_Процесс!G13 -> 100 | G13: =2_Процесс!G13 -> 100 | H13: =2_Процесс!G13 -> 100 | I13: Калибровочная цель для генератора планировки: средний кратчайший путь по графу ≈ L
A14: lift_time | B14: Время лифта (один проход) | C14: с | D14: ДОПУЩЕНИЕ — команда | E14: шаг 2: lift_time | F14: =2_Процесс!G16 -> 0 | G14: =2_Процесс!G16 -> 0 | H14: =2_Процесс!G16 -> 0 | I14: Задержка в узле-лифте (очередь FIFO, ёмкость = число лифтов)
A15: trips_day | B15: Рейсов в сутки | C15: рейсов/сут | D15: ПРЕДПОСЧИТАН — шаг 4 | E15: шаг 4: trips_day | F15: =4_Потребность!F20 -> 1900 | G15: =4_Потребность!G20 -> 1900 | H15: =4_Потребность!H20 -> 1900 | I15: Суммарный объём заявок за сутки
A16: avg_h | B16: Средняя интенсивность | C16: оп./ч | D16: ПРЕДПОСЧИТАН — шаг 4 | E16: шаг 4: avg_h | F16: =4_Потребность!F17 -> 86.363636 | G16: =4_Потребность!G17 -> 86.363636 | H16: =4_Потребность!H17 -> 86.363636 | I16: Базовый темп генератора заявок
A17: peak_trips | B17: Пиковая интенсивность | C17: рейсов/ч | D17: ПРЕДПОСЧИТАН — шаг 4 | E17: шаг 4: peak_trips | F17: =4_Потребность!F19 -> 129.54545 | G17: =4_Потребность!G19 -> 129.54545 | H17: =4_Потребность!H19 -> 129.54545 | I17: Темп генератора в пиковые окна (склад: × пиковый коэф.; аэропорт: по расписанию рейсов; мед: окна 07–10, 15–17)
A18: hours_day | B18: Часов работы | C18: ч | D18: ПРЕДПОСЧИТАН — шаг 2 | E18: шаг 2: hours_day | F18: =2_Процесс!G5 -> 22 | G18: =2_Процесс!G5 -> 22 | H18: =2_Процесс!G5 -> 22 | I18: Длина смоделированных суток
A19: t_cycle | B19: Расчётный цикл рейса | C19: с | D19: ПРЕДПОСЧИТАН — шаг 5 | E19: шаг 5: t_cycle | F19: =5_Парк!F20 -> 342.22222 | G19: =5_Парк!G20 -> 342.22222 | H19: =5_Парк!H20 -> 282.22222 | I19: Контрольное значение: средний цикл в симуляции
A20: eff_prod | B20: Расчётная производительность робота | C20: рейсов/ч | D20: ПРЕДПОСЧИТАН — шаг 5 | E20: шаг 5: eff_prod | F20: =5_Парк!F22 -> 7.9948052 | G20: =5_Парк!G22 -> 7.9948052 | H20: =5_Парк!H22 -> 9.6944882 | I20: Контрольное значение
A21: fleet_cap | B21: Расчётная пропускная способность парка | C21: рейсов/ч | D21: ПРЕДПОСЧИТАН — шаг 5 | E21: шаг 5: fleet_cap | F21: =5_Парк!F25 -> 151.9013 | G21: =5_Парк!G25 -> 151.9013 | H21: =5_Парк!H25 -> 155.11181 | I21: Контрольное значение: должна быть ≥ пиковой потребности
A22: util_avg | B22: Расчётная среднесуточная загрузка | C22: % | D22: ПРЕДПОСЧИТАН — шаг 5 | E22: шаг 5: util_avg | F22: =5_Парк!F26 -> 0.43209877 | G22: =5_Парк!G26 -> 0.43209877 | H22: =5_Парк!H26 -> 0.42315516 | I22: Контрольное значение
A24: Б. РЕЗУЛЬТАТЫ СИМУЛЯЦИИ (ввод после прогона; синие ячейки) и В. ПРАВИЛА ПОДТВЕРЖДЕНИЯ
A25: Ключ | B25: Метрика симуляции | C25: Ед. | D25: Тип | E25: Правило проверки | F25: Покупка A | G25: RaaS A | H25: Покупка B | I25: Действие при нарушении (обратная связь в модель)
A26: sim_cap | B26: Фактическая пропускная способность парка в пике | C26: рейсов/ч | D26: СИМУЛИРОВАН — шаг 12 | E26: ≥ peak_trips (шаг 4) | I26: Увеличить N_reserve или n_robots (шаг 5); проверить узкие места
A27: sim_cycle | B27: Фактический средний цикл рейса | C27: с | D27: СИМУЛИРОВАН — шаг 12 | E27: в пределах ±N_sim_tol от t_cycle | I27: Обновить N_kv, tload/tunload, lift_time (1b, 1c, 2) с фиксацией изменения (ТЗ 3.5.4)
A28: sim_util | B28: Фактическая средняя загрузка парка | C28: % | D28: СИМУЛИРОВАН — шаг 12 | E28: в пределах ±N_sim_tol от util_avg | I28: Если ниже — рассмотреть меньший парк / RaaS; если выше — риск нехватки резерва
A29: sim_queue | B29: Среднее ожидание в очередях (станции, лифты) | C29: с | D29: СИМУЛИРОВАН — шаг 12 | E29: информативно; > 10% цикла → узкое место | I29: Добавить станцию/лифтовую интеграцию → capex_site (шаг 7)
A30: sim_charge_loss | B30: Доля времени на зарядке | C30: % | D30: СИМУЛИРОВАН — шаг 12 | E30: ≤ 1 − N_util | I30: Если больше — уточнить N_util или добавить станции (шаг 5)
A31: sim_sla | B31: Доля заявок, выполненных в норматив | C31: % | D31: СИМУЛИРОВАН — шаг 12 | E31: ≥ 95% (норматив доставки: мед 20 мин, аэропорт TAT) | I31: Пересмотреть маршруты/приоритеты; при невыполнении — увеличить парк
B33: Проверки (формулы; «нет данных», пока результаты симуляции не введены):
B34: Пропускная способность подтверждена | F34: =IF(F26="","нет данных",IF(F26>=F17,"ДА","НЕТ — парк недостаточен")) -> нет данных | G34: =IF(G26="","нет данных",IF(G26>=G17,"ДА","НЕТ — парк недостаточен")) -> нет данных | H34: =IF(H26="","нет данных",IF(H26>=H17,"ДА","НЕТ — парк недостаточен")) -> нет данных
B35: Цикл рейса подтверждён (±допуск) | F35: =IF(F27="","нет данных",IF(ABS(F27/F19-1)<=N_sim_tol,"ДА","НЕТ — уточнить N_kv / времена операций / лифты")) -> нет данных | G35: =IF(G27="","нет данных",IF(ABS(G27/G19-1)<=N_sim_tol,"ДА","НЕТ — уточнить N_kv / времена операций / лифты")) -> нет данных | H35: =IF(H27="","нет данных",IF(ABS(H27/H19-1)<=N_sim_tol,"ДА","НЕТ — уточнить N_kv / времена операций / лифты")) -> нет данных
B36: Загрузка парка подтверждена (±допуск) | F36: =IF(F28="","нет данных",IF(ABS(F28-F22)<=N_sim_tol,"ДА","НЕТ — пересмотреть состав парка")) -> нет данных | G36: =IF(G28="","нет данных",IF(ABS(G28-G22)<=N_sim_tol,"ДА","НЕТ — пересмотреть состав парка")) -> нет данных | H36: =IF(H28="","нет данных",IF(ABS(H28-H22)<=N_sim_tol,"ДА","НЕТ — пересмотреть состав парка")) -> нет данных
B37: ИТОГ: расчёт подтверждён симуляцией | F37: =IF(OR(F34="нет данных",F35="нет данных",F36="нет данных"),"нет данных",IF(AND(F34="ДА",F35="ДА",F36="ДА"),"ПОДТВЕРЖДЁН","ТРЕБУЕТ КОРРЕКТИРОВКИ")) -> нет данных | G37: =IF(OR(G34="нет данных",G35="нет данных",G36="нет данных"),"нет данных",IF(AND(G34="ДА",G35="ДА",G36="ДА"),"ПОДТВЕРЖДЁН","ТРЕБУЕТ КОРРЕКТИРОВКИ")) -> нет данных | H37: =IF(OR(H34="нет данных",H35="нет данных",H36="нет данных"),"нет данных",IF(AND(H34="ДА",H35="ДА",H36="ДА"),"ПОДТВЕРЖДЁН","ТРЕБУЕТ КОРРЕКТИРОВКИ")) -> нет данных
B39: Порядок: расчёт (шаги 1–11) → генерация схемы из сырых данных (площади, проходы, этажи, лифты, точки) → симуляция с параметрами блока А → сравнение с контрольными значениями → при расхождении корректировка допущений (N_kv, времена операций, lift_time, L) и пересчёт шагов 5–11 → повторный прогон.
B40: Расчёт первичен, симуляция — верификатор: это соответствует ТЗ 3.6.2 («подтверждать расчётную производительность») и защищает демонстрацию от зависимости от готовности симулятора. Экономика никогда не берётся напрямую из симуляции; из неё берутся только уточнённые операционные допущения.
B41: Все изменённые по результатам симуляции параметры получают тип «СИМУЛИРОВАН — шаг 12» и фиксируются в журнале проекта с версией расчёта (ТЗ 3.1.5, 3.5.4).

Sheet 13_Итог
A1: ШАГ 13. СВОДКА ПО ВЫБРАННОМУ ОБЪЕКТУ
A2: Объект и процесс — из 0_Легенда; все значения — ссылки на шаги.
A4: Объект: | B4: =SEL_OBJ -> Склад
A5: Процесс: | B5: =SEL_PROC -> перемещение паллет док ↔ хранение
A7: Показатель | B7: Ед. | C7: База | D7: Покупка A | E7: RaaS A | F7: Покупка B | G7: Шаг
A8: Решение | C8: — | D8: =3_Решение_фильтры!F18 -> DMR Carrier P (FMR) | E8: =3_Решение_фильтры!G18 -> DMR Carrier P (FMR) | F8: =3_Решение_фильтры!H18 -> Ronavi H1500 (AMR, 1500 кг) | G8: шаг 3
A9: Применимость | C9: — | D9: =3_Решение_фильтры!F44 -> Применимо: ключевые ограничения выполнены | E9: =3_Решение_фильтры!G44 -> Применимо: ключевые ограничения выполнены | F9: =3_Решение_фильтры!H44 -> Применимо: ключевые ограничения выполнены | G9: шаг 3
A10: Роботов / станций | B10: шт. | C10: 0 | D10: =5_Парк!F23 -> 19 | E10: =5_Парк!G23 -> 19 | F10: =5_Парк!H23 -> 16 | G10: шаг 5
A11: CAPEX | B11: руб. | C11: 0 | D11: =7_CAPEX!F25 -> 113546400 | E11: =7_CAPEX!G25 -> 11517000 | F11: =7_CAPEX!H25 -> 61604400 | G11: шаг 7
A12: Проверка бюджета | C12: — | D12: =7_CAPEX!F26 -> Превышает бюджет | E12: =7_CAPEX!G26 -> В бюджете | F12: =7_CAPEX!H26 -> В бюджете | G12: шаг 7
A13: OPEX процесса | B13: руб./год | C13: =6_База!F14 -> 46872000 | D13: =9_Эффект!F19 -> 30050305 | E13: =9_Эффект!G19 -> 48841305 | F13: =9_Эффект!H19 -> 31481760 | G13: шаг 9
A14: в т.ч. OPEX решения | B14: руб./год | C14: 0 | D14: =8_OPEX!F24 -> 18801025 | E14: =8_OPEX!G24 -> 37592025 | F14: =8_OPEX!H24 -> 11326800 | G14: шаг 8
A15: ΔOPEX к базе | B15: руб./год | C15: 0 | D15: =9_Эффект!F20 -> -16821695 | E15: =9_Эффект!G20 -> 1969305 | F15: =9_Эффект!H20 -> -15390240 | G15: шаг 9
A16: Высвобождаемый персонал | B16: FTE | C16: 0 | D16: =9_Эффект!F16 -> 19 | E16: =9_Эффект!G16 -> 19 | F16: =9_Эффект!H16 -> 14.25 | G16: шаг 9
A17: Чистый годовой эффект | B17: руб./год | C17: 0 | D17: =9_Эффект!F23 -> 16821695 | E17: =9_Эффект!G23 -> -1969305 | F17: =9_Эффект!H23 -> 15390240 | G17: шаг 9
A18: Эффект с амортизацией | B18: руб./год | C18: 0 | D18: =9_Эффект!F25 -> 600780.71 | E18: =9_Эффект!G25 -> -1969305 | F18: =9_Эффект!H25 -> 6589611.4 | G18: шаг 9
A19: Простой срок окупаемости | B19: лет | C19: — | D19: =9_Эффект!F26 -> 6.7499975 | E19: =9_Эффект!G26 -> не окупается | F19: =9_Эффект!H26 -> 4.0028226 | G19: шаг 9
A20: ROI за горизонт (ТЗ) | B20: % | C20: — | D20: =9_Эффект!F30 -> 0.66878805 | E20: =9_Эффект!G30 -> -0.85495572 | F20: =9_Эффект!H30 -> 1.1789937 | G20: шаг 9
A21: NPV | B21: руб. | C21: — | D21: =10_ДенПоток!E21 -> -61828693 | E21: =10_ДенПоток!H21 -> -18118416 | F21: =10_ДенПоток!K21 -> -12483903 | G21: шаг 10
A22: IRR | B22: % | C22: — | D22: =10_ДенПоток!E22 -> -0.12423456 | E22: =10_ДенПоток!H22 -> — | F22: =10_ДенПоток!K22 -> 0.058798111 | G22: шаг 10
A23: TCO решения | B23: руб. | C23: 0 | D23: =9_Эффект!F32 -> 215721525 | E23: =9_Эффект!G32 -> 199477125 | F23: =9_Эффект!H32 -> 122558400 | G23: шаг 9
A24: Совокупные затраты процесса за горизонт | B24: руб. | C24: =6_База!F15 -> 234360000 | D24: =9_Эффект!F33 -> 271967925 | E24: =9_Эффект!G33 -> 255723525 | F24: =9_Эффект!H33 -> 223333200 | G24: шаг 9
A25: Интерпретация | C25: — | D25: =9_Эффект!F35 -> Низкая — требует уточнения данных | E25: =9_Эффект!G35 -> Не окупается | F25: =9_Эффект!H35 -> Средняя — рекомендован пилот | G25: шаг 9
A26: Риски | C26: — | D26: =9_Эффект!F36 -> Зрелость: piloting; ТТХ требуют подтверждения; CAPEX выше бюджета; | E26: =9_Эффект!G36 -> Зрелость: piloting; ТТХ требуют подтверждения; | F26: =9_Эффект!H36 | G26: шаг 9
A28: Результат — предварительная оценка; требует верификации при обследовании объекта (ТЗ 3.7.5). Подтверждение расчёта симуляцией — лист 12_Симуляция.
