Workbook
Name Aer_aisle: Аэропорт!$D$36
Name Aer_auto_share: Аэропорт!$D$29
Name Aer_bag_mass: Аэропорт!$D$12
Name Aer_bags_day: Аэропорт!$D$11
Name Aer_base_labor: Аэропорт!$D$50
Name Aer_budget: Аэропорт!$D$19
Name Aer_clearance: Аэропорт!$D$37
Name Aer_consum_per_robot: Аэропорт!$D$58
Name Aer_divisible: Аэропорт!$D$31
Name Aer_driver_share: Аэропорт!$D$47
Name Aer_fleet_per_shift: Аэропорт!$D$54
Name Aer_fleet_sal: Аэропорт!$D$55
Name Aer_flights_day: Аэропорт!$D$9
Name Aer_flights_peak_h: Аэропорт!$D$10
Name Aer_fte_target: Аэропорт!$D$48
Name Aer_gates: Аэропорт!$D$8
Name Aer_handling_req: Аэропорт!$D$40
Name Aer_horizon: Аэропорт!$D$20
Name Aer_hours_day: Аэропорт!$D$26
Name Aer_indoor_req: Аэропорт!$D$41
Name Aer_integration: Аэропорт!$D$57
Name Aer_L: Аэропорт!$D$32
Name Aer_labor_target: Аэропорт!$D$49
Name Aer_lift_share: Аэропорт!$D$34
Name Aer_lift_time: Аэропорт!$D$35
Name Aer_loss_k: Аэропорт!$D$53
Name Aer_noise: Аэропорт!$D$17
Name Aer_ops_day: Аэропорт!$D$27
Name Aer_other_effects: Аэропорт!$D$59
Name Aer_outdoor_req: Аэропорт!$D$38
Name Aer_peak_ops_h: Аэропорт!$D$28
Name Aer_power_kw: Аэропорт!$D$18
Name Aer_ramp_staff: Аэропорт!$D$13
Name Aer_repl_body: Аэропорт!$D$45
Name Aer_repl_forks: Аэропорт!$D$42
Name Aer_repl_platform: Аэропорт!$D$43
Name Aer_repl_tow: Аэропорт!$D$44
Name Aer_S_apron: Аэропорт!$D$7
Name Aer_S_terminal: Аэропорт!$D$6
Name Aer_sal_ramp: Аэропорт!$D$14
Name Aer_sal_target: Аэропорт!$D$51
Name Aer_shift_h: Аэропорт!$D$25
Name Aer_shifts: Аэропорт!$D$24
Name Aer_site_pct: Аэропорт!$D$56
Name Aer_speed_cap: Аэропорт!$D$33
Name Aer_task_class: Аэропорт!$D$39
Name Aer_temp_min: Аэропорт!$D$46
Name Aer_temp_min_ds: Аэропорт!$D$16
Name Aer_turnover: Аэропорт!$D$52
Name Aer_turnover_ds: Аэропорт!$D$15
Name Aer_unit_mass: Аэропорт!$D$30
Name Cat_auton: Каталог!$M$4:$M$13
Name Cat_cap: Каталог!$K$4:$K$13
Name Cat_charge: Каталог!$N$4:$N$13
Name Cat_code: Каталог!$A$4:$A$13
Name Cat_conf: Каталог!$AE$4:$AE$13
Name Cat_date: Каталог!$AF$4:$AF$13
Name Cat_handling: Каталог!$AA$4:$AA$13
Name Cat_hgt: Каталог!$Q$4:$Q$13
Name Cat_indoor: Каталог!$Z$4:$Z$13

Sheet Легенда
A1: ЭКОНОМИЧЕСКАЯ МОДЕЛЬ ПЛАТФОРМЫ ПОДБОРА РОБОТИЗИРОВАННЫХ РЕШЕНИЙ (кейс ФЦ БАС) — v1.1
A3: Назначение | B3: Прозрачная расчётная модель по п. 3.5 ТЗ: состав оборудования, CAPEX, OPEX, годовой эффект, срок окупаемости, ROI, TCO, чувствительность, интерпретация. Один лист = один тип объекта (Склад / Аэропорт / Медучреждение).
A4: Как читать листы объектов | B4: Блок 1 — параметры объекта из демо-датасета (Датасеты_хакатон.xlsx). Блок 2 — параметры процесса и допущения команды. Блок 3 — расчётный движок: каждая колонка = один прогон сценария (решение × модель приобретения × вариант чувствительности). Блок 4 — сравнение сценариев. Блок 5 — денежный поток по годам. Блок 6 — чувствительность. Блок 7 — заключение.
A5: Цветовая легенда | B5: Синий шрифт — вводимые значения (из датасета или каталога). Жёлтая заливка — допущения команды (обязательно документированы в столбце «Источник»). Чёрный — формулы. Зелёный — ссылки на другой лист. Зелёная заливка — ключевые результаты.
A6: Что менять | B6: Меняйте только синие ячейки (столбец «Значение») на листах Склад / Аэропорт / Медучреждение / Нормативы / Каталог. Все результаты пересчитываются автоматически. Диапазоны min/max — для валидации ввода в платформе.
A7: Сценарии | B7: Базовый (без роботизации) + не менее двух роботизированных: «Покупка» (CAPEX у заказчика) и «RaaS» (аренда/роботы как услуга: ежемесячный платёж, CAPEX только на интеграцию и подготовку объекта). Для каждого объекта также добавлен альтернативный продукт (Покупка B).
A8: Источники данных | B8: Датасет: Датасеты_хакатон.xlsx (листы Склад/Аэропорт/Медучреждение). Цены: catalog_export_v4.csv (столбец «Цена изделия», с НДС, без доставки и ПНР — Дополнения п.6). ТТХ: Примеры_решений_типы_объектов.docx и описания в каталоге. Формулы: ТЗ п.3.5, Дополнения п.2.
A9: Ограничение | B9: Результат является предварительной оценкой (экспресс-предынвестиционная) и требует верификации при обследовании объекта (ТЗ п.3.7.5).
A10: Версия модели | B10: v1.1 от 17.09.2026. Изменения к v1.0: в каталог добавлены поля «класс задачи», «способ обработки груза», «допуск в помещения»; коэффициент замещения труда задаётся парой «задача × способ обработки» (блок 2), а не роботом; добавлены фильтры класса задачи, способа обработки и допуска в помещения. Демо-результаты не изменились. Версия исходных данных: датасет (хакатон), каталог v4.

Sheet Каталог
A1: КАТАЛОГ РЕШЕНИЙ (выборка для демо): цены — catalog_export_v4.csv; ТТХ — Примеры_решений_типы_объектов.docx / описания каталога / допущения
A3: Код решения | B3: Наименование | C3: Производитель | D3: Тип | E3: Подтип | F3: Сценарий (каталог) | G3: Статус (каталог) | H3: УГТ | I3: Рын. потенциал | J3: Цена изделия, руб. (с НДС) | K3: Грузоподъёмность, кг | L3: Макс. скорость, м/с | M3: Автономность, ч | N3: Время зарядки, мин | O3: Длина, мм | P3: Ширина, мм | Q3: Высота, мм | R3: Темп. мин, °C | S3: Темп. макс, °C | T3: Ср. потребляемая мощность, кВт | U3: Заявленная производительность (справочно) | V3: Время загрузки, с | W3: Время разгрузки, с | X3: Коэф. замещения (справочно; в расчёте — по паре задача×способ обработки, блок 2 листа объекта) | Y3: Уличная эксплуатация (1/0) | Z3: Допуск в помещения (1/0) | AA3: Способ обработки груза | AB3: Класс задачи | AC3: Тип навигации | AD3: Источник ТТХ | AE3: ТТХ подтверждены | AF3: Дата актуализации | AG3: Примечание / допущения
A4: DMR-CARRIER-P | B4: DMR Carrier P (FMR, вилочный AMR) | C4: ООО "Диком-Сервис" | D4: Мобильные роботы | E4: FMR | F4: Внутрискладская логистика | G4: piloting | H4: 8 | I4: 4 | J4: 4300000 | K4: 1500 | L4: 1.5 | M4: 10 | N4: 90 | O4: 1975 | P4: 1000 | Q4: 2050 | R4: 5 | S4: 35 | T4: 3 | U4: 40–60 паллет/ч (типичный проект, докс организатора) | V4: 60 | W4: 60 | X4: 0.8 | Y4: 0 | Z4: 1 | AA4: вилы | AB4: транспорт | AC4: SLAM (лидары) | AD4: Docx организатора (пример FMR); цена — CSV каталога | AE4: Частично | AF4: 2026-09-16 | AG4: Габариты в docx даны как В×Ш×Г 2050×1975×1000 — принято: длина 1975, ширина 1000. Время зарядки, темп. диапазон, мощность, времена операций — допущения команды.
A5: AK-2000-2 | B5: AK-2000-2 (FMR) | C5: ООО "ГК Автомакон" | D5: Автономные наземные ТС | E5: FMR | F5: Внутрискладская логистика | G5: operation | H5: 9 | I5: 4 | J5: 2940000 | K5: 1500 | L5: 1.5 | M5: 10 | N5: 90 | O5: 1975 | P5: 1000 | Q5: 2050 | R5: 5 | S5: 35 | T5: 3 | U5: Кейс: 67 роботов в РЦ X5 «Новая Рига» | V5: 60 | W5: 60 | X5: 0.8 | Y5: 0 | Z5: 1 | AA5: вилы | AB5: транспорт | AC5: SLAM | AD5: ТТХ приняты по аналогу FMR (DMR Carrier P) — ТРЕБУЕТ ПРОВЕРКИ по сайту производителя | AE5: Нет | AF5: 2026-09-16 | AG5: В каталоге ТТХ отсутствуют; по Дополнениям п.4 недостающие ТТХ заполняются из открытых источников. До подтверждения — решение помечается «требует проверки».
A6: RONAVI-H1500 | B6: Ronavi H1500 (AMR, до 1500 кг) | C6: ООО "Ронави Роботикс" | D6: Мобильные роботы | E6: AMR | F6: Внутрискладская логистика | G6: operation | H6: 8 | I6: 4 | J6: 2700000 | K6: 1500 | L6: 1.5 | M6: 6 | N6: 18 | O6: 1044 | P6: 654 | Q6: 380 | R6: 5 | S6: 25 | T6: 1 | U6: 80–100 паллет/ч (типовая конфигурация зоны, docx) | V6: 30 | W6: 30 | X6: 0.6 | Y6: 0 | Z6: 1 | AA6: платформа | AB6: транспорт | AC6: QR-метки + SLAM | AD6: Docx организатора; цена — CSV каталога | AE6: Да | AF6: 2026-09-16 | AG6: Робот подъёмного типа: требует передачи паллет через станции/конвейер (не забирает с пола) — отсюда коэф. замещения 0.6 и повышенная доля подготовки объекта.
A7: RONAVI-M | B7: Ronavi M (AMR для стеллажей/тележек, до 1200 кг) | C7: ООО "Ронави Роботикс" | D7: Мобильные роботы | E7: AMR | F7: Внутрискладская логистика | G7: piloting | H7: 7 | I7: 4 | J7: 2400000 | K7: 1200 | L7: 1.5 | M7: 6 | N7: 18 | O7: 1044 | P7: 654 | Q7: 380 | R7: 5 | S7: 30 | T7: 1 | U7: — | V7: 45 | W7: 45 | X7: 0.8 | Y7: 0 | Z7: 1 | AA7: платформа | AB7: транспорт | AC7: QR-метки + SLAM | AD7: Описание каталога (назначение, грузоподъёмность); остальные ТТХ по аналогу H1500 — ТРЕБУЮТ ПРОВЕРКИ | AE7: Частично | AF7: 2026-09-16 | AG7: Робот с поворотным кругом для транспортировки мобильных стеллажей/столиков — подходит под больничные тележки (подъезд под тележку).
A8: MOROS-AMR800 | B8: AMR 800 (Морос, до 800 кг) | C8: ООО "Морос" | D8: Мобильные роботы | E8: AMR | F8: Внутрискладская логистика | G8: operation | H8: 9 | I8: 4 | J8: 1800000 | K8: 800 | L8: 1.5 | M8: 20 | N8: 60 | O8: 1100 | P8: 600 | Q8: 230 | R8: 5 | S8: 30 | T8: 1 | U8: Кейс: 27 роботов на складах e-commerce | V8: 45 | W8: 45 | X8: 0.8 | Y8: 0 | Z8: 1 | AA8: платформа | AB8: транспорт | AC8: SLAM | AD8: Описание каталога (AMR 1500: 1100×600×230, 1.5 м/с, проезд от 680 мм, 22 ч) — приняты по аналогу для AMR 800; ТРЕБУЮТ ПРОВЕРКИ | AE8: Частично | AF8: 2026-09-16 | AG8: Подходит под перевозку тележек до 800 кг.
A9: RONAVI-SD | B9: Ronavi SD (AMR, до 10 кг) | C9: ООО "Ронави Роботикс" | D9: Мобильные роботы | E9: AMR | F9: Внутрискладская логистика | G9: piloting | H9: 8 | I9: 4 | J9: 1400000 | K9: 10 | L9: 2.5 | M9: 10 | N9: 60 | O9: 420 | P9: 400 | Q9: 200 | R9: 5 | S9: 30 | T9: 0.3 | U9: — | V9: 20 | W9: 20 | X9: 0.5 | Y9: 0 | Z9: 1 | AA9: кузов | AB9: транспорт | AC9: QR-метки | AD9: Docx организатора (пример для медучреждения) | AE9: Да | AF9: 2026-09-16 | AG9: Мин. ширина проезда 700 мм. Применим только для лёгкой доставки (медикаменты, пробы) — исключается фильтром по грузоподъёмности для процесса «тележки».
A10: PUDUBOT-2 | B10: PuduBot 2 (робот-доставщик) | C10: Pudu Robotics (внешний) | D10: Мобильные роботы | E10: Робот-доставщик | F10: Доставка внутри помещений | G10: внешний источник | K10: 10 | L10: 1.2 | M10: 12 | N10: 240 | O10: 580 | P10: 535 | Q10: 1290 | R10: 5 | S10: 35 | T10: 0.3 | U10: 10 кг на полку | V10: 20 | W10: 20 | X10: 0.5 | Y10: 0 | Z10: 1 | AA10: кузов | AB10: транспорт | AC10: VSLAM + лазерный SLAM | AD10: Docx организатора; цены в каталоге ФЦ БАС нет | AE10: Частично | AF10: 2026-09-16 | AG10: Нет цены в каталоге организатора → в расчёт не включается без ввода цены; отсутствует в реестре отечественных решений.
A11: COGNITIVE-TUG | B11: Беспилотный тягач (Cognitive Pilot) | C11: АО "Когнитив Пилот" | D11: Автономные наземные ТС | E11: Беспилотный тягач | F11: Перевозка грузов на закрытых площадках | G11: operation | H11: 8 | I11: 3 | J11: 4000000 | K11: 3000 | L11: 4.17 | M11: 24 | N11: 30 | O11: 2300 | P11: 1400 | Q11: 1500 | R11: -40 | S11: 45 | T11: 6 | U11: Кейс: 45 тягачей для Пулково (перевозка багажа) | V11: 180 | W11: 180 | X11: 0.8 | Y11: 1 | Z11: 0 | AA11: буксировка | AB11: транспорт | AC11: Мультисенсорный автопилот | AD11: Docx организатора; цена — CSV каталога | AE11: Да | AF11: 2026-09-16 | AG11: Гибридная СУ: «энергия» смоделирована как эквивалент 6 кВт·ч/ч работы (топливо+электро) — допущение. Скорость принята рабочая 15 км/ч (4.17 м/с) из диапазона 5–25 км/ч. Время сцепки/расцепки тележек 180 с — допущение.
A12: EVOCARGO-N1 | B12: EVOCARGO N1 (беспилотный электрогрузовик) | C12: ООО "Эвокарго" | D12: Автономные наземные ТС | E12: Беспилотный грузовик | F12: Перевозка грузов на закрытых площадках | G12: operation | H12: 9 | I12: 5 | J12: 6000000 | K12: 2000 | L12: 5.56 | M12: 8 | N12: 30 | O12: 5000 | P12: 1800 | Q12: 2200 | R12: -40 | S12: 50 | T12: 6 | U12: 6 европаллет; запас хода 150–200 км | V12: 240 | W12: 240 | X12: 0.8 | Y12: 1 | Z12: 0 | AA12: кузов | AB12: транспорт | AC12: Автопилот L4–5 | AD12: Docx организатора; цена — CSV каталога | AE12: Да | AF12: 2026-09-16 | AG12: Автономность 8 ч оценена из АКБ 36 кВт·ч при 6 кВт·ч/ч (допущение). Скорость принята 20 км/ч (5.56 м/с). Погрузка/разгрузка 240 с — допущение (перегрузка багажных контейнеров).
A13: MARK-2-SE | B13: MARK 2 SE (робот-уборщик) | C13: ООО "Р2Б" | D13: Мобильные роботы | E13: Робот-уборщик | F13: Уборка помещений | G13: operation | H13: 9 | I13: 4 | J13: 1900000 | K13: 0 | L13: 1 | M13: 3 | N13: 120 | O13: 860 | P13: 610 | Q13: 980 | R13: 5 | S13: 35 | T13: 1 | U13: до 1000 м²/ч | V13: 0 | W13: 0 | X13: 0.7 | Y13: 0 | Z13: 1 | AA13: щётки | AB13: уборка | AC13: Лидар + камеры | AD13: Docx организатора; цена — CSV каталога | AE13: Да | AF13: 2026-09-16 | AG13: Для процесса «уборка» (расчёт по площади, не по рейсам) — в демо-сценарии не используется; включён для полноты каталога и расширения модели.
A15: Жёлтая заливка = ТТХ приняты по аналогу или являются допущением команды (Дополнения п.4: заполняются из открытых источников и помечаются как требующие проверки). Коэф. замещения труда, времена загрузки/разгрузки и мощность — экспертные допущения команды для всех решений.

Sheet Нормативы
A1: ГЛОБАЛЬНЫЕ НОРМАТИВЫ И ДОПУЩЕНИЯ (используются всеми объектами)
A3: Код (имя ячейки) | B3: Норматив | C3: Ед. изм. | D3: Значение | E3: Min | F3: Max | G3: Источник / обоснование | H3: Тип
A4: N_fot | B4: Коэффициент начислений на ФОТ (страховые взносы) | C4: коэф. | D4: 1.302 | E4: 1.302 | F4: 1.302 | G4: Датасет (все листы): ОПФ 22% + ОМС 5.1% + ОСС 2.9% + НСиПЗ 0.2% = 30.2% | H4: норматив/датасет | I4: payroll_multiplier
A5: N_util | B5: Коэффициент загрузки робота (доля продуктивного времени: зарядка, ожидание, простои) | C5: доля | D5: 0.8 | E5: 0.7 | F5: 0.85 | G5: Датасет, лист «Легенда»: типовой KPI AMR 70–85% | H5: норматив/датасет | I5: productive_time_share
A6: N_avail | B6: Коэффициент технической готовности (доступности) робота | C6: доля | D6: 0.9 | E6: 0.9 | F6: 0.98 | G6: Допущение команды: плановое ТО и отказы; типовой SLA вендоров 95–98% | H6: допущение | I6: technical_availability
A7: N_reserve | B7: Резерв парка роботов на пиковую нагрузку | C7: доля | D7: 0.1 | E7: 0.15 | F7: 0.2 | G7: Датасет, лист «Легенда»: резерв 15–20% | H7: норматив/датасет | I7: fleet_reserve_share
A8: N_kv | B8: Отношение средней эксплуатационной скорости к максимальной (разгон, повороты, трафик, зоны людей) | C8: коэф. | D8: 1 | E8: 0.5 | F8: 0.8 | G8: Допущение команды (практика проектов AMR); проверяется имитацией | H8: допущение | I8: operating_speed_factor
A9: N_charger_ratio | B9: Роботов на одну зарядную станцию | C9: шт./станцию | D9: 2 | E9: 2 | F9: 6 | G9: Допущение команды (opportunity charging) | H9: допущение | I9: robots_per_charger
A10: N_charger_price | B10: Стоимость зарядной станции с монтажом | C10: руб. | D10: 1000 | E10: 150000 | F10: 500000 | G10: Допущение команды (оценка рынка) | H10: допущение | I10: charger_installed_price
A11: N_charger_kw | B11: Мощность одной зарядной станции | C11: кВт | D11: 5 | E11: 3 | F11: 10 | G11: Допущение команды (типовые станции AMR 3–10 кВт) | H11: допущение | I11: charger_power_kw
A12: N_sw_pct | B12: ПО управления флотом (FMS), разовая лицензия и внедрение, % от стоимости оборудования | C12: доля | D12: 0.1 | E12: 0.05 | F12: 0.15 | G12: Допущение команды | H12: допущение | I12: fms_upfront_share
A13: N_delivery_pct | B13: Доставка оборудования, % от стоимости оборудования | C13: доля | D13: 0.05 | E13: 0.01 | F13: 0.05 | G13: Допущение команды; Дополнения п.6: доставка не включена в цену | H13: допущение | I13: delivery_share
A14: N_pnr_pct | B14: Пусконаладочные работы, % от стоимости оборудования | C14: доля | D14: 0.1 | E14: 0.03 | F14: 0.1 | G14: Допущение команды; Дополнения п.6: ПНР не включены в цену | H14: допущение | I14: commissioning_share
A15: N_training | B15: Обучение персонала заказчика (разово на проект) | C15: руб. | D15: 500 | E15: 100000 | F15: 1000000 | G15: Допущение команды | H15: допущение | I15: training_cost
... A33: N_pb_mid | B33: Граница «средней целесообразности»: срок окупаемости до, лет | C33: лет | D33: 4 | E33: 4 | F33: 7 | G33: ТЗ п.3.5.7 | H33: норматив/датасет | I33: medium_payback_years
A34: N_sens | B34: Шаг анализа чувствительности (±) | C34: доля | D34: 0.2 | E34: 0.1 | F34: 0.3 | G34: Допущение команды (ТЗ п.3.5.6 — минимум 3 параметра) | H34: допущение
A35: N_loss_k_default | B35: Коэффициент потерь рабочего времени персонала (отпуск, болезнь) — по умолчанию для объектов без данных | C35: доля | D35: 0.25 | E35: 0.15 | F35: 0.35 | G35: Датасет «Склад»: 25%; для аэропорта и медучреждения применён как допущение | H35: допущение | I35: staff_time_loss_share

Sheet Склад
A1: ОБЪЕКТ: СКЛАД — процесс: перемещение паллет (приёмка → хранение, хранение → отгрузка)
A2: Синие ячейки — ввод; жёлтая заливка — допущения команды; чёрные — формулы. Результаты помечены зелёной заливкой.
A4: БЛОК 1. ПАРАМЕТРЫ ОБЪЕКТА (демо-датасет организатора, лист «Склад»)
A5: Код | B5: Параметр | C5: Ед. изм. | D5: Значение | E5: Min | F5: Max | G5: Источник / обоснование | H5: Тип
A6: Skl_S_total | B6: Общая площадь склада | C6: м² | D6: 20000 | E6: 10000 | F6: 100000 | G6: Датасет, лист «Склад» | H6: датасет
A7: Skl_S_active | B7: Площадь активной (роботизируемой) зоны | C7: м² | D7: 10000 | E7: 5000 | F7: 50000 | G7: Датасет, лист «Склад» (50% общей площади) | H7: датасет
A8: Skl_aisle_main | B8: Ширина главных проездов | C8: м | D8: 3.5 | E8: 2.5 | F8: 6 | G8: Датасет, лист «Склад» — определяет допустимые габариты робота | H8: датасет
A9: Skl_aisle_rack | B9: Ширина рабочих проходов между стеллажами | C9: м | D9: 2.8 | E9: 1.5 | F9: 4.5 | G9: Датасет, лист «Склад» | H9: датасет
A10: Skl_shifts | B10: Количество рабочих смен в сутки | C10: смен | D10: 2 | E10: 1 | F10: 3 | G10: Датасет, лист «Склад» | H10: датасет | I10: shifts_per_day
A11: Skl_shift_h | B11: Продолжительность смены (с учётом перерывов) | C11: ч | D11: 11 | E11: 10 | F11: 11 | G11: Датасет, лист «Склад» | H11: датасет | I11: operating_hours_per_day
A12: Skl_days | B12: Рабочих дней в году | C12: дн. | D12: 365 | E12: 365 | F12: 365 | G12: Датасет, лист «Склад» | H12: датасет
A13: Skl_peak_k | B13: Пиковый коэффициент нагрузки (макс. час / средний час) | C13: коэф. | D13: 1.5 | E13: 1.2 | F13: 2.5 | G13: Датасет, лист «Склад» | H13: датасет | I13: peak_factor
A14: Skl_in_pallets | B14: Объём приёмки | C14: поддон/сут | D14: 1000 | E14: 500 | F14: 5000 | G14: Датасет, лист «Склад» | H14: датасет | I14: operations_per_day
A15: Skl_out_pallets | B15: Объём отгрузки | C15: поддон/сут | D15: 1000 | E15: 500 | F15: 5000 | G15: Датасет, лист «Склад» | H15: датасет | I15: operations_per_day
A16: Skl_forklift_ops | B16: Операторы погрузчиков (численность, все смены) | C16: чел. | D16: 25 | E16: 5 | F16: 80 | G16: Датасет, лист «Склад» — целевая функция для автономных погрузчиков | H16: датасет
A17: Skl_sal_forklift | B17: Средняя з/п оператора погрузчика (gross) | C17: руб./мес. | D17: 120000 | E17: 80000 | F17: 170000 | G17: Датасет, лист «Склад» | H17: датасет | I17: fleet_operator_monthly_salary, target_monthly_salary
A18: Skl_loss_k | B18: Коэффициент потерь рабочего времени (отпуск, болезнь, текучесть) | C18: доля | D18: 0.25 | E18: 0.15 | F18: 0.35 | G18: Датасет, лист «Склад» | H18: датасет | I18: staff_time_loss_share
A19: Skl_pallet_mass | B19: Средняя масса грузовой единицы (паллет) | C19: кг | D19: 800 | E19: 200 | F19: 1500 | G19: Датасет, лист «Склад» | H19: датасет
A20: Skl_oversize_share | B20: Доля негабаритных/нестандартных грузов (остаётся ручной) | C20: доля | D20: 0.05 | E20: 0 | F20: 0.3 | G20: Датасет, лист «Склад» | H20: датасет
A21: Skl_power_kw | B21: Мощность электроснабжения (доступная) | C21: кВт | D21: 500 | E21: 100 | F21: 3000 | G21: Датасет, лист «Склад» | H21: датасет | I21: available_charging_power_kw
A22: Skl_budget | B22: Планируемый бюджет на роботизацию (CAPEX) | C22: млн руб. | D22: 80 | E22: 10 | F22: 500 | G22: Датасет, лист «Склад» | H22: датасет | I22: budget
A23: Skl_horizon | B23: Горизонт расчёта окупаемости | C23: лет | D23: 5 | E23: 3 | F23: 10 | G23: Датасет, лист «Склад» | H23: датасет | I23: horizon_years
A25: БЛОК 2. ПАРАМЕТРЫ ПРОЦЕССА И ДОПУЩЕНИЯ КОМАНДЫ
A26: Код | B26: Параметр | C26: Ед. изм. | D26: Значение | E26: Min | F26: Max | G26: Источник / обоснование | H26: Тип
A27: Skl_ops_day | B27: Объём операций процесса = приёмка + отгрузка (перемещение паллет док ↔ зона хранения) | C27: оп./сут | D27: =Skl_in_pallets+Skl_out_pallets -> 2000 | G27: Формула из датасета | H27: формула
A28: Skl_auto_share | B28: Доля автоматизируемых операций = 1 − доля негабарита | C28: доля | D28: 1 | G28: Формула из датасета | H28: формула | I28: automatable_share
A29: Skl_hours_day | B29: Часов работы процесса в сутки = смен × продолжительность смены | C29: ч | D29: =Skl_shifts*Skl_shift_h -> 22 | G29: Формула из датасета | H29: формула
A30: Skl_peak_ops_h | B30: Пиковая интенсивность = объём / часов × пиковый коэффициент | C30: оп./ч | D30: =Skl_ops_day/Skl_hours_day*Skl_peak_k -> 136.36364 | G30: Формула из датасета | H30: формула
A31: Skl_unit_mass | B31: Масса единицы груза (паллет) | C31: кг | D31: =Skl_pallet_mass -> 800 | G31: Датасет | H31: формула | I31: load_unit_mass_kg
A32: Skl_divisible | B32: Груз делимый на несколько рейсов (1) / неделимый (0) | C32: 1/0 | D32: 0 | E32: 0 | F32: 1 | G32: Допущение: паллет неделим — при недостаточной грузоподъёмности решение исключается | H32: допущение | I32: load_is_divisible
A33: Skl_L | B33: Средняя длина маршрута (док ↔ ячейка) = √(площадь активной зоны) | C33: м | D33: =SQRT(Skl_S_active) -> 100 | G33: Допущение команды: средняя дистанция перемещения ≈ корню из площади зоны (проверяется на 2D-схеме) | H33: формула | I33: one_way_route_m | J33: there is in input dataset
A34: Skl_speed_cap | B34: Ограничение скорости на объекте | C34: м/с | D34: 1.5 | E34: 0.5 | F34: 2 | G34: Допущение: 1.5 м/с — типовой лимит для AMR/FMR в зонах с людьми | H34: допущение | I34: site_speed_limit_mps | J34: метры в секунду
A35: Skl_lift_share | B35: Доля рейсов через лифт/подъёмник | C35: доля | D35: 0 | E35: 0 | F35: 1 | G35: Датасет: 1 этаж — лифты не требуются | H35: датасет | I35: lift_trip_share
A36: Skl_lift_time | B36: Время ожидания + проезда лифта (в один проход) | C36: с | D36: 0 | E36: 0 | F36: 300 | G36: Не применяется (1 этаж) | H36: датасет | I36: one_way_lift_seconds
A37: Skl_aisle | B37: Минимальная ширина прохода для фильтра решений | C37: м | D37: =MIN(Skl_aisle_main,Skl_aisle_rack) -> 2.8 | G37: Формула из датасета | H37: формула
A38: Skl_clearance | B38: Запас по ширине проезда для безопасного движения | C38: м | D38: 0.6 | E38: 0.3 | F38: 1 | G38: Допущение команды (по 0.3 м с каждой стороны) | H38: допущение
A39: Skl_outdoor_req | B39: Требуется уличная эксплуатация (1/0) | C39: 1/0 | D39: 0 | E39: 0 | F39: 1 | G39: Склад — закрытое отапливаемое помещение | H39: датасет
A40: Skl_task_class | B40: Класс задачи процесса | D40: транспорт | G40: транспорт (рейсы) / уборка (площадь) | H40: датасет
A41: Skl_handling_req | B41: Допустимые способы обработки груза (через ;) | D41: вилы;платформа | G41: Допущение команды: паллет с пола — вилы; платформа — через станции передачи (часть труда остаётся → 0.6) | H41: допущение
A42: Skl_indoor_req | B42: Работа внутри помещений (1/0) | C42: 1/0 | D42: 1 | E42: 0 | F42: 1 | G42: Уличные гибриды/грузовики не допускаются в помещения | H42: датасет
A43: Skl_repl_forks | B43: Коэф. замещения труда: вилы | C43: доля | D43: 0.5 | E43: 0.5 | F43: 0.9 | G43: Допущение команды: полный цикл без станций; остаются высотные/нестандартные операции | H43: допущение | I43: replacement_by_handling :[{forks, 0.5}]
A44: Skl_repl_platform | B44: Коэф. замещения труда: платформа (подъём/станции передачи) | C44: доля | D44: 0 | E44: 0.4 | F44: 0.9 | G44: Допущение команды | H44: допущение
A45: Skl_repl_tow | B45: Коэф. замещения труда: буксировка | C45: доля | D45: 0 | E45: 0.5 | F45: 0.9 | G45: Допущение команды: сцепка тележек остаётся ручной | H45: допущение
A46: Skl_repl_body | B46: Коэф. замещения труда: кузов | C46: доля | D46: 0 | E46: 0.3 | F46: 0.9 | G46: Допущение команды: ручная погрузка/выгрузка кузова | H46: допущение
A47: Skl_temp_min | B47: Минимальная температура в зоне работы | C47: °C | D47: 5 | E47: -30 | F47: 25 | G47: Допущение: отапливаемый склад | H47: допущение
A48: Skl_fte_target | B48: Целевые FTE процесса = операторы погрузчиков × доля их функции в процессе × доля автоматизируемых операций | C48: FTE | D48: =Skl_forklift_ops*Skl_func_share*Skl_auto_share -> 25 | G48: Формула | H48: формула | I48: target_fte | J48: I feel we should calculate it in the service
A49: Skl_func_share | B49: Доля рабочего времени операторов погрузчиков, приходящаяся на перемещение паллет | C49: доля | D49: 1 | E49: 0.5 | F49: 1 | G49: Допущение команды: целевая функция полностью совпадает с процессом | H49: допущение
A50: Skl_labor_target | B50: Годовой ФОТ целевых FTE (с начислениями) | C50: руб./год | D50: =Skl_fte_target*Skl_sal_forklift*12*N_fot -> 46872000 | G50: Формула | H50: формула | I50: target_annual_payroll, baseline_annual_opex
A51: Skl_base_labor | B51: Годовой ФОТ всего целевого персонала процесса (база) | C51: руб./год | D51: =Skl_forklift_ops*Skl_sal_forklift*12*N_fot -> 46872000 | G51: Формула: численность × оклад × 12 × ФОТ-коэф. | H51: формула
A52: Skl_sal_target | B52: Средний оклад целевого персонала (для оценки стоимости замены) | C52: руб./мес. | D52: =Skl_sal_forklift -> 120000 | G52: Датасет | H52: формула
A53: Skl_turnover | B53: Годовая текучесть целевого персонала | C53: доля | D53: 0 | E53: 0 | F53: 0.6 | G53: В датасете «Склад» показатель отсутствует → принято 0 (эффект не учитывается); при наличии данных — ввести | H53: допущение | I53: annual_staff_turnover
A54: Skl_fleet_per_shift | B54: Операторы флота роботов (диспетчер/техник) на смену | C54: чел./смену | D54: 1 | E54: 0 | F54: 3 | G54: Допущение команды | H54: допущение | I54: fleet_operators_per_shift
A55: Skl_fleet_sal | B55: Оклад оператора флота | C55: руб./мес. | D55: =Skl_sal_forklift -> 120000 | G55: Допущение: на уровне оператора погрузчика | H55: формула
A56: Skl_site_pct | B56: Подготовка объекта (разметка, QR-метки, Wi-Fi, ворота), % от стоимости парка | C56: доля | D56: 0.05 | E56: 0.02 | F56: 0.15 | G56: Допущение команды | H56: допущение | I56: site_preparation_share
A57: Skl_integration | B57: Интеграция с WMS / 1С:ERP | C57: руб. | D57: 0 | E57: 500000 | F57: 6000000 | G57: Допущение команды (оценка рынка интеграторов; датасет: WMS есть, 1С:ERP через REST/COM) | H57: допущение | I57: integration_cost
A58: Skl_consum_per_robot | B58: Расходные материалы на робота в год | C58: руб./год | D58: 0 | E58: 0 | F58: 200000 | G58: Для складских AMR/FMR отдельные расходники не выделяются (учтены в сервисе) | H58: допущение | I58: annual_consumables_per_robot
A59: Skl_other_effects | B59: Иные измеримые эффекты (снижение ошибок, потерь, ускорение оборота) | C59: руб./год | D59: 0 | E59: 0 | G59: Ввод пользователя; в датасете нет данных о стоимости ошибок → 0 (консервативно) | H59: допущение
A61: БЛОК 3. РАСЧЁТНЫЙ ДВИЖОК (каждая колонка = один прогон: решение × модель приобретения × вариант чувствительности)
B62: Сценарий | E62: Покупка A | F62: Покупка A | G62: Покупка A | H62: Покупка A | I62: Покупка A | J62: Покупка A | K62: Покупка A | L62: RaaS A | M62: RaaS A | N62: RaaS A | O62: RaaS A | P62: RaaS A | Q62: RaaS A | R62: RaaS A | S62: Покупка B | T62: Покупка B | U62: Покупка B | V62: Покупка B | W62: Покупка B | X62: Покупка B | Y62: Покупка B
B63: Код решения (см. лист Каталог) | E63: RONAVI-H1500 | F63: DMR-CARRIER-P | G63: DMR-CARRIER-P | H63: DMR-CARRIER-P | I63: DMR-CARRIER-P | J63: DMR-CARRIER-P | K63: DMR-CARRIER-P | L63: DMR-CARRIER-P | M63: DMR-CARRIER-P | N63: DMR-CARRIER-P | O63: DMR-CARRIER-P | P63: DMR-CARRIER-P | Q63: DMR-CARRIER-P | R63: DMR-CARRIER-P | S63: RONAVI-H1500 | T63: RONAVI-H1500 | U63: RONAVI-H1500 | V63: RONAVI-H1500 | W63: RONAVI-H1500 | X63: RONAVI-H1500 | Y63: RONAVI-H1500
B64: Модель приобретения | E64: Покупка | F64: Покупка | G64: Покупка | H64: Покупка | I64: Покупка | J64: Покупка | K64: Покупка | L64: RaaS | M64: RaaS | N64: RaaS | O64: RaaS | P64: RaaS | Q64: RaaS | R64: RaaS | S64: Покупка | T64: Покупка | U64: Покупка | V64: Покупка | W64: Покупка | X64: Покупка | Y64: Покупка
B65: k_цена оборудования | E65: 1 | F65: =1-N_sens -> 0.8 | G65: =1+N_sens -> 1.2 | H65: 1 | I65: 1 | J65: 1 | K65: 1 | L65: 1 | M65: =1-N_sens -> 0.8 | N65: =1+N_sens -> 1.2 | O65: 1 | P65: 1 | Q65: 1 | R65: 1 | S65: 1 | T65: =1-N_sens -> 0.8 | U65: =1+N_sens -> 1.2 | V65: 1 | W65: 1 | X65: 1 | Y65: 1
B66: k_объём операций | E66: 1 | F66: 1 | G66: 1 | H66: =1-N_sens -> 0.8 | I66: =1+N_sens -> 1.2 | J66: 1 | K66: 1 | L66: 1 | M66: 1 | N66: 1 | O66: =1-N_sens -> 0.8 | P66: =1+N_sens -> 1.2 | Q66: 1 | R66: 1 | S66: 1 | T66: 1 | U66: 1 | V66: =1-N_sens -> 0.8 | W66: =1+N_sens -> 1.2 | X66: 1 | Y66: 1
B67: k_стоимость труда | E67: 1 | F67: 1 | G67: 1 | H67: 1 | I67: 1 | J67: =1-N_sens -> 0.8 | K67: =1+N_sens -> 1.2 | L67: 1 | M67: 1 | N67: 1 | O67: 1 | P67: 1 | Q67: =1-N_sens -> 0.8 | R67: =1+N_sens -> 1.2 | S67: 1 | T67: 1 | U67: 1 | V67: 1 | W67: 1 | X67: =1-N_sens -> 0.8 | Y67: =1+N_sens -> 1.2
B68: Вариант расчёта | E68: База | F68: Оборуд. − | G68: Оборуд. + | H68: Объём − | I68: Объём + | J68: Труд − | K68: Труд + | L68: База | M68: Оборуд. − | N68: Оборуд. + | O68: Объём − | P68: Объём + | Q68: Труд − | R68: Труд + | S68: База | T68: Оборуд. − | U68: Оборуд. + | V68: Объём − | W68: Объём + | X68: Труд − | Y68: Труд +
B70: 3.1 Параметры решения (подтягиваются из листа «Каталог» по коду)
A71: sol_name | B71: Наименование решения | D71: INDEX(Cat_name,MATCH(63,Cat_code,0)) | E71: =INDEX(Cat_name,MATCH(E$63,Cat_code,0)) -> Ronavi H1500 (AMR, до 1500 кг) | F71: =INDEX(Cat_name,MATCH(F$63,Cat_code,0)) -> DMR Carrier P (FMR, вилочный AMR) | G71: =INDEX(Cat_name,MATCH(G$63,Cat_code,0)) -> DMR Carrier P (FMR, вилочный AMR) | H71: =INDEX(Cat_name,MATCH(H$63,Cat_code,0)) -> DMR Carrier P (FMR, вилочный AMR) | I71: =INDEX(Cat_name,MATCH(I$63,Cat_code,0)) -> DMR Carrier P (FMR, вилочный AMR) | J71: =INDEX(Cat_name,MATCH(J$63,Cat_code,0)) -> DMR Carrier P (FMR, вилочный AMR) | K71: =INDEX(Cat_name,MATCH(K$63,Cat_code,0)) -> DMR Carrier P (FMR, вилочный AMR) | L71: =INDEX(Cat_name,MATCH(L$63,Cat_code,0)) -> DMR Carrier P (FMR, вилочный AMR) | ... Y71: =INDEX(Cat_name,MATCH(Y$63,Cat_code,0)) -> Ronavi H1500 (AMR, до 1500 кг)
A72: sol_status | B72: Статус в каталоге | D72: INDEX(Cat_status,MATCH(63,Cat_code,0)) | E72: =INDEX(Cat_status,MATCH(E$63,Cat_code,0)) -> operation | F72: =INDEX(Cat_status,MATCH(F$63,Cat_code,0)) -> piloting | G72: =INDEX(Cat_status,MATCH(G$63,Cat_code,0)) -> piloting | H72: =INDEX(Cat_status,MATCH(H$63,Cat_code,0)) -> piloting | I72: =INDEX(Cat_status,MATCH(I$63,Cat_code,0)) -> piloting | J72: =INDEX(Cat_status,MATCH(J$63,Cat_code,0)) -> piloting | K72: =INDEX(Cat_status,MATCH(K$63,Cat_code,0)) -> piloting | L72: =INDEX(Cat_status,MATCH(L$63,Cat_code,0)) -> piloting | ... Y72: =INDEX(Cat_status,MATCH(Y$63,Cat_code,0)) -> operation
A73: sol_conf | B73: ТТХ подтверждены | D73: INDEX(Cat_conf,MATCH(63,Cat_code,0)) | E73: =INDEX(Cat_conf,MATCH(E$63,Cat_code,0)) -> Да | F73: =INDEX(Cat_conf,MATCH(F$63,Cat_code,0)) -> Частично | G73: =INDEX(Cat_conf,MATCH(G$63,Cat_code,0)) -> Частично | H73: =INDEX(Cat_conf,MATCH(H$63,Cat_code,0)) -> Частично | I73: =INDEX(Cat_conf,MATCH(I$63,Cat_code,0)) -> Частично | J73: =INDEX(Cat_conf,MATCH(J$63,Cat_code,0)) -> Частично | K73: =INDEX(Cat_conf,MATCH(K$63,Cat_code,0)) -> Частично | L73: =INDEX(Cat_conf,MATCH(L$63,Cat_code,0)) -> Частично | ... Y73: =INDEX(Cat_conf,MATCH(Y$63,Cat_code,0)) -> Да
A74: price0 | B74: Цена изделия по каталогу (с НДС) | C74: руб. | D74: INDEX(Cat_price,MATCH(63,Cat_code,0)) | E74: =INDEX(Cat_price,MATCH(E$63,Cat_code,0)) -> 2700000 | F74: =INDEX(Cat_price,MATCH(F$63,Cat_code,0)) -> 4300000 | G74: =INDEX(Cat_price,MATCH(G$63,Cat_code,0)) -> 4300000 | H74: =INDEX(Cat_price,MATCH(H$63,Cat_code,0)) -> 4300000 | I74: =INDEX(Cat_price,MATCH(I$63,Cat_code,0)) -> 4300000 | J74: =INDEX(Cat_price,MATCH(J$63,Cat_code,0)) -> 4300000 | K74: =INDEX(Cat_price,MATCH(K$63,Cat_code,0)) -> 4300000 | L74: =INDEX(Cat_price,MATCH(L$63,Cat_code,0)) -> 4300000 | ... Y74: =INDEX(Cat_price,MATCH(Y$63,Cat_code,0)) -> 2700000
A75: price | B75: Цена в расчёте (с учётом k_цена) | C75: руб. | D75: [price0]*65 | E75: =E74*E$65 -> 2700000 | F75: =F74*F$65 -> 3440000 | G75: =G74*G$65 -> 5160000 | H75: =H74*H$65 -> 4300000 | I75: =I74*I$65 -> 4300000 | J75: =J74*J$65 -> 4300000 | K75: =K74*K$65 -> 4300000 | L75: =L74*L$65 -> 4300000 | ... Y75: =Y74*Y$65 -> 2700000
A76: cap | B76: Грузоподъёмность | C76: кг | D76: INDEX(Cat_cap,MATCH(63,Cat_code,0)) | E76: =INDEX(Cat_cap,MATCH(E$63,Cat_code,0)) -> 1500 | F76: =INDEX(Cat_cap,MATCH(F$63,Cat_code,0)) -> 1500 | G76: =INDEX(Cat_cap,MATCH(G$63,Cat_code,0)) -> 1500 | H76: =INDEX(Cat_cap,MATCH(H$63,Cat_code,0)) -> 1500 | I76: =INDEX(Cat_cap,MATCH(I$63,Cat_code,0)) -> 1500 | J76: =INDEX(Cat_cap,MATCH(J$63,Cat_code,0)) -> 1500 | K76: =INDEX(Cat_cap,MATCH(K$63,Cat_code,0)) -> 1500 | L76: =INDEX(Cat_cap,MATCH(L$63,Cat_code,0)) -> 1500 | ... Y76: =INDEX(Cat_cap,MATCH(Y$63,Cat_code,0)) -> 1500
A77: vmax | B77: Максимальная скорость | C77: м/с | D77: INDEX(Cat_vmax,MATCH(63,Cat_code,0)) | E77: =INDEX(Cat_vmax,MATCH(E$63,Cat_code,0)) -> 1.5 | F77: =INDEX(Cat_vmax,MATCH(F$63,Cat_code,0)) -> 1.5 | G77: =INDEX(Cat_vmax,MATCH(G$63,Cat_code,0)) -> 1.5 | H77: =INDEX(Cat_vmax,MATCH(H$63,Cat_code,0)) -> 1.5 | I77: =INDEX(Cat_vmax,MATCH(I$63,Cat_code,0)) -> 1.5 | J77: =INDEX(Cat_vmax,MATCH(J$63,Cat_code,0)) -> 1.5 | K77: =INDEX(Cat_vmax,MATCH(K$63,Cat_code,0)) -> 1.5 | L77: =INDEX(Cat_vmax,MATCH(L$63,Cat_code,0)) -> 1.5 | ... Y77: =INDEX(Cat_vmax,MATCH(Y$63,Cat_code,0)) -> 1.5
A78: tload | B78: Время загрузки (сцепки/подхвата) | C78: с | D78: INDEX(Cat_tload,MATCH(63,Cat_code,0)) | E78: =INDEX(Cat_tload,MATCH(E$63,Cat_code,0)) -> 30 | F78: =INDEX(Cat_tload,MATCH(F$63,Cat_code,0)) -> 60 | G78: =INDEX(Cat_tload,MATCH(G$63,Cat_code,0)) -> 60 | H78: =INDEX(Cat_tload,MATCH(H$63,Cat_code,0)) -> 60 | I78: =INDEX(Cat_tload,MATCH(I$63,Cat_code,0)) -> 60 | J78: =INDEX(Cat_tload,MATCH(J$63,Cat_code,0)) -> 60 | K78: =INDEX(Cat_tload,MATCH(K$63,Cat_code,0)) -> 60 | L78: =INDEX(Cat_tload,MATCH(L$63,Cat_code,0)) -> 60 | ... Y78: =INDEX(Cat_tload,MATCH(Y$63,Cat_code,0)) -> 30
A79: tunload | B79: Время разгрузки | C79: с | D79: INDEX(Cat_tunload,MATCH(63,Cat_code,0)) | E79: =INDEX(Cat_tunload,MATCH(E$63,Cat_code,0)) -> 30 | F79: =INDEX(Cat_tunload,MATCH(F$63,Cat_code,0)) -> 60 | G79: =INDEX(Cat_tunload,MATCH(G$63,Cat_code,0)) -> 60 | H79: =INDEX(Cat_tunload,MATCH(H$63,Cat_code,0)) -> 60 | I79: =INDEX(Cat_tunload,MATCH(I$63,Cat_code,0)) -> 60 | J79: =INDEX(Cat_tunload,MATCH(J$63,Cat_code,0)) -> 60 | K79: =INDEX(Cat_tunload,MATCH(K$63,Cat_code,0)) -> 60 | L79: =INDEX(Cat_tunload,MATCH(L$63,Cat_code,0)) -> 60 | ... Y79: =INDEX(Cat_tunload,MATCH(Y$63,Cat_code,0)) -> 30
A80: power | B80: Средняя потребляемая мощность | C80: кВт | D80: INDEX(Cat_power,MATCH(63,Cat_code,0)) | E80: =INDEX(Cat_power,MATCH(E$63,Cat_code,0)) -> 1 | F80: =INDEX(Cat_power,MATCH(F$63,Cat_code,0)) -> 3 | G80: =INDEX(Cat_power,MATCH(G$63,Cat_code,0)) -> 3 | H80: =INDEX(Cat_power,MATCH(H$63,Cat_code,0)) -> 3 | I80: =INDEX(Cat_power,MATCH(I$63,Cat_code,0)) -> 3 | J80: =INDEX(Cat_power,MATCH(J$63,Cat_code,0)) -> 3 | K80: =INDEX(Cat_power,MATCH(K$63,Cat_code,0)) -> 3 | L80: =INDEX(Cat_power,MATCH(L$63,Cat_code,0)) -> 3 | ... Y80: =INDEX(Cat_power,MATCH(Y$63,Cat_code,0)) -> 1
A81: handling | B81: Способ обработки груза | D81: INDEX(Cat_handling,MATCH(63,Cat_code,0)) | E81: =INDEX(Cat_handling,MATCH(E$63,Cat_code,0)) -> платформа | F81: =INDEX(Cat_handling,MATCH(F$63,Cat_code,0)) -> вилы | G81: =INDEX(Cat_handling,MATCH(G$63,Cat_code,0)) -> вилы | H81: =INDEX(Cat_handling,MATCH(H$63,Cat_code,0)) -> вилы | I81: =INDEX(Cat_handling,MATCH(I$63,Cat_code,0)) -> вилы | J81: =INDEX(Cat_handling,MATCH(J$63,Cat_code,0)) -> вилы | K81: =INDEX(Cat_handling,MATCH(K$63,Cat_code,0)) -> вилы | L81: =INDEX(Cat_handling,MATCH(L$63,Cat_code,0)) -> вилы | ... Y81: =INDEX(Cat_handling,MATCH(Y$63,Cat_code,0)) -> платформа
A82: indoor | B82: Допуск в помещения | C82: 1/0 | D82: INDEX(Cat_indoor,MATCH(63,Cat_code,0)) | E82: =INDEX(Cat_indoor,MATCH(E$63,Cat_code,0)) -> 1 | F82: =INDEX(Cat_indoor,MATCH(F$63,Cat_code,0)) -> 1 | G82: =INDEX(Cat_indoor,MATCH(G$63,Cat_code,0)) -> 1 | H82: =INDEX(Cat_indoor,MATCH(H$63,Cat_code,0)) -> 1 | I82: =INDEX(Cat_indoor,MATCH(I$63,Cat_code,0)) -> 1 | J82: =INDEX(Cat_indoor,MATCH(J$63,Cat_code,0)) -> 1 | K82: =INDEX(Cat_indoor,MATCH(K$63,Cat_code,0)) -> 1 | L82: =INDEX(Cat_indoor,MATCH(L$63,Cat_code,0)) -> 1 | ... Y82: =INDEX(Cat_indoor,MATCH(Y$63,Cat_code,0)) -> 1
A83: task | B83: Класс задачи решения | D83: INDEX(Cat_task,MATCH(63,Cat_code,0)) | E83: =INDEX(Cat_task,MATCH(E$63,Cat_code,0)) -> транспорт | F83: =INDEX(Cat_task,MATCH(F$63,Cat_code,0)) -> транспорт | G83: =INDEX(Cat_task,MATCH(G$63,Cat_code,0)) -> транспорт | H83: =INDEX(Cat_task,MATCH(H$63,Cat_code,0)) -> транспорт | I83: =INDEX(Cat_task,MATCH(I$63,Cat_code,0)) -> транспорт | J83: =INDEX(Cat_task,MATCH(J$63,Cat_code,0)) -> транспорт | K83: =INDEX(Cat_task,MATCH(K$63,Cat_code,0)) -> транспорт | L83: =INDEX(Cat_task,MATCH(L$63,Cat_code,0)) -> транспорт | ... Y83: =INDEX(Cat_task,MATCH(Y$63,Cat_code,0)) -> транспорт
A84: repl | B84: Коэффициент замещения труда = по паре «задача × способ обработки» (блок 2) | C84: доля | D84: IF([handling]="вилы",Skl_repl_forks,IF([handling]="платформа",Skl_repl_platform,IF([handling]="буксировка",Skl_repl_tow,IF([handling]="кузов",Skl_repl_body,0)))) | E84: =IF(F81="вилы",Skl_repl_forks,IF(F81="платформа",Skl_repl_platform,IF(F81="буксировка",Skl_repl_tow,IF(F81="кузов",Skl_repl_body,0)))) -> 0.5 | F84: =IF(F81="вилы",Skl_repl_forks,IF(F81="платформа",Skl_repl_platform,IF(F81="буксировка",Skl_repl_tow,IF(F81="кузов",Skl_repl_body,0)))) -> 0.5 | G84: =IF(G81="вилы",Skl_repl_forks,IF(G81="платформа",Skl_repl_platform,IF(G81="буксировка",Skl_repl_tow,IF(G81="кузов",Skl_repl_body,0)))) -> 0.5 | H84: =IF(H81="вилы",Skl_repl_forks,IF(H81="платформа",Skl_repl_platform,IF(H81="буксировка",Skl_repl_tow,IF(H81="кузов",Skl_repl_body,0)))) -> 0.5 | I84: =IF(I81="вилы",Skl_repl_forks,IF(I81="платформа",Skl_repl_platform,IF(I81="буксировка",Skl_repl_tow,IF(I81="кузов",Skl_repl_body,0)))) -> 0.5 | J84: =IF(J81="вилы",Skl_repl_forks,IF(J81="платформа",Skl_repl_platform,IF(J81="буксировка",Skl_repl_tow,IF(J81="кузов",Skl_repl_body,0)))) -> 0.5 | K84: =IF(K81="вилы",Skl_repl_forks,IF(K81="платформа",Skl_repl_platform,IF(K81="буксировка",Skl_repl_tow,IF(K81="кузов",Skl_repl_body,0)))) -> 0.5 | L84: =IF(L81="вилы",Skl_repl_forks,IF(L81="платформа",Skl_repl_platform,IF(L81="буксировка",Skl_repl_tow,IF(L81="кузов",Skl_repl_body,0)))) -> 0.5 | M84: =IF(M81="вилы",Skl_repl_forks,IF(M81="платформа",Skl_repl_platform,IF(M81="буксировка",Skl_repl_tow,IF(M81="кузов",Skl_repl_body,0)))) -> 0.5 | ... Y84: =IF(Y81="вилы",Skl_repl_forks,IF(Y81="платформа",Skl_repl_platform,IF(Y81="буксировка",Skl_repl_tow,IF(Y81="кузов",Skl_repl_body,0)))) -> 0
A85: wid | B85: Ширина робота | C85: мм | D85: INDEX(Cat_wid,MATCH(63,Cat_code,0)) | E85: =INDEX(Cat_wid,MATCH(E$63,Cat_code,0)) -> 654 | F85: =INDEX(Cat_wid,MATCH(F$63,Cat_code,0)) -> 1000 | G85: =INDEX(Cat_wid,MATCH(G$63,Cat_code,0)) -> 1000 | H85: =INDEX(Cat_wid,MATCH(H$63,Cat_code,0)) -> 1000 | I85: =INDEX(Cat_wid,MATCH(I$63,Cat_code,0)) -> 1000 | J85: =INDEX(Cat_wid,MATCH(J$63,Cat_code,0)) -> 1000 | K85: =INDEX(Cat_wid,MATCH(K$63,Cat_code,0)) -> 1000 | L85: =INDEX(Cat_wid,MATCH(L$63,Cat_code,0)) -> 1000 | ... Y85: =INDEX(Cat_wid,MATCH(Y$63,Cat_code,0)) -> 654
A86: tmin | B86: Допустимая минимальная температура | C86: °C | D86: INDEX(Cat_tmin,MATCH(63,Cat_code,0)) | E86: =INDEX(Cat_tmin,MATCH(E$63,Cat_code,0)) -> 5 | F86: =INDEX(Cat_tmin,MATCH(F$63,Cat_code,0)) -> 5 | G86: =INDEX(Cat_tmin,MATCH(G$63,Cat_code,0)) -> 5 | H86: =INDEX(Cat_tmin,MATCH(H$63,Cat_code,0)) -> 5 | I86: =INDEX(Cat_tmin,MATCH(I$63,Cat_code,0)) -> 5 | J86: =INDEX(Cat_tmin,MATCH(J$63,Cat_code,0)) -> 5 | K86: =INDEX(Cat_tmin,MATCH(K$63,Cat_code,0)) -> 5 | L86: =INDEX(Cat_tmin,MATCH(L$63,Cat_code,0)) -> 5 | ... Y86: =INDEX(Cat_tmin,MATCH(Y$63,Cat_code,0)) -> 5
A87: outdoor | B87: Уличная эксплуатация | C87: 1/0 | D87: INDEX(Cat_outdoor,MATCH(63,Cat_code,0)) | E87: =INDEX(Cat_outdoor,MATCH(E$63,Cat_code,0)) -> 0 | F87: =INDEX(Cat_outdoor,MATCH(F$63,Cat_code,0)) -> 0 | G87: =INDEX(Cat_outdoor,MATCH(G$63,Cat_code,0)) -> 0 | H87: =INDEX(Cat_outdoor,MATCH(H$63,Cat_code,0)) -> 0 | I87: =INDEX(Cat_outdoor,MATCH(I$63,Cat_code,0)) -> 0 | J87: =INDEX(Cat_outdoor,MATCH(J$63,Cat_code,0)) -> 0 | K87: =INDEX(Cat_outdoor,MATCH(K$63,Cat_code,0)) -> 0 | L87: =INDEX(Cat_outdoor,MATCH(L$63,Cat_code,0)) -> 0 | ... Y87: =INDEX(Cat_outdoor,MATCH(Y$63,Cat_code,0)) -> 0
B88: 3.2 Проверка применимости (ТЗ п.3.4.3: ключевое ограничение → решение не рекомендуется)
A89: chk_task | B89: Проверка класса задачи (транспорт / уборка) | D89: IF([task]=Skl_task_class,"ОК","НЕТ") | E89: =IF(E83=Skl_task_class,"ОК","НЕТ") -> ОК | F89: =IF(F83=Skl_task_class,"ОК","НЕТ") -> ОК | G89: =IF(G83=Skl_task_class,"ОК","НЕТ") -> ОК | H89: =IF(H83=Skl_task_class,"ОК","НЕТ") -> ОК | I89: =IF(I83=Skl_task_class,"ОК","НЕТ") -> ОК | J89: =IF(J83=Skl_task_class,"ОК","НЕТ") -> ОК | K89: =IF(K83=Skl_task_class,"ОК","НЕТ") -> ОК | L89: =IF(L83=Skl_task_class,"ОК","НЕТ") -> ОК | ... Y89: =IF(Y83=Skl_task_class,"ОК","НЕТ") -> ОК
A90: chk_handling | B90: Проверка способа обработки груза (в списке допустимых для задачи) | D90: IF(ISNUMBER(SEARCH([handling],Skl_handling_req)),"ОК","НЕТ") | E90: =IF(ISNUMBER(SEARCH(E81,Skl_handling_req)),"ОК","НЕТ") -> ОК | F90: =IF(ISNUMBER(SEARCH(F81,Skl_handling_req)),"ОК","НЕТ") -> ОК | G90: =IF(ISNUMBER(SEARCH(G81,Skl_handling_req)),"ОК","НЕТ") -> ОК | H90: =IF(ISNUMBER(SEARCH(H81,Skl_handling_req)),"ОК","НЕТ") -> ОК | I90: =IF(ISNUMBER(SEARCH(I81,Skl_handling_req)),"ОК","НЕТ") -> ОК | J90: =IF(ISNUMBER(SEARCH(J81,Skl_handling_req)),"ОК","НЕТ") -> ОК | K90: =IF(ISNUMBER(SEARCH(K81,Skl_handling_req)),"ОК","НЕТ") -> ОК | L90: =IF(ISNUMBER(SEARCH(L81,Skl_handling_req)),"ОК","НЕТ") -> ОК | ... Y90: =IF(ISNUMBER(SEARCH(Y81,Skl_handling_req)),"ОК","НЕТ") -> ОК
A91: chk_indoor | B91: Проверка допуска в помещения | D91: IF(AND(Skl_indoor_req=1,[indoor]=0),"НЕТ","ОК") | E91: =IF(AND(Skl_indoor_req=1,E82=0),"НЕТ","ОК") -> ОК | F91: =IF(AND(Skl_indoor_req=1,F82=0),"НЕТ","ОК") -> ОК | G91: =IF(AND(Skl_indoor_req=1,G82=0),"НЕТ","ОК") -> ОК | H91: =IF(AND(Skl_indoor_req=1,H82=0),"НЕТ","ОК") -> ОК | I91: =IF(AND(Skl_indoor_req=1,I82=0),"НЕТ","ОК") -> ОК | J91: =IF(AND(Skl_indoor_req=1,J82=0),"НЕТ","ОК") -> ОК | K91: =IF(AND(Skl_indoor_req=1,K82=0),"НЕТ","ОК") -> ОК | L91: =IF(AND(Skl_indoor_req=1,L82=0),"НЕТ","ОК") -> ОК | ... Y91: =IF(AND(Skl_indoor_req=1,Y82=0),"НЕТ","ОК") -> ОК
A92: chk_cap | B92: Проверка грузоподъёмности (неделимый груз: кап. ≥ масса единицы) | D92: IF(AND(Skl_divisible=0,[cap]<Skl_unit_mass),"НЕТ","ОК") | E92: =IF(AND(Skl_divisible=0,E76<Skl_unit_mass),"НЕТ","ОК") -> ОК | F92: =IF(AND(Skl_divisible=0,F76<Skl_unit_mass),"НЕТ","ОК") -> ОК | G92: =IF(AND(Skl_divisible=0,G76<Skl_unit_mass),"НЕТ","ОК") -> ОК | H92: =IF(AND(Skl_divisible=0,H76<Skl_unit_mass),"НЕТ","ОК") -> ОК | I92: =IF(AND(Skl_divisible=0,I76<Skl_unit_mass),"НЕТ","ОК") -> ОК | J92: =IF(AND(Skl_divisible=0,J76<Skl_unit_mass),"НЕТ","ОК") -> ОК | K92: =IF(AND(Skl_divisible=0,K76<Skl_unit_mass),"НЕТ","ОК") -> ОК | L92: =IF(AND(Skl_divisible=0,L76<Skl_unit_mass),"НЕТ","ОК") -> ОК | ... Y92: =IF(AND(Skl_divisible=0,Y76<Skl_unit_mass),"НЕТ","ОК") -> ОК
A93: chk_aisle | B93: Проверка проезда (ширина робота + запас ≤ мин. ширина прохода) | D93: IF([wid]/1000+Skl_clearance<=Skl_aisle,"ОК","НЕТ") | E93: =IF(E85/1000+Skl_clearance<=Skl_aisle,"ОК","НЕТ") -> ОК | F93: =IF(F85/1000+Skl_clearance<=Skl_aisle,"ОК","НЕТ") -> ОК | G93: =IF(G85/1000+Skl_clearance<=Skl_aisle,"ОК","НЕТ") -> ОК | H93: =IF(H85/1000+Skl_clearance<=Skl_aisle,"ОК","НЕТ") -> ОК | I93: =IF(I85/1000+Skl_clearance<=Skl_aisle,"ОК","НЕТ") -> ОК | J93: =IF(J85/1000+Skl_clearance<=Skl_aisle,"ОК","НЕТ") -> ОК | K93: =IF(K85/1000+Skl_clearance<=Skl_aisle,"ОК","НЕТ") -> ОК | L93: =IF(L85/1000+Skl_clearance<=Skl_aisle,"ОК","НЕТ") -> ОК | ... Y93: =IF(Y85/1000+Skl_clearance<=Skl_aisle,"ОК","НЕТ") -> ОК
A94: chk_env | B94: Проверка условий эксплуатации (улица / мин. температура) | D94: IF(Skl_outdoor_req=1,IF(AND([outdoor]=1,[tmin]<=Skl_temp_min),"ОК","НЕТ"),"ОК") | E94: =IF(Skl_outdoor_req=1,IF(AND(E87=1,E86<=Skl_temp_min),"ОК","НЕТ"),"ОК") -> ОК | F94: =IF(Skl_outdoor_req=1,IF(AND(F87=1,F86<=Skl_temp_min),"ОК","НЕТ"),"ОК") -> ОК | G94: =IF(Skl_outdoor_req=1,IF(AND(G87=1,G86<=Skl_temp_min),"ОК","НЕТ"),"ОК") -> ОК | H94: =IF(Skl_outdoor_req=1,IF(AND(H87=1,H86<=Skl_temp_min),"ОК","НЕТ"),"ОК") -> ОК | I94: =IF(Skl_outdoor_req=1,IF(AND(I87=1,I86<=Skl_temp_min),"ОК","НЕТ"),"ОК") -> ОК | J94: =IF(Skl_outdoor_req=1,IF(AND(J87=1,J86<=Skl_temp_min),"ОК","НЕТ"),"ОК") -> ОК | K94: =IF(Skl_outdoor_req=1,IF(AND(K87=1,K86<=Skl_temp_min),"ОК","НЕТ"),"ОК") -> ОК | L94: =IF(Skl_outdoor_req=1,IF(AND(L87=1,L86<=Skl_temp_min),"ОК","НЕТ"),"ОК") -> ОК | ... Y94: =IF(Skl_outdoor_req=1,IF(AND(Y87=1,Y86<=Skl_temp_min),"ОК","НЕТ"),"ОК") -> ОК
A95: feasible | B95: Решение применимо (1/0) | C95: 1/0 | D95: IF(AND([chk_task]="ОК",[chk_handling]="ОК",[chk_indoor]="ОК",[chk_cap]="ОК",[chk_aisle]="ОК",[chk_env]="ОК"),1,0) | E95: =IF(AND(E89="ОК",E90="ОК",E91="ОК",E92="ОК",E93="ОК",E94="ОК"),1,0) -> 1 | F95: =IF(AND(F89="ОК",F90="ОК",F91="ОК",F92="ОК",F93="ОК",F94="ОК"),1,0) -> 1 | G95: =IF(AND(G89="ОК",G90="ОК",G91="ОК",G92="ОК",G93="ОК",G94="ОК"),1,0) -> 1 | H95: =IF(AND(H89="ОК",H90="ОК",H91="ОК",H92="ОК",H93="ОК",H94="ОК"),1,0) -> 1 | I95: =IF(AND(I89="ОК",I90="ОК",I91="ОК",I92="ОК",I93="ОК",I94="ОК"),1,0) -> 1 | J95: =IF(AND(J89="ОК",J90="ОК",J91="ОК",J92="ОК",J93="ОК",J94="ОК"),1,0) -> 1 | K95: =IF(AND(K89="ОК",K90="ОК",K91="ОК",K92="ОК",K93="ОК",K94="ОК"),1,0) -> 1 | L95: =IF(AND(L89="ОК",L90="ОК",L91="ОК",L92="ОК",L93="ОК",L94="ОК"),1,0) -> 1 | ... Y95: =IF(AND(Y89="ОК",Y90="ОК",Y91="ОК",Y92="ОК",Y93="ОК",Y94="ОК"),1,0) -> 1
A96: feas_text | B96: Причина включения / исключения | D96: IF([feasible]=1,"Применимо: все ключевые ограничения выполнены","Не применимо: "&IF([chk_task]="НЕТ","класс задачи; ","")&IF([chk_handling]="НЕТ","способ обработки груза; ","")&IF([chk_indoor]="НЕТ","не допущен в помещения; ","")&IF([chk_cap]="НЕТ","грузоподъёмность ниже массы единицы груза; ","")&IF([chk_aisle]="НЕТ","габариты не проходят по ширине прохода; ","")&IF([chk_env]="НЕТ","не сертифицирован для условий эксплуатации; ","")) | E96: =IF(E95=1,"Применимо: все ключевые ограничения выполнены","Не применимо: "&IF(E89="НЕТ","класс задачи; ","")&IF(E90="НЕТ","способ обработки груза; ","")&IF(E91="НЕТ","не допущен в помещения; ","")&IF(E92="НЕТ","грузоподъёмность ниже массы единицы груза; ","")&IF(E93="НЕТ","габариты не проходят по ширине прохода; ","")&IF(E94="НЕТ","не сертифицирован для условий эксплуатации; ","")) -> Применимо: все ключевые ограничения выполнены | F96: =IF(F95=1,"Применимо: все ключевые ограничения выполнены","Не применимо: "&IF(F89="НЕТ","класс задачи; ","")&IF(F90="НЕТ","способ обработки груза; ","")&IF(F91="НЕТ","не допущен в помещения; ","")&IF(F92="НЕТ","грузоподъёмность ниже массы единицы груза; ","")&IF(F93="НЕТ","габариты не проходят по ширине прохода; ","")&IF(F94="НЕТ","не сертифицирован для условий эксплуатации; ","")) -> Применимо: все ключевые ограничения выполнены | G96: =IF(G95=1,"Применимо: все ключевые ограничения выполнены","Не применимо: "&IF(G89="НЕТ","класс задачи; ","")&IF(G90="НЕТ","способ обработки груза; ","")&IF(G91="НЕТ","не допущен в помещения; ","")&IF(G92="НЕТ","грузоподъёмность ниже массы единицы груза; ","")&IF(G93="НЕТ","габариты не проходят по ширине прохода; ","")&IF(G94="НЕТ","не сертифицирован для условий эксплуатации; ","")) -> Применимо: все ключевые ограничения выполнены | H96: =IF(H95=1,"Применимо: все ключевые ограничения выполнены","Не применимо: "&IF(H89="НЕТ","класс задачи; ","")&IF(H90="НЕТ","способ обработки груза; ","")&IF(H91="НЕТ","не допущен в помещения; ","")&IF(H92="НЕТ","грузоподъёмность ниже массы единицы груза; ","")&IF(H93="НЕТ","габариты не проходят по ширине прохода; ","")&IF(H94="НЕТ","не сертифицирован для условий эксплуатации; ","")) -> Применимо: все ключевые ограничения выполнены | I96: =IF(I95=1,"Применимо: все ключевые ограничения выполнены","Не применимо: "&IF(I89="НЕТ","класс задачи; ","")&IF(I90="НЕТ","способ обработки груза; ","")&IF(I91="НЕТ","не допущен в помещения; ","")&IF(I92="НЕТ","грузоподъёмность ниже массы единицы груза; ","")&IF(I93="НЕТ","габариты не проходят по ширине прохода; ","")&IF(I94="НЕТ","не сертифицирован для условий эксплуатации; ","")) -> Применимо: все ключевые ограничения выполнены | J96: =IF(J95=1,"Применимо: все ключевые ограничения выполнены","Не применимо: "&IF(J89="НЕТ","класс задачи; ","")&IF(J90="НЕТ","способ обработки груза; ","")&IF(J91="НЕТ","не допущен в помещения; ","")&IF(J92="НЕТ","грузоподъёмность ниже массы единицы груза; ","")&IF(J93="НЕТ","габариты не проходят по ширине прохода; ","")&IF(J94="НЕТ","не сертифицирован для условий эксплуатации; ","")) -> Применимо: все ключевые ограничения выполнены | K96: =IF(K95=1,"Применимо: все ключевые ограничения выполнены","Не применимо: "&IF(K89="НЕТ","класс задачи; ","")&IF(K90="НЕТ","способ обработки груза; ","")&IF(K91="НЕТ","не допущен в помещения; ","")&IF(K92="НЕТ","грузоподъёмность ниже массы единицы груза; ","")&IF(K93="НЕТ","габариты не проходят по ширине прохода; ","")&IF(K94="НЕТ","не сертифицирован для условий эксплуатации; ","")) -> Применимо: все ключевые ограничения выполнены | L96: =IF(L95=1,"Применимо: все ключевые ограничения выполнены","Не применимо: "&IF(L89="НЕТ","класс задачи; ","")&IF(L90="НЕТ","способ обработки груза; ","")&IF(L91="НЕТ","не допущен в помещения; ","")&IF(L92="НЕТ","грузоподъёмность ниже массы единицы груза; ","")&IF(L93="НЕТ","габариты не проходят по ширине прохода; ","")&IF(L94="НЕТ","не сертифицирован для условий эксплуатации; ","")) -> Применимо: все ключевые ограничения выполнены | ... Y96: =IF(Y95=1,"Применимо: все ключевые ограничения выполнены","Не применимо: "&IF(Y89="НЕТ","класс задачи; ","")&IF(Y90="НЕТ","способ обработки груза; ","")&IF(Y91="НЕТ","не допущен в помещения; ","")&IF(Y92="НЕТ","грузоподъёмность ниже массы единицы груза; ","")&IF(Y93="НЕТ","габариты не проходят по ширине прохода; ","")&IF(Y94="НЕТ","не сертифицирован для условий эксплуатации; ","")) -> Применимо: все ключевые ограничения выполнены
B97: 3.3 Потребность в операциях (ТЗ п.3.5.2: пиковая потребность)
A98: ops_day | B98: Объём операций процесса в сутки (с учётом k_объём) | C98: оп./сут | D98: Skl_ops_day*66 | E98: =Skl_ops_day*E$66 -> 2000 | F98: =Skl_ops_day*F$66 -> 2000 | G98: =Skl_ops_day*G$66 -> 2000 | H98: =Skl_ops_day*H$66 -> 1600 | I98: =Skl_ops_day*I$66 -> 2400 | J98: =Skl_ops_day*J$66 -> 2000 | K98: =Skl_ops_day*K$66 -> 2000 | L98: =Skl_ops_day*L$66 -> 2000 | ... Y98: =Skl_ops_day*Y$66 -> 2000
A99: ops_auto | B99: Из них автоматизируемых (× доля автоматизируемых операций) | C99: оп./сут | D99: [ops_day]*Skl_auto_share | E99: =E98*Skl_auto_share -> 2000 | F99: =F98*Skl_auto_share -> 2000 | G99: =G98*Skl_auto_share -> 2000 | H99: =H98*Skl_auto_share -> 1600 | I99: =I98*Skl_auto_share -> 2400 | J99: =J98*Skl_auto_share -> 2000 | K99: =K98*Skl_auto_share -> 2000 | L99: =L98*Skl_auto_share -> 2000 | ... Y99: =Y98*Skl_auto_share -> 2000
A100: trips_per_op | B100: Рейсов робота на 1 операцию (делимый груз: округление вверх массы/грузоподъёмность) | C100: рейсов | D100: IF(Skl_divisible=1,ROUNDUP(Skl_unit_mass/MAX([cap],1),0),1) | E100: =IF(Skl_divisible=1,ROUNDUP(Skl_unit_mass/MAX(E76,1),0),1) -> 1 | F100: =IF(Skl_divisible=1,ROUNDUP(Skl_unit_mass/MAX(F76,1),0),1) -> 1 | G100: =IF(Skl_divisible=1,ROUNDUP(Skl_unit_mass/MAX(G76,1),0),1) -> 1 | H100: =IF(Skl_divisible=1,ROUNDUP(Skl_unit_mass/MAX(H76,1),0),1) -> 1 | I100: =IF(Skl_divisible=1,ROUNDUP(Skl_unit_mass/MAX(I76,1),0),1) -> 1 | J100: =IF(Skl_divisible=1,ROUNDUP(Skl_unit_mass/MAX(J76,1),0),1) -> 1 | K100: =IF(Skl_divisible=1,ROUNDUP(Skl_unit_mass/MAX(K76,1),0),1) -> 1 | L100: =IF(Skl_divisible=1,ROUNDUP(Skl_unit_mass/MAX(L76,1),0),1) -> 1 | ... Y100: =IF(Skl_divisible=1,ROUNDUP(Skl_unit_mass/MAX(Y76,1),0),1) -> 1
A101: hours_day | B101: Продолжительность работы процесса в сутки | C101: ч | D101: Skl_hours_day | E101: =Skl_hours_day -> 22 | F101: =Skl_hours_day -> 22 | G101: =Skl_hours_day -> 22 | H101: =Skl_hours_day -> 22 | I101: =Skl_hours_day -> 22 | J101: =Skl_hours_day -> 22 | K101: =Skl_hours_day -> 22 | L101: =Skl_hours_day -> 22 | ... Y101: =Skl_hours_day -> 22
A102: avg_h | B102: Среднечасовая потребность | C102: оп./ч | D102: [ops_auto]/[hours_day] | E102: =E99/E101 -> 90.909091 | F102: =F99/F101 -> 90.909091 | G102: =G99/G101 -> 90.909091 | H102: =H99/H101 -> 72.727273 | I102: =I99/I101 -> 109.09091 | J102: =J99/J101 -> 90.909091 | K102: =K99/K101 -> 90.909091 | L102: =L99/L101 -> 90.909091 | ... Y102: =Y99/Y101 -> 90.909091
A103: peak_h | B103: Пиковая потребность (автоматизируемая) | C103: оп./ч | D103: Skl_peak_ops_h*66*Skl_auto_share | E103: =Skl_peak_ops_h*E$66*Skl_auto_share -> 136.36364 | F103: =Skl_peak_ops_h*F$66*Skl_auto_share -> 136.36364 | G103: =Skl_peak_ops_h*G$66*Skl_auto_share -> 136.36364 | H103: =Skl_peak_ops_h*H$66*Skl_auto_share -> 109.09091 | I103: =Skl_peak_ops_h*I$66*Skl_auto_share -> 163.63636 | J103: =Skl_peak_ops_h*J$66*Skl_auto_share -> 136.36364 | K103: =Skl_peak_ops_h*K$66*Skl_auto_share -> 136.36364 | L103: =Skl_peak_ops_h*L$66*Skl_auto_share -> 136.36364 | ... Y103: =Skl_peak_ops_h*Y$66*Skl_auto_share -> 136.36364
A104: peak_trips | B104: Пиковая потребность в рейсах робота | C104: рейсов/ч | D104: [peak_h]*[trips_per_op] | E104: =E103*E100 -> 136.36364 | F104: =F103*F100 -> 136.36364 | G104: =G103*G100 -> 136.36364 | H104: =H103*H100 -> 109.09091 | I104: =I103*I100 -> 163.63636 | J104: =J103*J100 -> 136.36364 | K104: =K103*K100 -> 136.36364 | L104: =L103*L100 -> 136.36364 | ... Y104: =Y103*Y100 -> 136.36364
...

Sheet Аэропорт
A1: ОБЪЕКТ: АЭРОПОРТ — процесс: перевозка багажа перрон ↔ терминал (RAMP)
A2: Синие ячейки — ввод; жёлтая заливка — допущения команды; чёрные — формулы. Результаты помечены зелёной заливкой.
A4: БЛОК 1. ПАРАМЕТРЫ ОБЪЕКТА (демо-датасет организатора, лист «Аэропорт»)
A5: Код | B5: Параметр | C5: Ед. изм. | D5: Значение | E5: Min | F5: Max | G5: Источник / обоснование | H5: Тип
A6: Aer_S_terminal | B6: Суммарная площадь терминала(ов) | C6: м² | D6: 85000 | E6: 8000 | F6: 500000 | G6: Датасет, лист «Аэропорт» | H6: датасет
A7: Aer_S_apron | B7: Площадь перрона и технических зон | C7: м² | D7: 100000 | E7: 10000 | F7: 800000 | G7: Датасет, лист «Аэропорт» | H7: датасет
A8: Aer_gates | B8: Количество выходов на посадку | C8: шт. | D8: 20 | E8: 8 | F8: 50 | G8: Датасет, лист «Аэропорт» | H8: датасет
A9: Aer_flights_day | B9: Среднесуточное количество рейсов (взлёт+посадка) | C9: рейсов/сут | D9: 280 | E9: 30 | F9: 1200 | G9: Датасет, лист «Аэропорт» | H9: датасет
A10: Aer_flights_peak_h | B10: Пиковое количество рейсов в час | C10: рейсов/ч | D10: 32 | E10: 4 | F10: 120 | G10: Датасет, лист «Аэропорт» | H10: датасет
A11: Aer_bags_day | B11: Объём перемещения багажа | C11: ед./сут | D11: 35000 | E11: 3000 | F11: 300000 | G11: Датасет, лист «Аэропорт» | H11: датасет
A12: Aer_bag_mass | B12: Средняя масса единицы багажа | C12: кг | D12: 18 | E12: 10 | F12: 35 | G12: Датасет, лист «Аэропорт» | H12: датасет
A13: Aer_ramp_staff | B13: Численность персонала наземного обслуживания (рамп) | C13: чел. | D13: 320 | E13: 50 | F13: 2000 | G13: Датасет, лист «Аэропорт» | H13: датасет
A14: Aer_sal_ramp | B14: Средняя з/п сотрудника наземного обслуживания (gross) | C14: руб./мес. | D14: 100000 | E14: 70000 | F14: 150000 | G14: Датасет, лист «Аэропорт» | H14: датасет
A15: Aer_turnover_ds | B15: Годовая текучесть персонала | C15: доля | D15: 0.35 | E15: 0.15 | F15: 0.6 | G15: Датасет, лист «Аэропорт» | H15: датасет
A16: Aer_temp_min_ds | B16: Температура в неотапливаемых зонах (перрон, зима) | C16: °C | D16: -25 | E16: -40 | F16: 0 | G16: Датасет, лист «Аэропорт» | H16: датасет
A17: Aer_noise | B17: Ограничение по уровню шума | C17: дБА | D17: 70 | E17: 55 | F17: 80 | G17: Датасет, лист «Аэропорт» | H17: датасет
... A20: Aer_horizon | B20: Горизонт расчёта окупаемости | C20: лет | D20: 7 | E20: 5 | F20: 15 | G20: Датасет, лист «Аэропорт» | H20: датасет
A22: БЛОК 2. ПАРАМЕТРЫ ПРОЦЕССА И ДОПУЩЕНИЯ КОМАНДЫ
A23: Код | B23: Параметр | C23: Ед. изм. | D23: Значение | E23: Min | F23: Max | G23: Источник / обоснование | H23: Тип
A24: Aer_shifts | B24: Смен в сутки (круглосуточная работа аэропорта) | C24: смен | D24: 3 | E24: 2 | F24: 3 | G24: Допущение команды: режим 24/7, 3 смены по 8 ч | H24: допущение
A25: Aer_shift_h | B25: Продолжительность смены | C25: ч | D25: 8 | E25: 8 | F25: 12 | G25: Допущение команды | H25: допущение
A26: Aer_hours_day | B26: Часов работы процесса в сутки | C26: ч | D26: =Aer_shifts*Aer_shift_h -> 24 | G26: Формула | H26: формула
A27: Aer_ops_day | B27: Объём операций = рейсов × 2 (доставка багажа на борт + вывоз на выдачу) | C27: оп./сут | D27: =Aer_flights_day*2 -> 560 | G27: Формула из датасета | H27: формула
A28: Aer_peak_ops_h | B28: Пиковая интенсивность = пиковых рейсов/ч × 2 | C28: оп./ч | D28: =Aer_flights_peak_h*2 -> 64 | G28: Формула из датасета (пик задан напрямую, пиковый коэффициент не применяется) | H28: формула
A29: Aer_auto_share | B29: Доля автоматизируемых операций | C29: доля | D29: 0.9 | E29: 0.5 | F29: 1 | G29: Допущение: 10% рейсов (нестандартные стоянки, спецрейсы) остаются ручными | H29: допущение
A30: Aer_unit_mass | B30: Масса багажа одного рейса = багаж/сут ÷ рейсов/сут × масса единицы | C30: кг | D30: =Aer_bags_day/Aer_flights_day*Aer_bag_mass -> 2250 | G30: Формула из датасета | H30: формула
A31: Aer_divisible | B31: Груз делимый (1): багаж рейса можно везти несколькими рейсами робота | C31: 1/0 | D31: 1 | E31: 0 | F31: 1 | G31: Допущение | H31: допущение
A32: Aer_L | B32: Средняя длина маршрута (сортировка багажа ↔ стоянка ВС) = 2 × √(площадь перрона) | C32: м | D32: =2*SQRT(Aer_S_apron) -> 632.45553 | G32: Допущение команды (проверяется на схеме перрона) | H32: формула
A33: Aer_speed_cap | B33: Ограничение скорости на перроне | C33: м/с | D33: 4.17 | E33: 2 | F33: 7 | G33: Допущение: 15 км/ч — типовой лимит для перронной техники | H33: допущение
A34: Aer_lift_share | B34: Доля рейсов через лифт | C34: доля | D34: 0 | E34: 0 | F34: 1 | G34: Не применяется (перрон) | H34: датасет
A35: Aer_lift_time | B35: Время лифта | C35: с | D35: 0 | E35: 0 | F35: 300 | G35: Не применяется | H35: датасет
A36: Aer_aisle | B36: Минимальная ширина проезда (служебные проезды перрона) | C36: м | D36: 4 | E36: 3 | F36: 8 | G36: Допущение команды | H36: допущение
A37: Aer_clearance | B37: Запас по ширине проезда | C37: м | D37: 0.6 | E37: 0.3 | F37: 1 | G37: Допущение команды | H37: допущение
A38: Aer_outdoor_req | B38: Требуется уличная эксплуатация (1/0) | C38: 1/0 | D38: 1 | E38: 0 | F38: 1 | G38: Перрон — открытая зона (датасет: ограничения по погоде и допускам) | H38: датасет
A39: Aer_task_class | B39: Класс задачи процесса | D39: транспорт | G39: транспорт (рейсы) / уборка (площадь) | H39: датасет
A40: Aer_handling_req | B40: Допустимые способы обработки груза (через ;) | D40: буксировка;кузов | G40: Допущение команды: багажные тележки — буксировка; контейнеры — кузов | H40: допущение
A41: Aer_indoor_req | B41: Работа внутри помещений (1/0) | C41: 1/0 | D41: 0 | E41: 0 | F41: 1 | G41: Уличные гибриды/грузовики не допускаются в помещения | H41: датасет
A42: Aer_repl_forks | B42: Коэф. замещения труда: вилы | C42: доля | D42: 0.8 | E42: 0.5 | F42: 0.9 | G42: Допущение команды: полный цикл без станций; остаются высотные/нестандартные операции | H42: допущение
A43: Aer_repl_platform | B43: Коэф. замещения труда: платформа (подъём/станции передачи) | C43: доля | D43: 0.6 | E43: 0.4 | F43: 0.9 | G43: Допущение команды | H43: допущение
A44: Aer_repl_tow | B44: Коэф. замещения труда: буксировка | C44: доля | D44: 0.8 | E44: 0.5 | F44: 0.9 | G44: Допущение команды: сцепка тележек остаётся ручной | H44: допущение
A45: Aer_repl_body | B45: Коэф. замещения труда: кузов | C45: доля | D45: 0.8 | E45: 0.3 | F45: 0.9 | G45: Допущение команды: ручная погрузка/выгрузка кузова | H45: допущение
A46: Aer_temp_min | B46: Минимальная температура эксплуатации | C46: °C | D46: =Aer_temp_min_ds -> -25 | G46: Датасет | H46: формула
A47: Aer_driver_share | B47: Доля водителей багажных тягачей в персонале рампа | C47: доля | D47: 0.2 | E47: 0.1 | F47: 0.35 | G47: Допущение команды (в датасете нет разбивки персонала рампа по функциям) | H47: допущение
A48: Aer_fte_target | B48: Целевые FTE = персонал рампа × доля водителей × доля автоматизируемых операций | C48: FTE | D48: =Aer_ramp_staff*Aer_driver_share*Aer_auto_share -> 57.6 | G48: Формула | H48: формула
A49: Aer_labor_target | B49: Годовой ФОТ целевых FTE (с начислениями) | C49: руб./год | D49: =Aer_fte_target*Aer_sal_ramp*12*N_fot -> 89994240 | G49: Формула | H49: формула
A50: Aer_base_labor | B50: Годовой ФОТ всего целевого персонала процесса (водители тягачей) | C50: руб./год | D50: =Aer_ramp_staff*Aer_driver_share*Aer_sal_ramp*12*N_fot -> 99993600 | G50: Формула | H50: формула
A51: Aer_sal_target | B51: Средний оклад целевого персонала | C51: руб./мес. | D51: =Aer_sal_ramp -> 100000 | G51: Датасет | H51: формула
A52: Aer_turnover | B52: Годовая текучесть целевого персонала | C52: доля | D52: =Aer_turnover_ds -> 0.35 | G52: Датасет | H52: формула
A53: Aer_loss_k | B53: Коэффициент потерь рабочего времени | C53: доля | D53: =N_loss_k_default -> 0.25 | G53: Нормативы (по умолчанию 25%) | H53: формула
A54: Aer_fleet_per_shift | B54: Операторы флота (диспетчер) на смену | C54: чел./смену | D54: 1 | E54: 0 | F54: 3 | G54: Допущение команды | H54: допущение
A55: Aer_fleet_sal | B55: Оклад оператора флота | C55: руб./мес. | D55: =Aer_sal_ramp -> 100000 | G55: Допущение: на уровне персонала рампа | H55: формула
A56: Aer_site_pct | B56: Подготовка объекта (разметка airside, СКУД, связь), % от стоимости парка | C56: доля | D56: 0.1 | E56: 0.05 | F56: 0.25 | G56: Допущение команды (сертификация airside, интеграция со СКУД OSDP) | H56: допущение
A57: Aer_integration | B57: Интеграция с AODB/FIDS и системой обработки багажа | C57: руб. | D57: 3000000 | E57: 1000000 | F57: 10000000 | G57: Допущение команды | H57: допущение
A58: Aer_consum_per_robot | B58: Расходные материалы на робота в год | C58: руб./год | D58: 0 | E58: 0 | F58: 300000 | G58: Учтены в сервисе | H58: допущение
A59: Aer_other_effects | B59: Иные измеримые эффекты (сокращение задержек рейсов, повреждений багажа) | C59: руб./год | D59: 0 | E59: 0 | G59: Ввод пользователя; консервативно 0 | H59: допущение
A61: БЛОК 3. РАСЧЁТНЫЙ ДВИЖОК (каждая колонка = один прогон: решение × модель приобретения × вариант чувствительности)
B62: Сценарий | E62: Покупка A | F62: Покупка A | G62: Покупка A | H62: Покупка A | I62: Покупка A | J62: Покупка A | K62: Покупка A | L62: RaaS A | M62: RaaS A | N62: RaaS A | O62: RaaS A | P62: RaaS A | Q62: RaaS A | R62: RaaS A | S62: Покупка B | T62: Покупка B | U62: Покупка B | V62: Покупка B | W62: Покупка B | X62: Покупка B | Y62: Покупка B
B63: Код решения (см. лист Каталог) | E63: COGNITIVE-TUG | F63: COGNITIVE-TUG | G63: COGNITIVE-TUG | H63: COGNITIVE-TUG | I63: COGNITIVE-TUG | J63: COGNITIVE-TUG | K63: COGNITIVE-TUG | L63: COGNITIVE-TUG | M63: COGNITIVE-TUG | N63: COGNITIVE-TUG | O63: COGNITIVE-TUG | P63: COGNITIVE-TUG | Q63: COGNITIVE-TUG | R63: COGNITIVE-TUG | S63: EVOCARGO-N1 | T63: EVOCARGO-N1 | U63: EVOCARGO-N1 | V63: EVOCARGO-N1 | W63: EVOCARGO-N1 | X63: EVOCARGO-N1 | Y63: EVOCARGO-N1
B64: Модель приобретения | E64: Покупка | F64: Покупка | G64: Покупка | H64: Покупка | I64: Покупка | J64: Покупка | K64: Покупка | L64: RaaS | M64: RaaS | N64: RaaS | O64: RaaS | P64: RaaS | Q64: RaaS | R64: RaaS | S64: Покупка | T64: Покупка | U64: Покупка | V64: Покупка | W64: Покупка | X64: Покупка | Y64: Покупка
B65: k_цена оборудования | E65: 1 | F65: =1-N_sens -> 0.8 | G65: =1+N_sens -> 1.2 | H65: 1 | I65: 1 | J65: 1 | K65: 1 | L65: 1 | M65: =1-N_sens -> 0.8 | N65: =1+N_sens -> 1.2 | O65: 1 | P65: 1 | Q65: 1 | R65: 1 | S65: 1 | T65: =1-N_sens -> 0.8 | U65: =1+N_sens -> 1.2 | V65: 1 | W65: 1 | X65: 1 | Y65: 1
B66: k_объём операций | E66: 1 | F66: 1 | G66: 1 | H66: =1-N_sens -> 0.8 | I66: =1+N_sens -> 1.2 | J66: 1 | K66: 1 | L66: 1 | M66: 1 | N66: 1 | O66: =1-N_sens -> 0.8 | P66: =1+N_sens -> 1.2 | Q66: 1 | R66: 1 | S66: 1 | T66: 1 | U66: 1 | V66: =1-N_sens -> 0.8 | W66: =1+N_sens -> 1.2 | X66: 1 | Y66: 1
B67: k_стоимость труда | E67: 1 | F67: 1 | G67: 1 | H67: 1 | I67: 1 | J67: =1-N_sens -> 0.8 | K67: =1+N_sens -> 1.2 | L67: 1 | M67: 1 | N67: 1 | O67: 1 | P67: 1 | Q67: =1-N_sens -> 0.8 | R67: =1+N_sens -> 1.2 | S67: 1 | T67: 1 | U67: 1 | V67: 1 | W67: 1 | X67: =1-N_sens -> 0.8 | Y67: =1+N_sens -> 1.2
B68: Вариант расчёта | E68: База | F68: Оборуд. − | G68: Оборуд. + | H68: Объём − | I68: Объём + | J68: Труд − | K68: Труд + | L68: База | M68: Оборуд. − | N68: Оборуд. + | O68: Объём − | P68: Объём + | Q68: Труд − | R68: Труд + | S68: База | T68: Оборуд. − | U68: Оборуд. + | V68: Объём − | W68: Объём + | X68: Труд − | Y68: Труд +
B70: 3.1 Параметры решения (подтягиваются из листа «Каталог» по коду)
A71: sol_name | B71: Наименование решения | D71: INDEX(Cat_name,MATCH(63,Cat_code,0)) | E71: =INDEX(Cat_name,MATCH(E$63,Cat_code,0)) -> Беспилотный тягач (Cognitive Pilot) | F71: =INDEX(Cat_name,MATCH(F$63,Cat_code,0)) -> Беспилотный тягач (Cognitive Pilot) | G71: =INDEX(Cat_name,MATCH(G$63,Cat_code,0)) -> Беспилотный тягач (Cognitive Pilot) | H71: =INDEX(Cat_name,MATCH(H$63,Cat_code,0)) -> Беспилотный тягач (Cognitive Pilot) | I71: =INDEX(Cat_name,MATCH(I$63,Cat_code,0)) -> Беспилотный тягач (Cognitive Pilot) | J71: =INDEX(Cat_name,MATCH(J$63,Cat_code,0)) -> Беспилотный тягач (Cognitive Pilot) | K71: =INDEX(Cat_name,MATCH(K$63,Cat_code,0)) -> Беспилотный тягач (Cognitive Pilot) | L71: =INDEX(Cat_name,MATCH(L$63,Cat_code,0)) -> Беспилотный тягач (Cognitive Pilot) | ... Y71: =INDEX(Cat_name,MATCH(Y$63,Cat_code,0)) -> EVOCARGO N1 (беспилотный электрогрузовик)
A72: sol_status | B72: Статус в каталоге | D72: INDEX(Cat_status,MATCH(63,Cat_code,0)) | E72: =INDEX(Cat_status,MATCH(E$63,Cat_code,0)) -> operation | F72: =INDEX(Cat_status,MATCH(F$63,Cat_code,0)) -> operation | G72: =INDEX(Cat_status,MATCH(G$63,Cat_code,0)) -> operation | H72: =INDEX(Cat_status,MATCH(H$63,Cat_code,0)) -> operation | I72: =INDEX(Cat_status,MATCH(I$63,Cat_code,0)) -> operation | J72: =INDEX(Cat_status,MATCH(J$63,Cat_code,0)) -> operation | K72: =INDEX(Cat_status,MATCH(K$63,Cat_code,0)) -> operation | L72: =INDEX(Cat_status,MATCH(L$63,Cat_code,0)) -> operation | ... Y72: =INDEX(Cat_status,MATCH(Y$63,Cat_code,0)) -> operation
A73: sol_conf | B73: ТТХ подтверждены | D73: INDEX(Cat_conf,MATCH(63,Cat_code,0)) | E73: =INDEX(Cat_conf,MATCH(E$63,Cat_code,0)) -> Да | F73: =INDEX(Cat_conf,MATCH(F$63,Cat_code,0)) -> Да | G73: =INDEX(Cat_conf,MATCH(G$63,Cat_code,0)) -> Да | H73: =INDEX(Cat_conf,MATCH(H$63,Cat_code,0)) -> Да | I73: =INDEX(Cat_conf,MATCH(I$63,Cat_code,0)) -> Да | J73: =INDEX(Cat_conf,MATCH(J$63,Cat_code,0)) -> Да | K73: =INDEX(Cat_conf,MATCH(K$63,Cat_code,0)) -> Да | L73: =INDEX(Cat_conf,MATCH(L$63,Cat_code,0)) -> Да | ... Y73: =INDEX(Cat_conf,MATCH(Y$63,Cat_code,0)) -> Да
A74: price0 | B74: Цена изделия по каталогу (с НДС) | C74: руб. | D74: INDEX(Cat_price,MATCH(63,Cat_code,0)) | E74: =INDEX(Cat_price,MATCH(E$63,Cat_code,0)) -> 4000000 | F74: =INDEX(Cat_price,MATCH(F$63,Cat_code,0)) -> 4000000 | G74: =INDEX(Cat_price,MATCH(G$63,Cat_code,0)) -> 4000000 | H74: =INDEX(Cat_price,MATCH(H$63,Cat_code,0)) -> 4000000 | I74: =INDEX(Cat_price,MATCH(I$63,Cat_code,0)) -> 4000000 | J74: =INDEX(Cat_price,MATCH(J$63,Cat_code,0)) -> 4000000 | K74: =INDEX(Cat_price,MATCH(K$63,Cat_code,0)) -> 4000000 | L74: =INDEX(Cat_price,MATCH(L$63,Cat_code,0)) -> 4000000 | ... Y74: =INDEX(Cat_price,MATCH(Y$63,Cat_code,0)) -> 6000000
A75: price | B75: Цена в расчёте (с учётом k_цена) | C75: руб. | D75: [price0]*65 | E75: =E74*E$65 -> 4000000 | F75: =F74*F$65 -> 3200000 | G75: =G74*G$65 -> 4800000 | H75: =H74*H$65 -> 4000000 | I75: =I74*I$65 -> 4000000 | J75: =J74*J$65 -> 4000000 | K75: =K74*K$65 -> 4000000 | L75: =L74*L$65 -> 4000000 | ... Y75: =Y74*Y$65 -> 6000000
A76: cap | B76: Грузоподъёмность | C76: кг | D76: INDEX(Cat_cap,MATCH(63,Cat_code,0)) | E76: =INDEX(Cat_cap,MATCH(E$63,Cat_code,0)) -> 3000 | F76: =INDEX(Cat_cap,MATCH(F$63,Cat_code,0)) -> 3000 | G76: =INDEX(Cat_cap,MATCH(G$63,Cat_code,0)) -> 3000 | H76: =INDEX(Cat_cap,MATCH(H$63,Cat_code,0)) -> 3000 | I76: =INDEX(Cat_cap,MATCH(I$63,Cat_code,0)) -> 3000 | J76: =INDEX(Cat_cap,MATCH(J$63,Cat_code,0)) -> 3000 | K76: =INDEX(Cat_cap,MATCH(K$63,Cat_code,0)) -> 3000 | L76: =INDEX(Cat_cap,MATCH(L$63,Cat_code,0)) -> 3000 | ... Y76: =INDEX(Cat_cap,MATCH(Y$63,Cat_code,0)) -> 2000
A77: vmax | B77: Максимальная скорость | C77: м/с | D77: INDEX(Cat_vmax,MATCH(63,Cat_code,0)) | E77: =INDEX(Cat_vmax,MATCH(E$63,Cat_code,0)) -> 4.17 | F77: =INDEX(Cat_vmax,MATCH(F$63,Cat_code,0)) -> 4.17 | G77: =INDEX(Cat_vmax,MATCH(G$63,Cat_code,0)) -> 4.17 | H77: =INDEX(Cat_vmax,MATCH(H$63,Cat_code,0)) -> 4.17 | I77: =INDEX(Cat_vmax,MATCH(I$63,Cat_code,0)) -> 4.17 | J77: =INDEX(Cat_vmax,MATCH(J$63,Cat_code,0)) -> 4.17 | K77: =INDEX(Cat_vmax,MATCH(K$63,Cat_code,0)) -> 4.17 | L77: =INDEX(Cat_vmax,MATCH(L$63,Cat_code,0)) -> 4.17 | ... Y77: =INDEX(Cat_vmax,MATCH(Y$63,Cat_code,0)) -> 5.56
A78: tload | B78: Время загрузки (сцепки/подхвата) | C78: с | D78: INDEX(Cat_tload,MATCH(63,Cat_code,0)) | E78: =INDEX(Cat_tload,MATCH(E$63,Cat_code,0)) -> 180 | F78: =INDEX(Cat_tload,MATCH(F$63,Cat_code,0)) -> 180 | G78: =INDEX(Cat_tload,MATCH(G$63,Cat_code,0)) -> 180 | H78: =INDEX(Cat_tload,MATCH(H$63,Cat_code,0)) -> 180 | I78: =INDEX(Cat_tload,MATCH(I$63,Cat_code,0)) -> 180 | J78: =INDEX(Cat_tload,MATCH(J$63,Cat_code,0)) -> 180 | K78: =INDEX(Cat_tload,MATCH(K$63,Cat_code,0)) -> 180 | L78: =INDEX(Cat_tload,MATCH(L$63,Cat_code,0)) -> 180 | ... Y78: =INDEX(Cat_tload,MATCH(Y$63,Cat_code,0)) -> 240
A79: tunload | B79: Время разгрузки | C79: с | D79: INDEX(Cat_tunload,MATCH(63,Cat_code,0)) | E79: =INDEX(Cat_tunload,MATCH(E$63,Cat_code,0)) -> 180 | F79: =INDEX(Cat_tunload,MATCH(F$63,Cat_code,0)) -> 180 | G79: =INDEX(Cat_tunload,MATCH(G$63,Cat_code,0)) -> 180 | H79: =INDEX(Cat_tunload,MATCH(H$63,Cat_code,0)) -> 180 | I79: =INDEX(Cat_tunload,MATCH(I$63,Cat_code,0)) -> 180 | J79: =INDEX(Cat_tunload,MATCH(J$63,Cat_code,0)) -> 180 | K79: =INDEX(Cat_tunload,MATCH(K$63,Cat_code,0)) -> 180 | L79: =INDEX(Cat_tunload,MATCH(L$63,Cat_code,0)) -> 180 | ... Y79: =INDEX(Cat_tunload,MATCH(Y$63,Cat_code,0)) -> 240
A80: power | B80: Средняя потребляемая мощность | C80: кВт | D80: INDEX(Cat_power,MATCH(63,Cat_code,0)) | E80: =INDEX(Cat_power,MATCH(E$63,Cat_code,0)) -> 6 | F80: =INDEX(Cat_power,MATCH(F$63,Cat_code,0)) -> 6 | G80: =INDEX(Cat_power,MATCH(G$63,Cat_code,0)) -> 6 | H80: =INDEX(Cat_power,MATCH(H$63,Cat_code,0)) -> 6 | I80: =INDEX(Cat_power,MATCH(I$63,Cat_code,0)) -> 6 | J80: =INDEX(Cat_power,MATCH(J$63,Cat_code,0)) -> 6 | K80: =INDEX(Cat_power,MATCH(K$63,Cat_code,0)) -> 6 | L80: =INDEX(Cat_power,MATCH(L$63,Cat_code,0)) -> 6 | ... Y80: =INDEX(Cat_power,MATCH(Y$63,Cat_code,0)) -> 6
A81: handling | B81: Способ обработки груза | D81: INDEX(Cat_handling,MATCH(63,Cat_code,0)) | E81: =INDEX(Cat_handling,MATCH(E$63,Cat_code,0)) -> буксировка | F81: =INDEX(Cat_handling,MATCH(F$63,Cat_code,0)) -> буксировка | G81: =INDEX(Cat_handling,MATCH(G$63,Cat_code,0)) -> буксировка | H81: =INDEX(Cat_handling,MATCH(H$63,Cat_code,0)) -> буксировка | I81: =INDEX(Cat_handling,MATCH(I$63,Cat_code,0)) -> буксировка | J81: =INDEX(Cat_handling,MATCH(J$63,Cat_code,0)) -> буксировка | K81: =INDEX(Cat_handling,MATCH(K$63,Cat_code,0)) -> буксировка | L81: =INDEX(Cat_handling,MATCH(L$63,Cat_code,0)) -> буксировка | ... Y81: =INDEX(Cat_handling,MATCH(Y$63,Cat_code,0)) -> кузов
A82: indoor | B82: Допуск в помещения | C82: 1/0 | D82: INDEX(Cat_indoor,MATCH(63,Cat_code,0)) | E82: =INDEX(Cat_indoor,MATCH(E$63,Cat_code,0)) -> 0 | F82: =INDEX(Cat_indoor,MATCH(F$63,Cat_code,0)) -> 0 | G82: =INDEX(Cat_indoor,MATCH(G$63,Cat_code,0)) -> 0 | H82: =INDEX(Cat_indoor,MATCH(H$63,Cat_code,0)) -> 0 | I82: =INDEX(Cat_indoor,MATCH(I$63,Cat_code,0)) -> 0 | J82: =INDEX(Cat_indoor,MATCH(J$63,Cat_code,0)) -> 0 | K82: =INDEX(Cat_indoor,MATCH(K$63,Cat_code,0)) -> 0 | L82: =INDEX(Cat_indoor,MATCH(L$63,Cat_code,0)) -> 0 | ... Y82: =INDEX(Cat_indoor,MATCH(Y$63,Cat_code,0)) -> 0
A83: task | B83: Класс задачи решения | D83: INDEX(Cat_task,MATCH(63,Cat_code,0)) | E83: =INDEX(Cat_task,MATCH(E$63,Cat_code,0)) -> транспорт | F83: =INDEX(Cat_task,MATCH(F$63,Cat_code,0)) -> транспорт | G83: =INDEX(Cat_task,MATCH(G$63,Cat_code,0)) -> транспорт | H83: =INDEX(Cat_task,MATCH(H$63,Cat_code,0)) -> транспорт | I83: =INDEX(Cat_task,MATCH(I$63,Cat_code,0)) -> транспорт | J83: =INDEX(Cat_task,MATCH(J$63,Cat_code,0)) -> транспорт | K83: =INDEX(Cat_task,MATCH(K$63,Cat_code,0)) -> транспорт | L83: =INDEX(Cat_task,MATCH(L$63,Cat_code,0)) -> транспорт | ... Y83: =INDEX(Cat_task,MATCH(Y$63,Cat_code,0)) -> транспорт
A84: repl | B84: Коэффициент замещения труда = по паре «задача × способ обработки» (блок 2) | C84: доля | D84: IF([handling]="вилы",Aer_repl_forks,IF([handling]="платформа",Aer_repl_platform,IF([handling]="буксировка",Aer_repl_tow,IF([handling]="кузов",Aer_repl_body,0)))) | E84: =IF(E81="вилы",Aer_repl_forks,IF(E81="платформа",Aer_repl_platform,IF(E81="буксировка",Aer_repl_tow,IF(E81="кузов",Aer_repl_body,0)))) -> 0.8 | F84: =IF(F81="вилы",Aer_repl_forks,IF(F81="платформа",Aer_repl_platform,IF(F81="буксировка",Aer_repl_tow,IF(F81="кузов",Aer_repl_body,0)))) -> 0.8 | G84: =IF(G81="вилы",Aer_repl_forks,IF(G81="платформа",Aer_repl_platform,IF(G81="буксировка",Aer_repl_tow,IF(G81="кузов",Aer_repl_body,0)))) -> 0.8 | H84: =IF(H81="вилы",Aer_repl_forks,IF(H81="платформа",Aer_repl_platform,IF(H81="буксировка",Aer_repl_tow,IF(H81="кузов",Aer_repl_body,0)))) -> 0.8 | I84: =IF(I81="вилы",Aer_repl_forks,IF(I81="платформа",Aer_repl_platform,IF(I81="буксировка",Aer_repl_tow,IF(I81="кузов",Aer_repl_body,0)))) -> 0.8 | J84: =IF(J81="вилы",Aer_repl_forks,IF(J81="платформа",Aer_repl_platform,IF(J81="буксировка",Aer_repl_tow,IF(J81="кузов",Aer_repl_body,0)))) -> 0.8 | K84: =IF(K81="вилы",Aer_repl_forks,IF(K81="платформа",Aer_repl_platform,IF(K81="буксировка",Aer_repl_tow,IF(K81="кузов",Aer_repl_body,0)))) -> 0.8 | L84: =IF(L81="вилы",Aer_repl_forks,IF(L81="платформа",Aer_repl_platform,IF(L81="буксировка",Aer_repl_tow,IF(L81="кузов",Aer_repl_body,0)))) -> 0.8 | ... Y84: =IF(Y81="вилы",Aer_repl_forks,IF(Y81="платформа",Aer_repl_platform,IF(Y81="буксировка",Aer_repl_tow,IF(Y81="кузов",Aer_repl_body,0)))) -> 0.8
A85: wid | B85: Ширина робота | C85: мм | D85: INDEX(Cat_wid,MATCH(63,Cat_code,0)) | E85: =INDEX(Cat_wid,MATCH(E$63,Cat_code,0)) -> 1400 | F85: =INDEX(Cat_wid,MATCH(F$63,Cat_code,0)) -> 1400 | G85: =INDEX(Cat_wid,MATCH(G$63,Cat_code,0)) -> 1400 | H85: =INDEX(Cat_wid,MATCH(H$63,Cat_code,0)) -> 1400 | I85: =INDEX(Cat_wid,MATCH(I$63,Cat_code,0)) -> 1400 | J85: =INDEX(Cat_wid,MATCH(J$63,Cat_code,0)) -> 1400 | K85: =INDEX(Cat_wid,MATCH(K$63,Cat_code,0)) -> 1400 | L85: =INDEX(Cat_wid,MATCH(L$63,Cat_code,0)) -> 1400 | ... Y85: =INDEX(Cat_wid,MATCH(Y$63,Cat_code,0)) -> 1800
A86: tmin | B86: Допустимая минимальная температура | C86: °C | D86: INDEX(Cat_tmin,MATCH(63,Cat_code,0)) | E86: =INDEX(Cat_tmin,MATCH(E$63,Cat_code,0)) -> -40 | F86: =INDEX(Cat_tmin,MATCH(F$63,Cat_code,0)) -> -40 | G86: =INDEX(Cat_tmin,MATCH(G$63,Cat_code,0)) -> -40 | H86: =INDEX(Cat_tmin,MATCH(H$63,Cat_code,0)) -> -40 | I86: =INDEX(Cat_tmin,MATCH(I$63,Cat_code,0)) -> -40 | J86: =INDEX(Cat_tmin,MATCH(J$63,Cat_code,0)) -> -40 | K86: =INDEX(Cat_tmin,MATCH(K$63,Cat_code,0)) -> -40 | L86: =INDEX(Cat_tmin,MATCH(L$63,Cat_code,0)) -> -40 | ... Y86: =INDEX(Cat_tmin,MATCH(Y$63,Cat_code,0)) -> -40
A87: outdoor | B87: Уличная эксплуатация | C87: 1/0 | D87: INDEX(Cat_outdoor,MATCH(63,Cat_code,0)) | E87: =INDEX(Cat_outdoor,MATCH(E$63,Cat_code,0)) -> 1 | F87: =INDEX(Cat_outdoor,MATCH(F$63,Cat_code,0)) -> 1 | G87: =INDEX(Cat_outdoor,MATCH(G$63,Cat_code,0)) -> 1 | H87: =INDEX(Cat_outdoor,MATCH(H$63,Cat_code,0)) -> 1 | I87: =INDEX(Cat_outdoor,MATCH(I$63,Cat_code,0)) -> 1 | J87: =INDEX(Cat_outdoor,MATCH(J$63,Cat_code,0)) -> 1 | K87: =INDEX(Cat_outdoor,MATCH(K$63,Cat_code,0)) -> 1 | L87: =INDEX(Cat_outdoor,MATCH(L$63,Cat_code,0)) -> 1 | ... Y87: =INDEX(Cat_outdoor,MATCH(Y$63,Cat_code,0)) -> 1
B88: 3.2 Проверка применимости (ТЗ п.3.4.3: ключевое ограничение → решение не рекомендуется)
A89: chk_task | B89: Проверка класса задачи (транспорт / уборка) | D89: IF([task]=Aer_task_class,"ОК","НЕТ") | E89: =IF(E83=Aer_task_class,"ОК","НЕТ") -> ОК | F89: =IF(F83=Aer_task_class,"ОК","НЕТ") -> ОК | G89: =IF(G83=Aer_task_class,"ОК","НЕТ") -> ОК | H89: =IF(H83=Aer_task_class,"ОК","НЕТ") -> ОК | I89: =IF(I83=Aer_task_class,"ОК","НЕТ") -> ОК | J89: =IF(J83=Aer_task_class,"ОК","НЕТ") -> ОК | K89: =IF(K83=Aer_task_class,"ОК","НЕТ") -> ОК | L89: =IF(L83=Aer_task_class,"ОК","НЕТ") -> ОК | ... Y89: =IF(Y83=Aer_task_class,"ОК","НЕТ") -> ОК
A90: chk_handling | B90: Проверка способа обработки груза (в списке допустимых для задачи) | D90: IF(ISNUMBER(SEARCH([handling],Aer_handling_req)),"ОК","НЕТ") | E90: =IF(ISNUMBER(SEARCH(E81,Aer_handling_req)),"ОК","НЕТ") -> ОК | F90: =IF(ISNUMBER(SEARCH(F81,Aer_handling_req)),"ОК","НЕТ") -> ОК | G90: =IF(ISNUMBER(SEARCH(G81,Aer_handling_req)),"ОК","НЕТ") -> ОК | H90: =IF(ISNUMBER(SEARCH(H81,Aer_handling_req)),"ОК","НЕТ") -> ОК | I90: =IF(ISNUMBER(SEARCH(I81,Aer_handling_req)),"ОК","НЕТ") -> ОК | J90: =IF(ISNUMBER(SEARCH(J81,Aer_handling_req)),"ОК","НЕТ") -> ОК | K90: =IF(ISNUMBER(SEARCH(K81,Aer_handling_req)),"ОК","НЕТ") -> ОК | L90: =IF(ISNUMBER(SEARCH(L81,Aer_handling_req)),"ОК","НЕТ") -> ОК | ... Y90: =IF(ISNUMBER(SEARCH(Y81,Aer_handling_req)),"ОК","НЕТ") -> ОК
A91: chk_indoor | B91: Проверка допуска в помещения | D91: IF(AND(Aer_indoor_req=1,[indoor]=0),"НЕТ","ОК") | E91: =IF(AND(Aer_indoor_req=1,E82=0),"НЕТ","ОК") -> ОК | F91: =IF(AND(Aer_indoor_req=1,F82=0),"НЕТ","ОК") -> ОК | G91: =IF(AND(Aer_indoor_req=1,G82=0),"НЕТ","ОК") -> ОК | H91: =IF(AND(Aer_indoor_req=1,H82=0),"НЕТ","ОК") -> ОК | I91: =IF(AND(Aer_indoor_req=1,I82=0),"НЕТ","ОК") -> ОК | J91: =IF(AND(Aer_indoor_req=1,J82=0),"НЕТ","ОК") -> ОК | K91: =IF(AND(Aer_indoor_req=1,K82=0),"НЕТ","ОК") -> ОК | L91: =IF(AND(Aer_indoor_req=1,L82=0),"НЕТ","ОК") -> ОК | ... Y91: =IF(AND(Aer_indoor_req=1,Y82=0),"НЕТ","ОК") -> ОК
A92: chk_cap | B92: Проверка грузоподъёмности (неделимый груз: кап. ≥ масса единицы) | D92: IF(AND(Aer_divisible=0,[cap]<Aer_unit_mass),"НЕТ","ОК") | E92: =IF(AND(Aer_divisible=0,E76<Aer_unit_mass),"НЕТ","ОК") -> ОК | F92: =IF(AND(Aer_divisible=0,F76<Aer_unit_mass),"НЕТ","ОК") -> ОК | G92: =IF(AND(Aer_divisible=0,G76<Aer_unit_mass),"НЕТ","ОК") -> ОК | H92: =IF(AND(Aer_divisible=0,H76<Aer_unit_mass),"НЕТ","ОК") -> ОК | I92: =IF(AND(Aer_divisible=0,I76<Aer_unit_mass),"НЕТ","ОК") -> ОК | J92: =IF(AND(Aer_divisible=0,J76<Aer_unit_mass),"НЕТ","ОК") -> ОК | K92: =IF(AND(Aer_divisible=0,K76<Aer_unit_mass),"НЕТ","ОК") -> ОК | L92: =IF(AND(Aer_divisible=0,L76<Aer_unit_mass),"НЕТ","ОК") -> ОК | ... Y92: =IF(AND(Aer_divisible=0,Y76<Aer_unit_mass),"НЕТ","ОК") -> ОК
A93: chk_aisle | B93: Проверка проезда (ширина робота + запас ≤ мин. ширина прохода) | D93: IF([wid]/1000+Aer_clearance<=Aer_aisle,"ОК","НЕТ") | E93: =IF(E85/1000+Aer_clearance<=Aer_aisle,"ОК","НЕТ") -> ОК | F93: =IF(F85/1000+Aer_clearance<=Aer_aisle,"ОК","НЕТ") -> ОК | G93: =IF(G85/1000+Aer_clearance<=Aer_aisle,"ОК","НЕТ") -> ОК | H93: =IF(H85/1000+Aer_clearance<=Aer_aisle,"ОК","НЕТ") -> ОК | I93: =IF(I85/1000+Aer_clearance<=Aer_aisle,"ОК","НЕТ") -> ОК | J93: =IF(J85/1000+Aer_clearance<=Aer_aisle,"ОК","НЕТ") -> ОК | K93: =IF(K85/1000+Aer_clearance<=Aer_aisle,"ОК","НЕТ") -> ОК | L93: =IF(L85/1000+Aer_clearance<=Aer_aisle,"ОК","НЕТ") -> ОК | ... Y93: =IF(Y85/1000+Aer_clearance<=Aer_aisle,"ОК","НЕТ") -> ОК
A94: chk_env | B94: Проверка условий эксплуатации (улица / мин. температура) | D94: IF(Aer_outdoor_req=1,IF(AND([outdoor]=1,[tmin]<=Aer_temp_min),"ОК","НЕТ"),"ОК") | E94: =IF(Aer_outdoor_req=1,IF(AND(E87=1,E86<=Aer_temp_min),"ОК","НЕТ"),"ОК") -> ОК | F94: =IF(Aer_outdoor_req=1,IF(AND(F87=1,F86<=Aer_temp_min),"ОК","НЕТ"),"ОК") -> ОК | G94: =IF(Aer_outdoor_req=1,IF(AND(G87=1,G86<=Aer_temp_min),"ОК","НЕТ"),"ОК") -> ОК | H94: =IF(Aer_outdoor_req=1,IF(AND(H87=1,H86<=Aer_temp_min),"ОК","НЕТ"),"ОК") -> ОК | I94: =IF(Aer_outdoor_req=1,IF(AND(I87=1,I86<=Aer_temp_min),"ОК","НЕТ"),"ОК") -> ОК | J94: =IF(Aer_outdoor_req=1,IF(AND(J87=1,J86<=Aer_temp_min),"ОК","НЕТ"),"ОК") -> ОК | K94: =IF(Aer_outdoor_req=1,IF(AND(K87=1,K86<=Aer_temp_min),"ОК","НЕТ"),"ОК") -> ОК | L94: =IF(Aer_outdoor_req=1,IF(AND(L87=1,L86<=Aer_temp_min),"ОК","НЕТ"),"ОК") -> ОК | ... Y94: =IF(Aer_outdoor_req=1,IF(AND(Y87=1,Y86<=Aer_temp_min),"ОК","НЕТ"),"ОК") -> ОК
A95: feasible | B95: Решение применимо (1/0) | C95: 1/0 | D95: IF(AND([chk_task]="ОК",[chk_handling]="ОК",[chk_indoor]="ОК",[chk_cap]="ОК",[chk_aisle]="ОК",[chk_env]="ОК"),1,0) | E95: =IF(AND(E89="ОК",E90="ОК",E91="ОК",E92="ОК",E93="ОК",E94="ОК"),1,0) -> 1 | F95: =IF(AND(F89="ОК",F90="ОК",F91="ОК",F92="ОК",F93="ОК",F94="ОК"),1,0) -> 1 | G95: =IF(AND(G89="ОК",G90="ОК",G91="ОК",G92="ОК",G93="ОК",G94="ОК"),1,0) -> 1 | H95: =IF(AND(H89="ОК",H90="ОК",H91="ОК",H92="ОК",H93="ОК",H94="ОК"),1,0) -> 1 | I95: =IF(AND(I89="ОК",I90="ОК",I91="ОК",I92="ОК",I93="ОК",I94="ОК"),1,0) -> 1 | J95: =IF(AND(J89="ОК",J90="ОК",J91="ОК",J92="ОК",J93="ОК",J94="ОК"),1,0) -> 1 | K95: =IF(AND(K89="ОК",K90="ОК",K91="ОК",K92="ОК",K93="ОК",K94="ОК"),1,0) -> 1 | L95: =IF(AND(L89="ОК",L90="ОК",L91="ОК",L92="ОК",L93="ОК",L94="ОК"),1,0) -> 1 | ... Y95: =IF(AND(Y89="ОК",Y90="ОК",Y91="ОК",Y92="ОК",Y93="ОК",Y94="ОК"),1,0) -> 1
A96: feas_text | B96: Причина включения / исключения | D96: IF([feasible]=1,"Применимо: все ключевые ограничения выполнены","Не применимо: "&IF([chk_task]="НЕТ","класс задачи; ","")&IF([chk_handling]="НЕТ","способ обработки груза; ","")&IF([chk_indoor]="НЕТ","не допущен в помещения; ","")&IF([chk_cap]="НЕТ","грузоподъёмность ниже массы единицы груза; ","")&IF([chk_aisle]="НЕТ","габариты не проходят по ширине прохода; ","")&IF([chk_env]="НЕТ","не сертифицирован для условий эксплуатации; ","")) | E96: =IF(E95=1,"Применимо: все ключевые ограничения выполнены","Не применимо: "&IF(E89="НЕТ","класс задачи; ","")&IF(E90="НЕТ","способ обработки груза; ","")&IF(E91="НЕТ","не допущен в помещения; ","")&IF(E92="НЕТ","грузоподъёмность ниже массы единицы груза; ","")&IF(E93="НЕТ","габариты не проходят по ширине прохода; ","")&IF(E94="НЕТ","не сертифицирован для условий эксплуатации; ","")) -> Применимо: все ключевые ограничения выполнены | F96: =IF(F95=1,"Применимо: все ключевые ограничения выполнены","Не применимо: "&IF(F89="НЕТ","класс задачи; ","")&IF(F90="НЕТ","способ обработки груза; ","")&IF(F91="НЕТ","не допущен в помещения; ","")&IF(F92="НЕТ","грузоподъёмность ниже массы единицы груза; ","")&IF(F93="НЕТ","габариты не проходят по ширине прохода; ","")&IF(F94="НЕТ","не сертифицирован для условий эксплуатации; ","")) -> Применимо: все ключевые ограничения выполнены | G96: =IF(G95=1,"Применимо: все ключевые ограничения выполнены","Не применимо: "&IF(G89="НЕТ","класс задачи; ","")&IF(G90="НЕТ","способ обработки груза; ","")&IF(G91="НЕТ","не допущен в помещения; ","")&IF(G92="НЕТ","грузоподъёмность ниже массы единицы груза; ","")&IF(G93="НЕТ","габариты не проходят по ширине прохода; ","")&IF(G94="НЕТ","не сертифицирован для условий эксплуатации; ","")) -> Применимо: все ключевые ограничения выполнены | H96: =IF(H95=1,"Применимо: все ключевые ограничения выполнены","Не применимо: "&IF(H89="НЕТ","класс задачи; ","")&IF(H90="НЕТ","способ обработки груза; ","")&IF(H91="НЕТ","не допущен в помещения; ","")&IF(H92="НЕТ","грузоподъёмность ниже массы единицы груза; ","")&IF(H93="НЕТ","габариты не проходят по ширине прохода; ","")&IF(H94="НЕТ","не сертифицирован для условий эксплуатации; ","")) -> Применимо: все ключевые ограничения выполнены | I96: =IF(I95=1,"Применимо: все ключевые ограничения выполнены","Не применимо: "&IF(I89="НЕТ","класс задачи; ","")&IF(I90="НЕТ","способ обработки груза; ","")&IF(I91="НЕТ","не допущен в помещения; ","")&IF(I92="НЕТ","грузоподъёмность ниже массы единицы груза; ","")&IF(I93="НЕТ","габариты не проходят по ширине прохода; ","")&IF(I94="НЕТ","не сертифицирован для условий эксплуатации; ","")) -> Применимо: все ключевые ограничения выполнены | J96: =IF(J95=1,"Применимо: все ключевые ограничения выполнены","Не применимо: "&IF(J89="НЕТ","класс задачи; ","")&IF(J90="НЕТ","способ обработки груза; ","")&IF(J91="НЕТ","не допущен в помещения; ","")&IF(J92="НЕТ","грузоподъёмность ниже массы единицы груза; ","")&IF(J93="НЕТ","габариты не проходят по ширине прохода; ","")&IF(J94="НЕТ","не сертифицирован для условий эксплуатации; ","")) -> Применимо: все ключевые ограничения выполнены | K96: =IF(K95=1,"Применимо: все ключевые ограничения выполнены","Не применимо: "&IF(K89="НЕТ","класс задачи; ","")&IF(K90="НЕТ","способ обработки груза; ","")&IF(K91="НЕТ","не допущен в помещения; ","")&IF(K92="НЕТ","грузоподъёмность ниже массы единицы груза; ","")&IF(K93="НЕТ","габариты не проходят по ширине прохода; ","")&IF(K94="НЕТ","не сертифицирован для условий эксплуатации; ","")) -> Применимо: все ключевые ограничения выполнены | L96: =IF(L95=1,"Применимо: все ключевые ограничения выполнены","Не применимо: "&IF(L89="НЕТ","класс задачи; ","")&IF(L90="НЕТ","способ обработки груза; ","")&IF(L91="НЕТ","не допущен в помещения; ","")&IF(L92="НЕТ","грузоподъёмность ниже массы единицы груза; ","")&IF(L93="НЕТ","габариты не проходят по ширине прохода; ","")&IF(L94="НЕТ","не сертифицирован для условий эксплуатации; ","")) -> Применимо: все ключевые ограничения выполнены | ... Y96: =IF(Y95=1,"Применимо: все ключевые ограничения выполнены","Не применимо: "&IF(Y89="НЕТ","класс задачи; ","")&IF(Y90="НЕТ","способ обработки груза; ","")&IF(Y91="НЕТ","не допущен в помещения; ","")&IF(Y92="НЕТ","грузоподъёмность ниже массы единицы груза; ","")&IF(Y93="НЕТ","габариты не проходят по ширине прохода; ","")&IF(Y94="НЕТ","не сертифицирован для условий эксплуатации; ","")) -> Применимо: все ключевые ограничения выполнены
B97: 3.3 Потребность в операциях (ТЗ п.3.5.2: пиковая потребность)
A98: ops_day | B98: Объём операций процесса в сутки (с учётом k_объём) | C98: оп./сут | D98: Aer_ops_day*66 | E98: =Aer_ops_day*E$66 -> 560 | F98: =Aer_ops_day*F$66 -> 560 | G98: =Aer_ops_day*G$66 -> 560 | H98: =Aer_ops_day*H$66 -> 448 | I98: =Aer_ops_day*I$66 -> 672 | J98: =Aer_ops_day*J$66 -> 560 | K98: =Aer_ops_day*K$66 -> 560 | L98: =Aer_ops_day*L$66 -> 560 | ... Y98: =Aer_ops_day*Y$66 -> 560
A99: ops_auto | B99: Из них автоматизируемых (× доля автоматизируемых операций) | C99: оп./сут | D99: [ops_day]*Aer_auto_share | E99: =E98*Aer_auto_share -> 504 | F99: =F98*Aer_auto_share -> 504 | G99: =G98*Aer_auto_share -> 504 | H99: =H98*Aer_auto_share -> 403.2 | I99: =I98*Aer_auto_share -> 604.8 | J99: =J98*Aer_auto_share -> 504 | K99: =K98*Aer_auto_share -> 504 | L99: =L98*Aer_auto_share -> 504 | ... Y99: =Y98*Aer_auto_share -> 504
A100: trips_per_op | B100: Рейсов робота на 1 операцию (делимый груз: округление вверх массы/грузоподъёмность) | C100: рейсов | D100: IF(Aer_divisible=1,ROUNDUP(Aer_unit_mass/MAX([cap],1),0),1) | E100: =IF(Aer_divisible=1,ROUNDUP(Aer_unit_mass/MAX(E76,1),0),1) -> 1 | F100: =IF(Aer_divisible=1,ROUNDUP(Aer_unit_mass/MAX(F76,1),0),1) -> 1 | G100: =IF(Aer_divisible=1,ROUNDUP(Aer_unit_mass/MAX(G76,1),0),1) -> 1 | H100: =IF(Aer_divisible=1,ROUNDUP(Aer_unit_mass/MAX(H76,1),0),1) -> 1 | I100: =IF(Aer_divisible=1,ROUNDUP(Aer_unit_mass/MAX(I76,1),0),1) -> 1 | J100: =IF(Aer_divisible=1,ROUNDUP(Aer_unit_mass/MAX(J76,1),0),1) -> 1 | K100: =IF(Aer_divisible=1,ROUNDUP(Aer_unit_mass/MAX(K76,1),0),1) -> 1 | L100: =IF(Aer_divisible=1,ROUNDUP(Aer_unit_mass/MAX(L76,1),0),1) -> 1 | ... Y100: =IF(Aer_divisible=1,ROUNDUP(Aer_unit_mass/MAX(Y76,1),0),1) -> 2
A101: hours_day | B101: Продолжительность работы процесса в сутки | C101: ч | D101: Aer_hours_day | E101: =Aer_hours_day -> 24 | F101: =Aer_hours_day -> 24 | G101: =Aer_hours_day -> 24 | H101: =Aer_hours_day -> 24 | I101: =Aer_hours_day -> 24 | J101: =Aer_hours_day -> 24 | K101: =Aer_hours_day -> 24 | L101: =Aer_hours_day -> 24 | ... Y101: =Aer_hours_day -> 24
A102: avg_h | B102: Среднечасовая потребность | C102: оп./ч | D102: [ops_auto]/[hours_day] | E102: =E99/E101 -> 21 | F102: =F99/F101 -> 21 | G102: =G99/G101 -> 21 | H102: =H99/H101 -> 16.8 | I102: =I99/I101 -> 25.2 | J102: =J99/J101 -> 21 | K102: =K99/K101 -> 21 | L102: =L99/L101 -> 21 | ... Y102: =Y99/Y101 -> 21
A103: peak_h | B103: Пиковая потребность (автоматизируемая) | C103: оп./ч | D103: Aer_peak_ops_h*66*Aer_auto_share | E103: =Aer_peak_ops_h*E$66*Aer_auto_share -> 57.6 | F103: =Aer_peak_ops_h*F$66*Aer_auto_share -> 57.6 | G103: =Aer_peak_ops_h*G$66*Aer_auto_share -> 57.6 | H103: =Aer_peak_ops_h*H$66*Aer_auto_share -> 46.08 | I103: =Aer_peak_ops_h*I$66*Aer_auto_share -> 69.12 | J103: =Aer_peak_ops_h*J$66*Aer_auto_share -> 57.6 | K103: =Aer_peak_ops_h*K$66*Aer_auto_share -> 57.6 | L103: =Aer_peak_ops_h*L$66*Aer_auto_share -> 57.6 | ... Y103: =Aer_peak_ops_h*Y$66*Aer_auto_share -> 57.6
A104: peak_trips | B104: Пиковая потребность в рейсах робота | C104: рейсов/ч | D104: [peak_h]*[trips_per_op] | E104: =E103*E100 -> 57.6 | F104: =F103*F100 -> 57.6 | G104: =G103*G100 -> 57.6 | H104: =H103*H100 -> 46.08 | I104: =I103*I100 -> 69.12 | J104: =J103*J100 -> 57.6 | K104: =K103*K100 -> 57.6 | L104: =L103*L100 -> 57.6 | ... Y104: =Y103*Y100 -> 115.2
B105: 3.4 Эффективная производительность робота и состав парка (ТЗ п.3.5.2: количество роботов)
A106: L | B106: Средняя длина маршрута (в одну сторону) | C106: м | D106: Aer_L | E106: =Aer_L -> 632.45553 | F106: =Aer_L -> 632.45553 | G106: =Aer_L -> 632.45553 | H106: =Aer_L -> 632.45553 | I106: =Aer_L -> 632.45553 | J106: =Aer_L -> 632.45553 | K106: =Aer_L -> 632.45553 | L106: =Aer_L -> 632.45553 | ... Y106: =Aer_L -> 632.45553
...

Sheet Медучреждение
A1: ОБЪЕКТ: МЕДУЧРЕЖДЕНИЕ — процесс: внутрибольничная транспортировка тележек (питание, бельё, отходы, расходники)
A2: Синие ячейки — ввод; жёлтая заливка — допущения команды; чёрные — формулы. Результаты помечены зелёной заливкой.
A4: БЛОК 1. ПАРАМЕТРЫ ОБЪЕКТА (демо-датасет организатора, лист «Медучреждение»)
A5: Код | B5: Параметр | C5: Ед. изм. | D5: Значение | E5: Min | F5: Max | G5: Источник / обоснование | H5: Тип
A6: Med_S_total | B6: Общая площадь здания(й) | C6: м² | D6: 45000 | E6: 3000 | F6: 200000 | G6: Датасет, лист «Медучреждение» | H6: датасет
A7: Med_floors | B7: Количество этажей (основной корпус) | C7: шт. | D7: 9 | E7: 3 | F7: 20 | G7: Датасет, лист «Медучреждение» | H7: датасет
A8: Med_lifts | B8: Количество лифтов (грузовых/медицинских) | C8: шт. | D8: 4 | E8: 1 | F8: 12 | G8: Датасет, лист «Медучреждение» | H8: датасет
A9: Med_beds | B9: Количество коек | C9: коек | D9: 650 | E9: 50 | F9: 2500 | G9: Датасет, лист «Медучреждение» | H9: датасет
A10: Med_feedings | B10: Количество кормлений в сутки | C10: раз/сут | D10: 3 | E10: 3 | F10: 5 | G10: Датасет, лист «Медучреждение» | H10: датасет
A11: Med_food_points | B11: Количество точек раздачи питания (отделений) | C11: шт. | D11: 18 | E11: 4 | F11: 60 | G11: Датасет, лист «Медучреждение» | H11: датасет
A12: Med_L_food | B12: Среднее расстояние от пищеблока до отделения | C12: м | D12: 180 | E12: 30 | F12: 500 | G12: Датасет, лист «Медучреждение» | H12: датасет
A13: Med_cart_mass | B13: Средняя масса тележки с питанием (брутто) | C13: кг | D13: 120 | E13: 40 | F13: 250 | G13: Датасет, лист «Медучреждение» | H13: датасет
A14: Med_linen_points | B14: Количество точек сбора/выдачи белья | C14: шт. | D14: 18 | E14: 4 | F14: 60 | G14: Датасет, лист «Медучреждение» | H14: датасет
A15: Med_linen_freq | B15: Периодичность смены белья | C15: раз/сут | D15: 1.3 | E15: 1 | F15: 3 | G15: Датасет, лист «Медучреждение» | H15: датасет
A16: Med_linen_mass | B16: Средняя масса контейнера с бельём | C16: кг | D16: 55 | E16: 20 | F16: 120 | G16: Датасет, лист «Медучреждение» | H16: датасет
A17: Med_supplies_trips | B17: Объём доставки расходных материалов | C17: рейсов/сут | D17: 45 | E17: 10 | F17: 200 | G17: Датасет, лист «Медучреждение» | H17: датасет
... A30: Med_horizon | B30: Горизонт расчёта окупаемости | C30: лет | D30: 7 | E30: 5 | F30: 15 | G30: Датасет, лист «Медучреждение» | H30: датасет
A32: БЛОК 2. ПАРАМЕТРЫ ПРОЦЕССА И ДОПУЩЕНИЯ КОМАНДЫ
A33: Код | B33: Параметр | C33: Ед. изм. | D33: Значение | E33: Min | F33: Max | G33: Источник / обоснование | H33: Тип
A34: Med_shifts | B34: Смен в сутки (стационар 24/7) | C34: смен | D34: 3 | E34: 2 | F34: 3 | G34: Датасет: 3 смены медперсонала | H34: датасет
A35: Med_hours_day | B35: Часов логистической работы в сутки (окно 06:00–22:00) | C35: ч | D35: 16 | E35: 8 | F35: 24 | G35: Допущение команды: ночью доставки минимальны (шум ≤30 дБА в палатах) | H35: допущение
A36: Med_peak_k | B36: Пиковый коэффициент (пики 07–10 и 15–17 по датасету) | C36: коэф. | D36: 1.8 | E36: 1.2 | F36: 2.5 | G36: Допущение команды: два пиковых окна | H36: допущение
A37: Med_ops_food | B37: Рейсы питания = кормлений × отделений × 2 (доставка + возврат тележек) | C37: оп./сут | D37: =Med_feedings*Med_food_points*2 -> 108 | G37: Формула из датасета | H37: формула
A38: Med_ops_linen | B38: Рейсы белья = точек × периодичность × 2 (чистое + грязное) | C38: оп./сут | D38: =Med_linen_points*Med_linen_freq*2 -> 46.8 | G38: Формула из датасета | H38: формула
A39: Med_ops_waste | B39: Рейсы отходов = точек × периодичность × 2 (вывоз + возврат тары) | C39: оп./сут | D39: =Med_waste_points*Med_waste_freq*2 -> 80 | G39: Формула из датасета | H39: формула
A40: Med_ops_supplies | B40: Рейсы расходных материалов | C40: оп./сут | D40: =Med_supplies_trips -> 45 | G40: Датасет | H40: формула
A41: Med_ops_day | B41: Объём операций процесса = питание + бельё + отходы + расходники | C41: оп./сут | D41: =Med_ops_food+Med_ops_linen+Med_ops_waste+Med_ops_supplies -> 279.8 | G41: Формула | H41: формула
A42: Med_peak_ops_h | B42: Пиковая интенсивность = объём / часов × пиковый коэффициент | C42: оп./ч | D42: =Med_ops_day/Med_hours_day*Med_peak_k -> 31.4775 | G42: Формула | H42: формула
A43: Med_auto_share | B43: Доля автоматизируемых операций | C43: доля | D43: 0.9 | E43: 0.5 | F43: 1 | G43: Допущение: 10% маршрутов (реанимация, оперблок, режимные зоны) остаются ручными | H43: допущение
A44: Med_unit_mass | B44: Масса единицы груза = максимальная из тележек процесса | C44: кг | D44: =MAX(Med_cart_mass,Med_linen_mass) -> 120 | G44: Формула из датасета | H44: формула
A45: Med_divisible | B45: Груз делимый (0 — тележка неделима) | C45: 1/0 | D45: 0 | E45: 0 | F45: 1 | G45: Допущение | H45: допущение
A46: Med_L | B46: Средняя длина маршрута (пищеблок ↔ отделение) | C46: м | D46: =Med_L_food -> 180 | G46: Датасет | H46: формула
A47: Med_speed_cap | B47: Ограничение скорости в коридорах | C47: м/с | D47: 1 | E47: 0.5 | F47: 1.5 | G47: Допущение: безопасность пациентов, разминовка с каталками | H47: допущение
A48: Med_lift_share | B48: Доля рейсов с использованием лифта | C48: доля | D48: 0.8 | E48: 0 | F48: 1 | G48: Допущение: 9 этажей, пищеблок/прачечная на нижних этажах | H48: допущение
A49: Med_lift_time | B49: Ожидание + проезд лифта (в один проход) | C49: с | D49: 180 | E49: 60 | F49: 600 | G49: Допущение команды: 4 лифта на 9 этажей — типичное узкое место (датасет) | H49: допущение
A50: Med_aisle | B50: Минимальная ширина прохода | C50: м | D50: =Med_corridor -> 2.4 | G50: Датасет | H50: формула
A51: Med_clearance | B51: Запас по ширине (разминовка с каталкой) | C51: м | D51: 0.9 | E51: 0.5 | F51: 1.5 | G51: Допущение: каталка ~0.7 м + зазоры | H51: допущение
A52: Med_outdoor_req | B52: Требуется уличная эксплуатация | C52: 1/0 | D52: 0 | E52: 0 | F52: 1 | G52: Внутрибольничная логистика | H52: датасет
A53: Med_task_class | B53: Класс задачи процесса | D53: транспорт | G53: транспорт (рейсы) / уборка (площадь) | H53: датасет
A54: Med_handling_req | B54: Допустимые способы обработки груза (через ;) | D54: платформа;кузов | G54: Допущение команды: тележки подхватываются платформой напрямую (→ 0.8); кузов — мелкие грузы | H54: допущение
A55: Med_indoor_req | B55: Работа внутри помещений (1/0) | C55: 1/0 | D55: 1 | E55: 0 | F55: 1 | G55: Уличные гибриды/грузовики не допускаются в помещения | H55: датасет
A56: Med_repl_forks | B56: Коэф. замещения труда: вилы | C56: доля | D56: 0.8 | E56: 0.5 | F56: 0.9 | G56: Допущение команды: полный цикл без станций; остаются высотные/нестандартные операции | H56: допущение
A57: Med_repl_platform | B57: Коэф. замещения труда: платформа (подъём/станции передачи) | C57: доля | D57: 0.8 | E57: 0.4 | F57: 0.9 | G57: Допущение команды | H57: допущение
A58: Med_repl_tow | B58: Коэф. замещения труда: буксировка | C58: доля | D58: 0.8 | E58: 0.5 | F58: 0.9 | G58: Допущение команды: сцепка тележек остаётся ручной | H58: допущение
A59: Med_repl_body | B59: Коэф. замещения труда: кузов | C59: доля | D59: 0.5 | E59: 0.3 | F59: 0.9 | G59: Допущение команды: ручная погрузка/выгрузка кузова | H59: допущение
A60: Med_temp_min | B60: Минимальная температура | C60: °C | D60: 18 | E60: 0 | F60: 25 | G60: Отапливаемое здание | H60: датасет
A61: Med_share_orderly | B61: Доля времени санитаров/транспортировщиков на транспортировку тележек | C61: доля | D61: 0.5 | E61: 0.3 | F61: 0.8 | G61: Допущение команды | H61: допущение
A62: Med_share_kitchen | B62: Доля времени пищеблока на транспортную функцию | C62: доля | D62: 0.3 | E62: 0.1 | F62: 0.5 | G62: Датасет: «частичное замещение — только транспортная функция»; величина — допущение | H62: допущение
A63: Med_share_laundry | B63: Доля времени прачечной на транспорт белья | C63: доля | D63: 0.5 | E63: 0.3 | F63: 0.8 | G63: Допущение команды | H63: допущение
A64: Med_fte_target | B64: Целевые FTE = Σ (численность × доля транспортной функции) × доля автоматизируемых | C64: FTE | D64: =(Med_orderlies*Med_share_orderly+Med_kitchen*Med_share_kitchen+Med_laundry*Med_share_laundry)*Med_auto_share -> 44.91 | G64: Формула | H64: формула
A65: Med_labor_target | B65: Годовой ФОТ целевых FTE (с начислениями) | C65: руб./год | D65: =(Med_orderlies*Med_share_orderly*Med_sal_orderly+Med_kitchen*Med_share_kitchen*Med_sal_kitchen+Med_laundry*Med_share_laundry*Med_sal_orderly)*Med_auto_share*12*N_fot -> 38237709 | G65: Формула (з/п прачечной принята = санитара) | H65: формула
A66: Med_base_labor | B66: Годовой ФОТ персонала транспортной функции (база) | C66: руб./год | D66: =(Med_orderlies*Med_share_orderly*Med_sal_orderly+Med_kitchen*Med_share_kitchen*Med_sal_kitchen+Med_laundry*Med_share_laundry*Med_sal_orderly)*12*N_fot -> 42486343 | G66: Формула | H66: формула
A67: Med_sal_target | B67: Средний оклад целевого персонала | C67: руб./мес. | D67: =Med_sal_orderly -> 55000 | G67: Датасет | H67: формула
A68: Med_turnover | B68: Годовая текучесть | C68: доля | D68: =Med_turnover_ds -> 0.45 | G68: Датасет | H68: формула
A69: Med_loss_k | B69: Коэффициент потерь рабочего времени | C69: доля | D69: =N_loss_k_default -> 0.25 | G69: Нормативы | H69: формула
A70: Med_fleet_per_shift | B70: Операторы флота на смену | C70: чел./смену | D70: 1 | E70: 0 | F70: 3 | G70: Допущение команды | H70: допущение
A71: Med_fleet_sal | B71: Оклад оператора флота | C71: руб./мес. | D71: =Med_sal_orderly -> 55000 | G71: Допущение | H71: формула
A72: Med_site_pct | B72: Подготовка объекта (API лифтов, двери, СКУД, Wi-Fi), % от стоимости парка | C72: доля | D72: 0.15 | E72: 0.05 | F72: 0.3 | G72: Допущение: датасет — BMS лифтов «частично», без API лифтов AMR не работает между этажами | H72: допущение
A73: Med_integration | B73: Интеграция с МИС (ЕМИАС) и лифтовым оборудованием | C73: руб. | D73: 2500000 | E73: 500000 | F73: 8000000 | G73: Допущение команды | H73: допущение
A74: Med_consum_per_robot | B74: Дезинфекция робота (2 обработки/сут × 365 × стоимость обработки 120 руб.) | C74: руб./год | D74: =2*365*120 -> 87600 | G74: Датасет: обеззараживание обязательно для Б-маршрутов; стоимость обработки — допущение | H74: формула
A75: Med_other_effects | B75: Иные измеримые эффекты (соблюдение нормативов доставки, снижение ВБИ) | C75: руб./год | D75: 0 | E75: 0 | G75: Консервативно 0; ввод пользователя | H75: допущение
A77: БЛОК 3. РАСЧЁТНЫЙ ДВИЖОК (каждая колонка = один прогон: решение × модель приобретения × вариант чувствительности)
B78: Сценарий | E78: Покупка A | F78: Покупка A | G78: Покупка A | H78: Покупка A | I78: Покупка A | J78: Покупка A | K78: Покупка A | L78: RaaS A | M78: RaaS A | N78: RaaS A | O78: RaaS A | P78: RaaS A | Q78: RaaS A | R78: RaaS A | S78: Покупка B | T78: Покупка B | U78: Покупка B | V78: Покупка B | W78: Покупка B | X78: Покупка B | Y78: Покупка B
B79: Код решения (см. лист Каталог) | E79: RONAVI-M | F79: RONAVI-M | G79: RONAVI-M | H79: RONAVI-M | I79: RONAVI-M | J79: RONAVI-M | K79: RONAVI-M | L79: RONAVI-M | M79: RONAVI-M | N79: RONAVI-M | O79: RONAVI-M | P79: RONAVI-M | Q79: RONAVI-M | R79: RONAVI-M | S79: MOROS-AMR800 | T79: MOROS-AMR800 | U79: MOROS-AMR800 | V79: MOROS-AMR800 | W79: MOROS-AMR800 | X79: MOROS-AMR800 | Y79: MOROS-AMR800
B80: Модель приобретения | E80: Покупка | F80: Покупка | G80: Покупка | H80: Покупка | I80: Покупка | J80: Покупка | K80: Покупка | L80: RaaS | M80: RaaS | N80: RaaS | O80: RaaS | P80: RaaS | Q80: RaaS | R80: RaaS | S80: Покупка | T80: Покупка | U80: Покупка | V80: Покупка | W80: Покупка | X80: Покупка | Y80: Покупка
B81: k_цена оборудования | E81: 1 | F81: =1-N_sens -> 0.8 | G81: =1+N_sens -> 1.2 | H81: 1 | I81: 1 | J81: 1 | K81: 1 | L81: 1 | M81: =1-N_sens -> 0.8 | N81: =1+N_sens -> 1.2 | O81: 1 | P81: 1 | Q81: 1 | R81: 1 | S81: 1 | T81: =1-N_sens -> 0.8 | U81: =1+N_sens -> 1.2 | V81: 1 | W81: 1 | X81: 1 | Y81: 1
B82: k_объём операций | E82: 1 | F82: 1 | G82: 1 | H82: =1-N_sens -> 0.8 | I82: =1+N_sens -> 1.2 | J82: 1 | K82: 1 | L82: 1 | M82: 1 | N82: 1 | O82: =1-N_sens -> 0.8 | P82: =1+N_sens -> 1.2 | Q82: 1 | R82: 1 | S82: 1 | T82: 1 | U82: 1 | V82: =1-N_sens -> 0.8 | W82: =1+N_sens -> 1.2 | X82: 1 | Y82: 1
B83: k_стоимость труда | E83: 1 | F83: 1 | G83: 1 | H83: 1 | I83: 1 | J83: =1-N_sens -> 0.8 | K83: =1+N_sens -> 1.2 | L83: 1 | M83: 1 | N83: 1 | O83: 1 | P83: 1 | Q83: =1-N_sens -> 0.8 | R83: =1+N_sens -> 1.2 | S83: 1 | T83: 1 | U83: 1 | V83: 1 | W83: 1 | X83: =1-N_sens -> 0.8 | Y83: =1+N_sens -> 1.2
B84: Вариант расчёта | E84: База | F84: Оборуд. − | G84: Оборуд. + | H84: Объём − | I84: Объём + | J84: Труд − | K84: Труд + | L84: База | M84: Оборуд. − | N84: Оборуд. + | O84: Объём − | P84: Объём + | Q84: Труд − | R84: Труд + | S84: База | T84: Оборуд. − | U84: Оборуд. + | V84: Объём − | W84: Объём + | X84: Труд − | Y84: Труд +
B86: 3.1 Параметры решения (подтягиваются из листа «Каталог» по коду)
A87: sol_name | B87: Наименование решения | D87: INDEX(Cat_name,MATCH(79,Cat_code,0)) | E87: =INDEX(Cat_name,MATCH(E$79,Cat_code,0)) -> Ronavi M (AMR для стеллажей/тележек, до 1200 кг) | F87: =INDEX(Cat_name,MATCH(F$79,Cat_code,0)) -> Ronavi M (AMR для стеллажей/тележек, до 1200 кг) | G87: =INDEX(Cat_name,MATCH(G$79,Cat_code,0)) -> Ronavi M (AMR для стеллажей/тележек, до 1200 кг) | H87: =INDEX(Cat_name,MATCH(H$79,Cat_code,0)) -> Ronavi M (AMR для стеллажей/тележек, до 1200 кг) | I87: =INDEX(Cat_name,MATCH(I$79,Cat_code,0)) -> Ronavi M (AMR для стеллажей/тележек, до 1200 кг) | J87: =INDEX(Cat_name,MATCH(J$79,Cat_code,0)) -> Ronavi M (AMR для стеллажей/тележек, до 1200 кг) | K87: =INDEX(Cat_name,MATCH(K$79,Cat_code,0)) -> Ronavi M (AMR для стеллажей/тележек, до 1200 кг) | L87: =INDEX(Cat_name,MATCH(L$79,Cat_code,0)) -> Ronavi M (AMR для стеллажей/тележек, до 1200 кг) | ... Y87: =INDEX(Cat_name,MATCH(Y$79,Cat_code,0)) -> AMR 800 (Морос, до 800 кг)
A88: sol_status | B88: Статус в каталоге | D88: INDEX(Cat_status,MATCH(79,Cat_code,0)) | E88: =INDEX(Cat_status,MATCH(E$79,Cat_code,0)) -> piloting | F88: =INDEX(Cat_status,MATCH(F$79,Cat_code,0)) -> piloting | G88: =INDEX(Cat_status,MATCH(G$79,Cat_code,0)) -> piloting | H88: =INDEX(Cat_status,MATCH(H$79,Cat_code,0)) -> piloting | I88: =INDEX(Cat_status,MATCH(I$79,Cat_code,0)) -> piloting | J88: =INDEX(Cat_status,MATCH(J$79,Cat_code,0)) -> piloting | K88: =INDEX(Cat_status,MATCH(K$79,Cat_code,0)) -> piloting | L88: =INDEX(Cat_status,MATCH(L$79,Cat_code,0)) -> piloting | ... Y88: =INDEX(Cat_status,MATCH(Y$79,Cat_code,0)) -> operation
A89: sol_conf | B89: ТТХ подтверждены | D89: INDEX(Cat_conf,MATCH(79,Cat_code,0)) | E89: =INDEX(Cat_conf,MATCH(E$79,Cat_code,0)) -> Частично | F89: =INDEX(Cat_conf,MATCH(F$79,Cat_code,0)) -> Частично | G89: =INDEX(Cat_conf,MATCH(G$79,Cat_code,0)) -> Частично | H89: =INDEX(Cat_conf,MATCH(H$79,Cat_code,0)) -> Частично | I89: =INDEX(Cat_conf,MATCH(I$79,Cat_code,0)) -> Частично | J89: =INDEX(Cat_conf,MATCH(J$79,Cat_code,0)) -> Частично | K89: =INDEX(Cat_conf,MATCH(K$79,Cat_code,0)) -> Частично | L89: =INDEX(Cat_conf,MATCH(L$79,Cat_code,0)) -> Частично | ... Y89: =INDEX(Cat_conf,MATCH(Y$79,Cat_code,0)) -> Частично
A90: price0 | B90: Цена изделия по каталогу (с НДС) | C90: руб. | D90: INDEX(Cat_price,MATCH(79,Cat_code,0)) | E90: =INDEX(Cat_price,MATCH(E$79,Cat_code,0)) -> 2400000 | F90: =INDEX(Cat_price,MATCH(F$79,Cat_code,0)) -> 2400000 | G90: =INDEX(Cat_price,MATCH(G$79,Cat_code,0)) -> 2400000 | H90: =INDEX(Cat_price,MATCH(H$79,Cat_code,0)) -> 2400000 | I90: =INDEX(Cat_price,MATCH(I$79,Cat_code,0)) -> 2400000 | J90: =INDEX(Cat_price,MATCH(J$79,Cat_code,0)) -> 2400000 | K90: =INDEX(Cat_price,MATCH(K$79,Cat_code,0)) -> 2400000 | L90: =INDEX(Cat_price,MATCH(L$79,Cat_code,0)) -> 2400000 | ... Y90: =INDEX(Cat_price,MATCH(Y$79,Cat_code,0)) -> 1800000
A91: price | B91: Цена в расчёте (с учётом k_цена) | C91: руб. | D91: [price0]*81 | E91: =E90*E$81 -> 2400000 | F91: =F90*F$81 -> 1920000 | G91: =G90*G$81 -> 2880000 | H91: =H90*H$81 -> 2400000 | I91: =I90*I$81 -> 2400000 | J91: =J90*J$81 -> 2400000 | K91: =K90*K$81 -> 2400000 | L91: =L90*L$81 -> 2400000 | ... Y91: =Y90*Y$81 -> 1800000
A92: cap | B92: Грузоподъёмность | C92: кг | D92: INDEX(Cat_cap,MATCH(79,Cat_code,0)) | E92: =INDEX(Cat_cap,MATCH(E$79,Cat_code,0)) -> 1200 | F92: =INDEX(Cat_cap,MATCH(F$79,Cat_code,0)) -> 1200 | G92: =INDEX(Cat_cap,MATCH(G$79,Cat_code,0)) -> 1200 | H92: =INDEX(Cat_cap,MATCH(H$79,Cat_code,0)) -> 1200 | I92: =INDEX(Cat_cap,MATCH(I$79,Cat_code,0)) -> 1200 | J92: =INDEX(Cat_cap,MATCH(J$79,Cat_code,0)) -> 1200 | K92: =INDEX(Cat_cap,MATCH(K$79,Cat_code,0)) -> 1200 | L92: =INDEX(Cat_cap,MATCH(L$79,Cat_code,0)) -> 1200 | ... Y92: =INDEX(Cat_cap,MATCH(Y$79,Cat_code,0)) -> 800
A93: vmax | B93: Максимальная скорость | C93: м/с | D93: INDEX(Cat_vmax,MATCH(79,Cat_code,0)) | E93: =INDEX(Cat_vmax,MATCH(E$79,Cat_code,0)) -> 1.5 | F93: =INDEX(Cat_vmax,MATCH(F$79,Cat_code,0)) -> 1.5 | G93: =INDEX(Cat_vmax,MATCH(G$79,Cat_code,0)) -> 1.5 | H93: =INDEX(Cat_vmax,MATCH(H$79,Cat_code,0)) -> 1.5 | I93: =INDEX(Cat_vmax,MATCH(I$79,Cat_code,0)) -> 1.5 | J93: =INDEX(Cat_vmax,MATCH(J$79,Cat_code,0)) -> 1.5 | K93: =INDEX(Cat_vmax,MATCH(K$79,Cat_code,0)) -> 1.5 | L93: =INDEX(Cat_vmax,MATCH(L$79,Cat_code,0)) -> 1.5 | ... Y93: =INDEX(Cat_vmax,MATCH(Y$79,Cat_code,0)) -> 1.5
A94: tload | B94: Время загрузки (сцепки/подхвата) | C94: с | D94: INDEX(Cat_tload,MATCH(79,Cat_code,0)) | E94: =INDEX(Cat_tload,MATCH(E$79,Cat_code,0)) -> 45 | F94: =INDEX(Cat_tload,MATCH(F$79,Cat_code,0)) -> 45 | G94: =INDEX(Cat_tload,MATCH(G$79,Cat_code,0)) -> 45 | H94: =INDEX(Cat_tload,MATCH(H$79,Cat_code,0)) -> 45 | I94: =INDEX(Cat_tload,MATCH(I$79,Cat_code,0)) -> 45 | J94: =INDEX(Cat_tload,MATCH(J$79,Cat_code,0)) -> 45 | K94: =INDEX(Cat_tload,MATCH(K$79,Cat_code,0)) -> 45 | L94: =INDEX(Cat_tload,MATCH(L$79,Cat_code,0)) -> 45 | ... Y94: =INDEX(Cat_tload,MATCH(Y$79,Cat_code,0)) -> 45
A95: tunload | B95: Время разгрузки | C95: с | D95: INDEX(Cat_tunload,MATCH(79,Cat_code,0)) | E95: =INDEX(Cat_tunload,MATCH(E$79,Cat_code,0)) -> 45 | F95: =INDEX(Cat_tunload,MATCH(F$79,Cat_code,0)) -> 45 | G95: =INDEX(Cat_tunload,MATCH(G$79,Cat_code,0)) -> 45 | H95: =INDEX(Cat_tunload,MATCH(H$79,Cat_code,0)) -> 45 | I95: =INDEX(Cat_tunload,MATCH(I$79,Cat_code,0)) -> 45 | J95: =INDEX(Cat_tunload,MATCH(J$79,Cat_code,0)) -> 45 | K95: =INDEX(Cat_tunload,MATCH(K$79,Cat_code,0)) -> 45 | L95: =INDEX(Cat_tunload,MATCH(L$79,Cat_code,0)) -> 45 | ... Y95: =INDEX(Cat_tunload,MATCH(Y$79,Cat_code,0)) -> 45
A96: power | B96: Средняя потребляемая мощность | C96: кВт | D96: INDEX(Cat_power,MATCH(79,Cat_code,0)) | E96: =INDEX(Cat_power,MATCH(E$79,Cat_code,0)) -> 1 | F96: =INDEX(Cat_power,MATCH(F$79,Cat_code,0)) -> 1 | G96: =INDEX(Cat_power,MATCH(G$79,Cat_code,0)) -> 1 | H96: =INDEX(Cat_power,MATCH(H$79,Cat_code,0)) -> 1 | I96: =INDEX(Cat_power,MATCH(I$79,Cat_code,0)) -> 1 | J96: =INDEX(Cat_power,MATCH(J$79,Cat_code,0)) -> 1 | K96: =INDEX(Cat_power,MATCH(K$79,Cat_code,0)) -> 1 | L96: =INDEX(Cat_power,MATCH(L$79,Cat_code,0)) -> 1 | ... Y96: =INDEX(Cat_power,MATCH(Y$79,Cat_code,0)) -> 1
A97: handling | B97: Способ обработки груза | D97: INDEX(Cat_handling,MATCH(79,Cat_code,0)) | E97: =INDEX(Cat_handling,MATCH(E$79,Cat_code,0)) -> платформа | F97: =INDEX(Cat_handling,MATCH(F$79,Cat_code,0)) -> платформа | G97: =INDEX(Cat_handling,MATCH(G$79,Cat_code,0)) -> платформа | H97: =INDEX(Cat_handling,MATCH(H$79,Cat_code,0)) -> платформа | I97: =INDEX(Cat_handling,MATCH(I$79,Cat_code,0)) -> платформа | J97: =INDEX(Cat_handling,MATCH(J$79,Cat_code,0)) -> платформа | K97: =INDEX(Cat_handling,MATCH(K$79,Cat_code,0)) -> платформа | L97: =INDEX(Cat_handling,MATCH(L$79,Cat_code,0)) -> платформа | ... Y97: =INDEX(Cat_handling,MATCH(Y$79,Cat_code,0)) -> платформа
A98: indoor | B98: Допуск в помещения | C98: 1/0 | D98: INDEX(Cat_indoor,MATCH(79,Cat_code,0)) | E98: =INDEX(Cat_indoor,MATCH(E$79,Cat_code,0)) -> 1 | F98: =INDEX(Cat_indoor,MATCH(F$79,Cat_code,0)) -> 1 | G98: =INDEX(Cat_indoor,MATCH(G$79,Cat_code,0)) -> 1 | H98: =INDEX(Cat_indoor,MATCH(H$79,Cat_code,0)) -> 1 | I98: =INDEX(Cat_indoor,MATCH(I$79,Cat_code,0)) -> 1 | J98: =INDEX(Cat_indoor,MATCH(J$79,Cat_code,0)) -> 1 | K98: =INDEX(Cat_indoor,MATCH(K$79,Cat_code,0)) -> 1 | L98: =INDEX(Cat_indoor,MATCH(L$79,Cat_code,0)) -> 1 | ... Y98: =INDEX(Cat_indoor,MATCH(Y$79,Cat_code,0)) -> 1
A99: task | B99: Класс задачи решения | D99: INDEX(Cat_task,MATCH(79,Cat_code,0)) | E99: =INDEX(Cat_task,MATCH(E$79,Cat_code,0)) -> транспорт | F99: =INDEX(Cat_task,MATCH(F$79,Cat_code,0)) -> транспорт | G99: =INDEX(Cat_task,MATCH(G$79,Cat_code,0)) -> транспорт | H99: =INDEX(Cat_task,MATCH(H$79,Cat_code,0)) -> транспорт | I99: =INDEX(Cat_task,MATCH(I$79,Cat_code,0)) -> транспорт | J99: =INDEX(Cat_task,MATCH(J$79,Cat_code,0)) -> транспорт | K99: =INDEX(Cat_task,MATCH(K$79,Cat_code,0)) -> транспорт | L99: =INDEX(Cat_task,MATCH(L$79,Cat_code,0)) -> транспорт | ... Y99: =INDEX(Cat_task,MATCH(Y$79,Cat_code,0)) -> транспорт
A100: repl | B100: Коэффициент замещения труда = по паре «задача × способ обработки» (блок 2) | C100: доля | D100: IF([handling]="вилы",Med_repl_forks,IF([handling]="платформа",Med_repl_platform,IF([handling]="буксировка",Med_repl_tow,IF([handling]="кузов",Med_repl_body,0)))) | E100: =IF(E97="вилы",Med_repl_forks,IF(E97="платформа",Med_repl_platform,IF(E97="буксировка",Med_repl_tow,IF(E97="кузов",Med_repl_body,0)))) -> 0.8 | F100: =IF(F97="вилы",Med_repl_forks,IF(F97="платформа",Med_repl_platform,IF(F97="буксировка",Med_repl_tow,IF(F97="кузов",Med_repl_body,0)))) -> 0.8 | G100: =IF(G97="вилы",Med_repl_forks,IF(G97="платформа",Med_repl_platform,IF(G97="буксировка",Med_repl_tow,IF(G97="кузов",Med_repl_body,0)))) -> 0.8 | H100: =IF(H97="вилы",Med_repl_forks,IF(H97="платформа",Med_repl_platform,IF(H97="буксировка",Med_repl_tow,IF(H97="кузов",Med_repl_body,0)))) -> 0.8 | I100: =IF(I97="вилы",Med_repl_forks,IF(I97="платформа",Med_repl_platform,IF(I97="буксировка",Med_repl_tow,IF(I97="кузов",Med_repl_body,0)))) -> 0.8 | J100: =IF(J97="вилы",Med_repl_forks,IF(J97="платформа",Med_repl_platform,IF(J97="буксировка",Med_repl_tow,IF(J97="кузов",Med_repl_body,0)))) -> 0.8 | K100: =IF(K97="вилы",Med_repl_forks,IF(K97="платформа",Med_repl_platform,IF(K97="буксировка",Med_repl_tow,IF(K97="кузов",Med_repl_body,0)))) -> 0.8 | L100: =IF(L97="вилы",Med_repl_forks,IF(L97="платформа",Med_repl_platform,IF(L97="буксировка",Med_repl_tow,IF(L97="кузов",Med_repl_body,0)))) -> 0.8 | ... Y100: =IF(Y97="вилы",Med_repl_forks,IF(Y97="платформа",Med_repl_platform,IF(Y97="буксировка",Med_repl_tow,IF(Y97="кузов",Med_repl_body,0)))) -> 0.8
A101: wid | B101: Ширина робота | C101: мм | D101: INDEX(Cat_wid,MATCH(79,Cat_code,0)) | E101: =INDEX(Cat_wid,MATCH(E$79,Cat_code,0)) -> 654 | F101: =INDEX(Cat_wid,MATCH(F$79,Cat_code,0)) -> 654 | G101: =INDEX(Cat_wid,MATCH(G$79,Cat_code,0)) -> 654 | H101: =INDEX(Cat_wid,MATCH(H$79,Cat_code,0)) -> 654 | I101: =INDEX(Cat_wid,MATCH(I$79,Cat_code,0)) -> 654 | J101: =INDEX(Cat_wid,MATCH(J$79,Cat_code,0)) -> 654 | K101: =INDEX(Cat_wid,MATCH(K$79,Cat_code,0)) -> 654 | L101: =INDEX(Cat_wid,MATCH(L$79,Cat_code,0)) -> 654 | ... Y101: =INDEX(Cat_wid,MATCH(Y$79,Cat_code,0)) -> 600
A102: tmin | B102: Допустимая минимальная температура | C102: °C | D102: INDEX(Cat_tmin,MATCH(79,Cat_code,0)) | E102: =INDEX(Cat_tmin,MATCH(E$79,Cat_code,0)) -> 5 | F102: =INDEX(Cat_tmin,MATCH(F$79,Cat_code,0)) -> 5 | G102: =INDEX(Cat_tmin,MATCH(G$79,Cat_code,0)) -> 5 | H102: =INDEX(Cat_tmin,MATCH(H$79,Cat_code,0)) -> 5 | I102: =INDEX(Cat_tmin,MATCH(I$79,Cat_code,0)) -> 5 | J102: =INDEX(Cat_tmin,MATCH(J$79,Cat_code,0)) -> 5 | K102: =INDEX(Cat_tmin,MATCH(K$79,Cat_code,0)) -> 5 | L102: =INDEX(Cat_tmin,MATCH(L$79,Cat_code,0)) -> 5 | ... Y102: =INDEX(Cat_tmin,MATCH(Y$79,Cat_code,0)) -> 5
A103: outdoor | B103: Уличная эксплуатация | C103: 1/0 | D103: INDEX(Cat_outdoor,MATCH(79,Cat_code,0)) | E103: =INDEX(Cat_outdoor,MATCH(E$79,Cat_code,0)) -> 0 | F103: =INDEX(Cat_outdoor,MATCH(F$79,Cat_code,0)) -> 0 | G103: =INDEX(Cat_outdoor,MATCH(G$79,Cat_code,0)) -> 0 | H103: =INDEX(Cat_outdoor,MATCH(H$79,Cat_code,0)) -> 0 | I103: =INDEX(Cat_outdoor,MATCH(I$79,Cat_code,0)) -> 0 | J103: =INDEX(Cat_outdoor,MATCH(J$79,Cat_code,0)) -> 0 | K103: =INDEX(Cat_outdoor,MATCH(K$79,Cat_code,0)) -> 0 | L103: =INDEX(Cat_outdoor,MATCH(L$79,Cat_code,0)) -> 0 | ... Y103: =INDEX(Cat_outdoor,MATCH(Y$79,Cat_code,0)) -> 0
B104: 3.2 Проверка применимости (ТЗ п.3.4.3: ключевое ограничение → решение не рекомендуется)
A105: chk_task | B105: Проверка класса задачи (транспорт / уборка) | D105: IF([task]=Med_task_class,"ОК","НЕТ") | E105: =IF(E99=Med_task_class,"ОК","НЕТ") -> ОК | F105: =IF(F99=Med_task_class,"ОК","НЕТ") -> ОК | G105: =IF(G99=Med_task_class,"ОК","НЕТ") -> ОК | H105: =IF(H99=Med_task_class,"ОК","НЕТ") -> ОК | I105: =IF(I99=Med_task_class,"ОК","НЕТ") -> ОК | J105: =IF(J99=Med_task_class,"ОК","НЕТ") -> ОК | K105: =IF(K99=Med_task_class,"ОК","НЕТ") -> ОК | L105: =IF(L99=Med_task_class,"ОК","НЕТ") -> ОК | ... Y105: =IF(Y99=Med_task_class,"ОК","НЕТ") -> ОК
A106: chk_handling | B106: Проверка способа обработки груза (в списке допустимых для задачи) | D106: IF(ISNUMBER(SEARCH([handling],Med_handling_req)),"ОК","НЕТ") | E106: =IF(ISNUMBER(SEARCH(E97,Med_handling_req)),"ОК","НЕТ") -> ОК | F106: =IF(ISNUMBER(SEARCH(F97,Med_handling_req)),"ОК","НЕТ") -> ОК | G106: =IF(ISNUMBER(SEARCH(G97,Med_handling_req)),"ОК","НЕТ") -> ОК | H106: =IF(ISNUMBER(SEARCH(H97,Med_handling_req)),"ОК","НЕТ") -> ОК | I106: =IF(ISNUMBER(SEARCH(I97,Med_handling_req)),"ОК","НЕТ") -> ОК | J106: =IF(ISNUMBER(SEARCH(J97,Med_handling_req)),"ОК","НЕТ") -> ОК | K106: =IF(ISNUMBER(SEARCH(K97,Med_handling_req)),"ОК","НЕТ") -> ОК | L106: =IF(ISNUMBER(SEARCH(L97,Med_handling_req)),"ОК","НЕТ") -> ОК | ... Y106: =IF(ISNUMBER(SEARCH(Y97,Med_handling_req)),"ОК","НЕТ") -> ОК
A107: chk_indoor | B107: Проверка допуска в помещения | D107: IF(AND(Med_indoor_req=1,[indoor]=0),"НЕТ","ОК") | E107: =IF(AND(Med_indoor_req=1,E98=0),"НЕТ","ОК") -> ОК | F107: =IF(AND(Med_indoor_req=1,F98=0),"НЕТ","ОК") -> ОК | G107: =IF(AND(Med_indoor_req=1,G98=0),"НЕТ","ОК") -> ОК | H107: =IF(AND(Med_indoor_req=1,H98=0),"НЕТ","ОК") -> ОК | I107: =IF(AND(Med_indoor_req=1,I98=0),"НЕТ","ОК") -> ОК | J107: =IF(AND(Med_indoor_req=1,J98=0),"НЕТ","ОК") -> ОК | K107: =IF(AND(Med_indoor_req=1,K98=0),"НЕТ","ОК") -> ОК | L107: =IF(AND(Med_indoor_req=1,L98=0),"НЕТ","ОК") -> ОК | ... Y107: =IF(AND(Med_indoor_req=1,Y98=0),"НЕТ","ОК") -> ОК
A108: chk_cap | B108: Проверка грузоподъёмности (неделимый груз: кап. ≥ масса единицы) | D108: IF(AND(Med_divisible=0,[cap]<Med_unit_mass),"НЕТ","ОК") | E108: =IF(AND(Med_divisible=0,E92<Med_unit_mass),"НЕТ","ОК") -> ОК | F108: =IF(AND(Med_divisible=0,F92<Med_unit_mass),"НЕТ","ОК") -> ОК | G108: =IF(AND(Med_divisible=0,G92<Med_unit_mass),"НЕТ","ОК") -> ОК | H108: =IF(AND(Med_divisible=0,H92<Med_unit_mass),"НЕТ","ОК") -> ОК | I108: =IF(AND(Med_divisible=0,I92<Med_unit_mass),"НЕТ","ОК") -> ОК | J108: =IF(AND(Med_divisible=0,J92<Med_unit_mass),"НЕТ","ОК") -> ОК | K108: =IF(AND(Med_divisible=0,K92<Med_unit_mass),"НЕТ","ОК") -> ОК | L108: =IF(AND(Med_divisible=0,L92<Med_unit_mass),"НЕТ","ОК") -> ОК | ... Y108: =IF(AND(Med_divisible=0,Y92<Med_unit_mass),"НЕТ","ОК") -> ОК
A109: chk_aisle | B109: Проверка проезда (ширина робота + запас ≤ мин. ширина прохода) | D109: IF([wid]/1000+Med_clearance<=Med_aisle,"ОК","НЕТ") | E109: =IF(E101/1000+Med_clearance<=Med_aisle,"ОК","НЕТ") -> ОК | F109: =IF(F101/1000+Med_clearance<=Med_aisle,"ОК","НЕТ") -> ОК | G109: =IF(G101/1000+Med_clearance<=Med_aisle,"ОК","НЕТ") -> ОК | H109: =IF(H101/1000+Med_clearance<=Med_aisle,"ОК","НЕТ") -> ОК | I109: =IF(I101/1000+Med_clearance<=Med_aisle,"ОК","НЕТ") -> ОК | J109: =IF(J101/1000+Med_clearance<=Med_aisle,"ОК","НЕТ") -> ОК | K109: =IF(K101/1000+Med_clearance<=Med_aisle,"ОК","НЕТ") -> ОК | L109: =IF(L101/1000+Med_clearance<=Med_aisle,"ОК","НЕТ") -> ОК | ... Y109: =IF(Y101/1000+Med_clearance<=Med_aisle,"ОК","НЕТ") -> ОК
A110: chk_env | B110: Проверка условий эксплуатации (улица / мин. температура) | D110: IF(Med_outdoor_req=1,IF(AND([outdoor]=1,[tmin]<=Med_temp_min),"ОК","НЕТ"),"ОК") | E110: =IF(Med_outdoor_req=1,IF(AND(E103=1,E102<=Med_temp_min),"ОК","НЕТ"),"ОК") -> ОК | F110: =IF(Med_outdoor_req=1,IF(AND(F103=1,F102<=Med_temp_min),"ОК","НЕТ"),"ОК") -> ОК | G110: =IF(Med_outdoor_req=1,IF(AND(G103=1,G102<=Med_temp_min),"ОК","НЕТ"),"ОК") -> ОК | H110: =IF(Med_outdoor_req=1,IF(AND(H103=1,H102<=Med_temp_min),"ОК","НЕТ"),"ОК") -> ОК | I110: =IF(Med_outdoor_req=1,IF(AND(I103=1,I102<=Med_temp_min),"ОК","НЕТ"),"ОК") -> ОК | J110: =IF(Med_outdoor_req=1,IF(AND(J103=1,J102<=Med_temp_min),"ОК","НЕТ"),"ОК") -> ОК | K110: =IF(Med_outdoor_req=1,IF(AND(K103=1,K102<=Med_temp_min),"ОК","НЕТ"),"ОК") -> ОК | L110: =IF(Med_outdoor_req=1,IF(AND(L103=1,L102<=Med_temp_min),"ОК","НЕТ"),"ОК") -> ОК | ... Y110: =IF(Med_outdoor_req=1,IF(AND(Y103=1,Y102<=Med_temp_min),"ОК","НЕТ"),"ОК") -> ОК
A111: feasible | B111: Решение применимо (1/0) | C111: 1/0 | D111: IF(AND([chk_task]="ОК",[chk_handling]="ОК",[chk_indoor]="ОК",[chk_cap]="ОК",[chk_aisle]="ОК",[chk_env]="ОК"),1,0) | E111: =IF(AND(E105="ОК",E106="ОК",E107="ОК",E108="ОК",E109="ОК",E110="ОК"),1,0) -> 1 | F111: =IF(AND(F105="ОК",F106="ОК",F107="ОК",F108="ОК",F109="ОК",F110="ОК"),1,0) -> 1 | G111: =IF(AND(G105="ОК",G106="ОК",G107="ОК",G108="ОК",G109="ОК",G110="ОК"),1,0) -> 1 | H111: =IF(AND(H105="ОК",H106="ОК",H107="ОК",H108="ОК",H109="ОК",H110="ОК"),1,0) -> 1 | I111: =IF(AND(I105="ОК",I106="ОК",I107="ОК",I108="ОК",I109="ОК",I110="ОК"),1,0) -> 1 | J111: =IF(AND(J105="ОК",J106="ОК",J107="ОК",J108="ОК",J109="ОК",J110="ОК"),1,0) -> 1 | K111: =IF(AND(K105="ОК",K106="ОК",K107="ОК",K108="ОК",K109="ОК",K110="ОК"),1,0) -> 1 | L111: =IF(AND(L105="ОК",L106="ОК",L107="ОК",L108="ОК",L109="ОК",L110="ОК"),1,0) -> 1 | ... Y111: =IF(AND(Y105="ОК",Y106="ОК",Y107="ОК",Y108="ОК",Y109="ОК",Y110="ОК"),1,0) -> 1
A112: feas_text | B112: Причина включения / исключения | D112: IF([feasible]=1,"Применимо: все ключевые ограничения выполнены","Не применимо: "&IF([chk_task]="НЕТ","класс задачи; ","")&IF([chk_handling]="НЕТ","способ обработки груза; ","")&IF([chk_indoor]="НЕТ","не допущен в помещения; ","")&IF([chk_cap]="НЕТ","грузоподъёмность ниже массы единицы груза; ","")&IF([chk_aisle]="НЕТ","габариты не проходят по ширине прохода; ","")&IF([chk_env]="НЕТ","не сертифицирован для условий эксплуатации; ","")) | E112: =IF(E111=1,"Применимо: все ключевые ограничения выполнены","Не применимо: "&IF(E105="НЕТ","класс задачи; ","")&IF(E106="НЕТ","способ обработки груза; ","")&IF(E107="НЕТ","не допущен в помещения; ","")&IF(E108="НЕТ","грузоподъёмность ниже массы единицы груза; ","")&IF(E109="НЕТ","габариты не проходят по ширине прохода; ","")&IF(E110="НЕТ","не сертифицирован для условий эксплуатации; ","")) -> Применимо: все ключевые ограничения выполнены | F112: =IF(F111=1,"Применимо: все ключевые ограничения выполнены","Не применимо: "&IF(F105="НЕТ","класс задачи; ","")&IF(F106="НЕТ","способ обработки груза; ","")&IF(F107="НЕТ","не допущен в помещения; ","")&IF(F108="НЕТ","грузоподъёмность ниже массы единицы груза; ","")&IF(F109="НЕТ","габариты не проходят по ширине прохода; ","")&IF(F110="НЕТ","не сертифицирован для условий эксплуатации; ","")) -> Применимо: все ключевые ограничения выполнены | G112: =IF(G111=1,"Применимо: все ключевые ограничения выполнены","Не применимо: "&IF(G105="НЕТ","класс задачи; ","")&IF(G106="НЕТ","способ обработки груза; ","")&IF(G107="НЕТ","не допущен в помещения; ","")&IF(G108="НЕТ","грузоподъёмность ниже массы единицы груза; ","")&IF(G109="НЕТ","габариты не проходят по ширине прохода; ","")&IF(G110="НЕТ","не сертифицирован для условий эксплуатации; ","")) -> Применимо: все ключевые ограничения выполнены | H112: =IF(H111=1,"Применимо: все ключевые ограничения выполнены","Не применимо: "&IF(H105="НЕТ","класс задачи; ","")&IF(H106="НЕТ","способ обработки груза; ","")&IF(H107="НЕТ","не допущен в помещения; ","")&IF(H108="НЕТ","грузоподъёмность ниже массы единицы груза; ","")&IF(H109="НЕТ","габариты не проходят по ширине прохода; ","")&IF(H110="НЕТ","не сертифицирован для условий эксплуатации; ","")) -> Применимо: все ключевые ограничения выполнены | I112: =IF(I111=1,"Применимо: все ключевые ограничения выполнены","Не применимо: "&IF(I105="НЕТ","класс задачи; ","")&IF(I106="НЕТ","способ обработки груза; ","")&IF(I107="НЕТ","не допущен в помещения; ","")&IF(I108="НЕТ","грузоподъёмность ниже массы единицы груза; ","")&IF(I109="НЕТ","габариты не проходят по ширине прохода; ","")&IF(I110="НЕТ","не сертифицирован для условий эксплуатации; ","")) -> Применимо: все ключевые ограничения выполнены | J112: =IF(J111=1,"Применимо: все ключевые ограничения выполнены","Не применимо: "&IF(J105="НЕТ","класс задачи; ","")&IF(J106="НЕТ","способ обработки груза; ","")&IF(J107="НЕТ","не допущен в помещения; ","")&IF(J108="НЕТ","грузоподъёмность ниже массы единицы груза; ","")&IF(J109="НЕТ","габариты не проходят по ширине прохода; ","")&IF(J110="НЕТ","не сертифицирован для условий эксплуатации; ","")) -> Применимо: все ключевые ограничения выполнены | K112: =IF(K111=1,"Применимо: все ключевые ограничения выполнены","Не применимо: "&IF(K105="НЕТ","класс задачи; ","")&IF(K106="НЕТ","способ обработки груза; ","")&IF(K107="НЕТ","не допущен в помещения; ","")&IF(K108="НЕТ","грузоподъёмность ниже массы единицы груза; ","")&IF(K109="НЕТ","габариты не проходят по ширине прохода; ","")&IF(K110="НЕТ","не сертифицирован для условий эксплуатации; ","")) -> Применимо: все ключевые ограничения выполнены | L112: =IF(L111=1,"Применимо: все ключевые ограничения выполнены","Не применимо: "&IF(L105="НЕТ","класс задачи; ","")&IF(L106="НЕТ","способ обработки груза; ","")&IF(L107="НЕТ","не допущен в помещения; ","")&IF(L108="НЕТ","грузоподъёмность ниже массы единицы груза; ","")&IF(L109="НЕТ","габариты не проходят по ширине прохода; ","")&IF(L110="НЕТ","не сертифицирован для условий эксплуатации; ","")) -> Применимо: все ключевые ограничения выполнены | ... Y112: =IF(Y111=1,"Применимо: все ключевые ограничения выполнены","Не применимо: "&IF(Y105="НЕТ","класс задачи; ","")&IF(Y106="НЕТ","способ обработки груза; ","")&IF(Y107="НЕТ","не допущен в помещения; ","")&IF(Y108="НЕТ","грузоподъёмность ниже массы единицы груза; ","")&IF(Y109="НЕТ","габариты не проходят по ширине прохода; ","")&IF(Y110="НЕТ","не сертифицирован для условий эксплуатации; ","")) -> Применимо: все ключевые ограничения выполнены
B113: 3.3 Потребность в операциях (ТЗ п.3.5.2: пиковая потребность)
A114: ops_day | B114: Объём операций процесса в сутки (с учётом k_объём) | C114: оп./сут | D114: Med_ops_day*82 | E114: =Med_ops_day*E$82 -> 279.8 | F114: =Med_ops_day*F$82 -> 279.8 | G114: =Med_ops_day*G$82 -> 279.8 | H114: =Med_ops_day*H$82 -> 223.84 | I114: =Med_ops_day*I$82 -> 335.76 | J114: =Med_ops_day*J$82 -> 279.8 | K114: =Med_ops_day*K$82 -> 279.8 | L114: =Med_ops_day*L$82 -> 279.8 | ... Y114: =Med_ops_day*Y$82 -> 279.8
A115: ops_auto | B115: Из них автоматизируемых (× доля автоматизируемых операций) | C115: оп./сут | D115: [ops_day]*Med_auto_share | E115: =E114*Med_auto_share -> 251.82 | F115: =F114*Med_auto_share -> 251.82 | G115: =G114*Med_auto_share -> 251.82 | H115: =H114*Med_auto_share -> 201.456 | I115: =I114*Med_auto_share -> 302.184 | J115: =J114*Med_auto_share -> 251.82 | K115: =K114*Med_auto_share -> 251.82 | L115: =L114*Med_auto_share -> 251.82 | ... Y115: =Y114*Med_auto_share -> 251.82
A116: trips_per_op | B116: Рейсов робота на 1 операцию (делимый груз: округление вверх массы/грузоподъёмность) | C116: рейсов | D116: IF(Med_divisible=1,ROUNDUP(Med_unit_mass/MAX([cap],1),0),1) | E116: =IF(Med_divisible=1,ROUNDUP(Med_unit_mass/MAX(E92,1),0),1) -> 1 | F116: =IF(Med_divisible=1,ROUNDUP(Med_unit_mass/MAX(F92,1),0),1) -> 1 | G116: =IF(Med_divisible=1,ROUNDUP(Med_unit_mass/MAX(G92,1),0),1) -> 1 | H116: =IF(Med_divisible=1,ROUNDUP(Med_unit_mass/MAX(H92,1),0),1) -> 1 | I116: =IF(Med_divisible=1,ROUNDUP(Med_unit_mass/MAX(I92,1),0),1) -> 1 | J116: =IF(Med_divisible=1,ROUNDUP(Med_unit_mass/MAX(J92,1),0),1) -> 1 | K116: =IF(Med_divisible=1,ROUNDUP(Med_unit_mass/MAX(K92,1),0),1) -> 1 | L116: =IF(Med_divisible=1,ROUNDUP(Med_unit_mass/MAX(L92,1),0),1) -> 1 | ... Y116: =IF(Med_divisible=1,ROUNDUP(Med_unit_mass/MAX(Y92,1),0),1) -> 1
...

Sheet Сравнение
A1: СВОДНЫЙ ДАШБОРД: три типа объектов × сценарии (значения подтягиваются с листов объектов)
A3: Объект | B3: Сценарий | C3: Решение | D3: Роботов | E3: CAPEX, руб. | F3: OPEX процесса, руб./год | G3: Чистый годовой эффект, руб./год | H3: Окупаемость, лет | I3: ROI за горизонт | J3: NPV, руб. | K3: TCO решения, руб. | L3: Интерпретация | M3: Риски
A4: Склад | B4: База (без роботизации) | C4: — | D4: 0 | E4: 0 | F4: =Склад!D180 -> 46872000
A5: Склад | B5: Покупка A | C5: =Склад!E173 -> Ronavi H1500 (AMR, до 1500 кг) | D5: =Склад!E176 -> 12 | E5: =Склад!E178 -> 46339150 | F5: =Склад!E180 -> 31382572 | G5: =Склад!E184 -> 15489428 | H5: =Склад!E186 -> 2.9916631 | I5: =Склад!E187 -> 1.6013919 | J5: =Склад!E206 -> 10165005 | K5: =Склад!E188 -> 89312010 | L5: =Склад!E190 -> Средняя целесообразность (2–4 лет) — рекомендован пилот | M5: =Склад!E191
A6: Склад | B6: RaaS A | C6: =Склад!F173 -> DMR Carrier P (FMR, вилочный AMR) | D6: =Склад!F176 -> 15 | E6: =Склад!F178 -> 10643050 | F6: =Склад!F180 -> 43675570 | G6: =Склад!F184 -> 3196430 | H6: =Склад!F186 -> 3.3296678 | I6: =Склад!F187 -> 1.5016513 | J6: =Склад!H206 -> 1473934.6 | K6: =Склад!F188 -> 111840900 | L6: =Склад!F190 -> Средняя целесообразность (2–4 лет) — рекомендован пилот | M6: =Склад!F191 -> Зрелость: статус «piloting»; ТТХ требуют подтверждения;
A7: Склад | B7: Покупка B | C7: =Склад!G173 -> Ronavi H1500 (AMR, до 1500 кг) | D7: =Склад!G176 -> 12 | E7: =Склад!G178 -> 46339150 | F7: =Склад!G180 -> 54818572 | G7: =Склад!G184 -> -7946572 | H7: =Склад!G186 -> не окупается | I7: =Склад!G187 -> -0.92735538 | J7: =Склад!K206 -> -78675874 | K7: =Склад!G188 -> 89312010 | L7: =Склад!G190 -> Не окупается: годовой эффект ≤ 0 | M7: =Склад!G191
A9: Аэропорт | B9: База (без роботизации) | C9: — | D9: 0 | E9: 0 | F9: =Аэропорт!D180 -> 99993600
A10: Аэропорт | B10: Покупка A | C10: =Аэропорт!E173 -> Беспилотный тягач (Cognitive Pilot) | D10: =Аэропорт!E176 -> 17 | E10: =Аэропорт!E178 -> 104290450 | F10: =Аэропорт!E180 -> 40836012 | G10: =Аэропорт!E184 -> 60770388 | H10: =Аэропорт!E186 -> 1.7161393 | I10: =Аэропорт!E187 -> 4.0137205 | J10: =Аэропорт!E206 -> 1.8692076e+08 | K10: =Аэропорт!E188 -> 200955078 | L10: =Аэропорт!E190 -> Высокая целесообразность (окупаемость до 2 лет) | M10: =Аэропорт!E191 -> низкая среднесуточная загрузка парка (парк рассчитан на пик) — рассмотреть частичную роботизацию или RaaS;
A11: Аэропорт | B11: RaaS A | C11: =Аэропорт!F173 -> Беспилотный тягач (Cognitive Pilot) | D11: =Аэропорт!F176 -> 17 | E11: =Аэропорт!F178 -> 18260550 | F11: =Аэропорт!F180 -> 50356012 | G11: =Аэропорт!F184 -> 51250388 | H11: =Аэропорт!F186 -> 0.35630072 | I11: =Аэропорт!F187 -> 19.646326 | J11: =Аэропорт!H206 -> 2.312478e+08 | K11: =Аэропорт!F188 -> 174765178 | L11: =Аэропорт!F190 -> Высокая целесообразность (окупаемость до 2 лет) | M11: =Аэропорт!F191 -> низкая среднесуточная загрузка парка (парк рассчитан на пик) — рассмотреть частичную роботизацию или RaaS;
A12: Аэропорт | B12: Покупка B | C12: =Аэропорт!G173 -> EVOCARGO N1 (беспилотный электрогрузовик) | D12: =Аэропорт!G176 -> 39 | E12: =Аэропорт!G178 -> 350812550 | F12: =Аэропорт!G180 -> 57667276 | G12: =Аэропорт!G184 -> 43939124 | H12: =Аэропорт!G186 -> 7.9840588 | I12: =Аэропорт!G187 -> 0.81004476 | J12: =Аэропорт!K206 -> -1.5288101e+08 | K12: =Аэропорт!G188 -> 581896026 | L12: =Аэропорт!G190 -> Низкая целесообразность (более 4 лет) — требует уточнения данных | M12: =Аэропорт!G191 -> CAPEX выше планового бюджета; низкая среднесуточная загрузка парка (парк рассчитан на пик) — рассмотреть частичную роботизацию или RaaS;
A14: Медучреждение | B14: База (без роботизации) | C14: — | D14: 0 | E14: 0 | F14: =Медучреждение!D196 -> 42486343
A15: Медучреждение | B15: Покупка A | C15: =Медучреждение!E189 -> Ronavi M (AMR для стеллажей/тележек, до 1200 кг) | D15: =Медучреждение!E192 -> 9 | E15: =Медучреждение!E194 -> 36020050 | F15: =Медучреждение!E196 -> 18077638 | G15: =Медучреждение!E200 -> 25297923 | H15: =Медучреждение!E202 -> 1.4238343 | I15: =Медучреждение!E203 -> 4.8563359 | J15: =Медучреждение!E222 -> 85665526 | K15: =Медучреждение!E204 -> 81450284 | L15: =Медучреждение!E206 -> Высокая целесообразность (окупаемость до 2 лет) | M15: =Медучреждение!E207 -> Зрелость: статус «piloting»; ТТХ требуют подтверждения; CAPEX выше планового бюджета;
A16: Медучреждение | B16: RaaS A | C16: =Медучреждение!F189 -> Ronavi M (AMR для стеллажей/тележек, до 1200 кг) | D16: =Медучреждение!F192 -> 9 | E16: =Медучреждение!F194 -> 8690550 | F16: =Медучреждение!F196 -> 21101638 | G16: =Медучреждение!F200 -> 22273923 | H16: =Медучреждение!F202 -> 0.39016701 | I16: =Медучреждение!F203 -> 17.941035 | J16: =Медучреждение!H222 -> 99748236 | K16: =Медучреждение!F204 -> 73128784 | L16: =Медучреждение!F206 -> Высокая целесообразность (окупаемость до 2 лет) | M16: =Медучреждение!F207 -> Зрелость: статус «piloting»; ТТХ требуют подтверждения;
A17: Медучреждение | B17: Покупка B | C17: =Медучреждение!G189 -> AMR 800 (Морос, до 800 кг) | D17: =Медучреждение!G192 -> 9 | E17: =Медучреждение!G194 -> 27704050 | F17: =Медучреждение!G196 -> 17537638 | G17: =Медучреждение!G200 -> 25837923 | H17: =Медучреждение!G202 -> 1.0722243 | I17: =Медучреждение!G203 -> 6.4700093 | J17: =Медучреждение!K222 -> 96979299 | K17: =Медучреждение!G204 -> 68814284 | L17: =Медучреждение!G206 -> Высокая целесообразность (окупаемость до 2 лет) | M17: =Медучреждение!G207 -> ТТХ требуют подтверждения;
A20: Все результаты — предварительная оценка (экспресс-предынвестиционная); требуют верификации при обследовании объекта (ТЗ п.3.7.5). Все формулы, единицы измерения, источники и допущения доступны на листах объектов и «Нормативы» (ТЗ п.3.5.8).
